Workbook

Sheet Hoja1
A1: CODI | B1: #id user | C1: Swipe Date | D1: Amount | E1: MONEDA | F1: User | G1: Descriptor | H1: Merchant Name | I1: Expense Type | J1: DESCRIPCION DEL CARGO | K1: FOLIO DE FACTURA | L1: Cuenta contable | M1: Cargo | N1: Descripcion
A2: {=_xlfn._xlws.FILTER(_xlfn.VSTACK('#16 Rogelio:#88 Rene Granados'!A12:K206),_xlfn.VSTACK('#16 Rogelio:#88 Rene Granados'!A12:A206)<>0)} -> TRX1294 | B2: #16 | C2: 46055.417 | D2: 363.15 | E2: USD | F2: Rogelio Gamez | G2: OPENAI *CHATGPT SUBSCR SAN FRANCISCO USA | H2: Openai | I2: Tech&Product | J2: 0 | K2: 0 | L2: =VLOOKUP(B2,[1]Total!$B:$Q,16,0) -> 603.81.004 Gastos de Oficina | M2: =D2 -> 363.15 | N2: =CONCATENATE(F2," ",G2," ",H2," ",I2," ",J2," ",K2," ") -> Rogelio Gamez OPENAI *CHATGPT SUBSCR SAN FRANCISCO USA Openai Tech&Product 0 0
A3: TRX1233 | B3: #16 | C3: 46058.417 | D3: 6615.11 | E3: MXN | F3: Rogelio Gamez | G3: PAYU *GOOGLE ADS MIGUEL HIDALG MEX | H3: Google | I3: Sales | J3: Marketing | K3: 0 | L3: 603.38.002 | M3: =D3 -> 6615.11 | N3: =CONCATENATE(F3," ",G3," ",H3," ",I3," ",J3," ",K3," ") -> Rogelio Gamez PAYU *GOOGLE ADS MIGUEL HIDALG MEX Google Sales Marketing 0
A4: TRX1185 | B4: #16 | C4: 46059.417 | D4: 696.88 | E4: MXN | F4: Rogelio Gamez | G4: Amazon Mexico CMX MEX | H4: Amazon | I4: Office expenses | J4: 0 | K4: 0 | L4: =VLOOKUP(B4,[1]Total!$B:$Q,16,0) -> 603.81.004 Gastos de Oficina | M4: =D4 -> 696.88 | N4: =CONCATENATE(F4," ",G4," ",H4," ",I4," ",J4," ",K4," ") -> Rogelio Gamez Amazon Mexico CMX MEX Amazon Office expenses 0 0
A5: TRX1184 | B5: #16 | C5: 46059.417 | D5: 903.99 | E5: MXN | F5: Rogelio Gamez | G5: Amazon Mexico CMX MEX | H5: Amazon | I5: Office expenses | J5: 0 | K5: 0 | L5: =VLOOKUP(B5,[1]Total!$B:$Q,16,0) -> 603.81.004 Gastos de Oficina | M5: =D5 -> 903.99 | N5: =CONCATENATE(F5," ",G5," ",H5," ",I5," ",J5," ",K5," ") -> Rogelio Gamez Amazon Mexico CMX MEX Amazon Office expenses 0 0
A6: TRX1179 | B6: #16 | C6: 46059.417 | D6: 647.17 | E6: MXN | F6: Rogelio Gamez | G6: Amazon Mexico CMX MEX | H6: Amazon | I6: Tech&Product | J6: 0 | K6: 0 | L6: =VLOOKUP(B6,[1]Total!$B:$Q,16,0) -> 603.81.004 Gastos de Oficina | M6: =D6 -> 647.17 | N6: =CONCATENATE(F6," ",G6," ",H6," ",I6," ",J6," ",K6," ") -> Rogelio Gamez Amazon Mexico CMX MEX Amazon Tech&Product 0 0
A7: TRX1177 | B7: #16 | C7: 46059.417 | D7: 620.01 | E7: MXN | F7: Rogelio Gamez | G7: Amazon Mexico CMX MEX | H7: Amazon | I7: Office expenses | J7: 0 | K7: 0 | L7: =VLOOKUP(B7,[1]Total!$B:$Q,16,0) -> 603.81.004 Gastos de Oficina | M7: =D7 -> 620.01 | N7: =CONCATENATE(F7," ",G7," ",H7," ",I7," ",J7," ",K7," ") -> Rogelio Gamez Amazon Mexico CMX MEX Amazon Office expenses 0 0
A8: TRX1170 | B8: #16 | C8: 46059.417 | D8: 4420 | E8: MXN | F8: Rogelio Gamez | G8: MERCADOPAGO *FIERCEMX Ciudad de Mex MEX | H8: Mercadopago | I8: Office expenses | J8: 0 | K8: 0 | L8: =VLOOKUP(B8,[1]Total!$B:$Q,16,0) -> 603.81.004 Gastos de Oficina | M8: =D8 -> 4420 | N8: =CONCATENATE(F8," ",G8," ",H8," ",I8," ",J8," ",K8," ") -> Rogelio Gamez MERCADOPAGO *FIERCEMX Ciudad de Mex MEX Mercadopago Office expenses 0 0
A9: TRX1157 | B9: #16 | C9: 46059.417 | D9: 8990 | E9: MXN | F9: Rogelio Gamez | G9: STR*SYNTAGE CIUDAD DE MEX MEX | H9: Str Syntage Ciudad De Mex Mex | I9: Office expenses | J9: 0 | K9: 0 | L9: =VLOOKUP(B9,[1]Total!$B:$Q,16,0) -> 603.81.004 Gastos de Oficina | M9: =D9 -> 8990 | N9: =CONCATENATE(F9," ",G9," ",H9," ",I9," ",J9," ",K9," ") -> Rogelio Gamez STR*SYNTAGE CIUDAD DE MEX MEX Str Syntage Ciudad De Mex Mex Office expenses 0 0
A10: TRX1541 | B10: #16 | C10: 46061.417 | D10: 17401.35 | E10: USD | F10: Rogelio Gamez | G10: NOTION LABS, INC. SAN FRANCISCO USA | H10: Notion | I10: Office expenses | J10: 0 | K10: 0 | L10: =VLOOKUP(B10,[1]Total!$B:$Q,16,0) -> 603.81.004 Gastos de Oficina | M10: =D10 -> 17401.35 | N10: =CONCATENATE(F10," ",G10," ",H10," ",I10," ",J10," ",K10," ") -> Rogelio Gamez NOTION LABS, INC. SAN FRANCISCO USA Notion Office expenses 0 0
A11: TRX1648 | B11: #16 | C11: 46061.417 | D11: 151306.79 | E11: USD | F11: Rogelio Gamez | G11: Amazon web services SEATTLE USA | H11: Amazon Web Services | I11: Sales | J11: Marketing | K11: 0 | L11: 603.38.002 | M11: =D11 -> 151306.79 | N11: =CONCATENATE(F11," ",G11," ",H11," ",I11," ",J11," ",K11," ") -> Rogelio Gamez Amazon web services SEATTLE USA Amazon Web Services Sales Marketing 0
A12: TRX1277 | B12: #16 | C12: 46062.417 | D12: 39 | E12: MXN | F12: Rogelio Gamez | G12: OFFICE DEPOT STAM TLANEPANTLA E MEX | H12: Office Depot | I12: Office expenses | J12: 0 | K12: 0 | L12: =VLOOKUP(B12,[1]Total!$B:$Q,16,0) -> 603.81.004 Gastos de Oficina | M12: =D12 -> 39 | N12: =CONCATENATE(F12," ",G12," ",H12," ",I12," ",J12," ",K12," ") -> Rogelio Gamez OFFICE DEPOT STAM TLANEPANTLA E MEX Office Depot Office expenses 0 0
A13: TRX1426 | B13: #16 | C13: 46064.417 | D13: 259.94 | E13: MXN | F13: Rogelio Gamez | G13: UBER * PENDING CMX MEX | H13: Uber | I13: G&A expenses | J13: 0 | K13: 0 | L13: =VLOOKUP(B13,[1]Total!$B:$Q,16,0) -> 603.81.004 Gastos de Oficina | M13: =D13 -> 259.94 | N13: =CONCATENATE(F13," ",G13," ",H13," ",I13," ",J13," ",K13," ") -> Rogelio Gamez UBER * PENDING CMX MEX Uber G&A expenses 0 0
A14: TRX1453 | B14: #16 | C14: 46065.417 | D14: 179 | E14: MXN | F14: Rogelio Gamez | G14: Amazon Mexico CMX MEX | H14: Amazon | I14: Office expenses | J14: 0 | K14: 0 | L14: =VLOOKUP(B14,[1]Total!$B:$Q,16,0) -> 603.81.004 Gastos de Oficina | M14: =D14 -> 179 | N14: =CONCATENATE(F14," ",G14," ",H14," ",I14," ",J14," ",K14," ") -> Rogelio Gamez Amazon Mexico CMX MEX Amazon Office expenses 0 0
A15: TRX1331 | B15: #16 | C15: 46065.417 | D15: 939.94 | E15: MXN | F15: Rogelio Gamez | G15: Amazon Mexico CMX MEX | H15: Amazon | I15: G&A expenses | J15: 0 | K15: 0 | L15: =VLOOKUP(B15,[1]Total!$B:$Q,16,0) -> 603.81.004 Gastos de Oficina | M15: =D15 -> 939.94 | N15: =CONCATENATE(F15," ",G15," ",H15," ",I15," ",J15," ",K15," ") -> Rogelio Gamez Amazon Mexico CMX MEX Amazon G&A expenses 0 0
A16: TRX1926 | B16: #16 | C16: 46065.417 | D16: 499.72 | E16: MXN | F16: Rogelio Gamez | G16: Amazon Mexico CMX MEX | H16: Amazon | I16: Tech&Product | J16: 0 | K16: 0 | L16: =VLOOKUP(B16,[1]Total!$B:$Q,16,0) -> 603.81.004 Gastos de Oficina | M16: =D16 -> 499.72 | N16: =CONCATENATE(F16," ",G16," ",H16," ",I16," ",J16," ",K16," ") -> Rogelio Gamez Amazon Mexico CMX MEX Amazon Tech&Product 0 0
A17: TRX1345 | B17: #16 | C17: 46065.417 | D17: 299.99 | E17: MXN | F17: Rogelio Gamez | G17: Amazon Mexico CMX MEX | H17: Amazon | I17: Office expenses | J17: 0 | K17: 0 | L17: =VLOOKUP(B17,[1]Total!$B:$Q,16,0) -> 603.81.004 Gastos de Oficina | M17: =D17 -> 299.99 | N17: =CONCATENATE(F17," ",G17," ",H17," ",I17," ",J17," ",K17," ") -> Rogelio Gamez Amazon Mexico CMX MEX Amazon Office expenses 0 0
A18: TRX1338 | B18: #16 | C18: 46065.417 | D18: 10000 | E18: MXN | F18: Rogelio Gamez | G18: PAYU *GOOGLE ADS MIGUEL HIDALG MEX | H18: Google | I18: Tech&Product | J18: 0 | K18: 0 | L18: =VLOOKUP(B18,[1]Total!$B:$Q,16,0) -> 603.81.004 Gastos de Oficina | M18: =D18 -> 10000 | N18: =CONCATENATE(F18," ",G18," ",H18," ",I18," ",J18," ",K18," ") -> Rogelio Gamez PAYU *GOOGLE ADS MIGUEL HIDALG MEX Google Tech&Product 0 0
A19: TRX1265 | B19: #16 | C19: 46065.417 | D19: 0.86 | E19: MXN | F19: Rogelio Gamez | G19: 20260211T04:49:55/Amazon Mexico\AV BLVD MANUEL A CAMACHO\CMX\11510 MEXMEX | H19: Amazon | I19: Sales | J19: Marketing | K19: 0 | L19: =VLOOKUP(B19,[1]Total!$B:$Q,16,0) -> 603.81.004 Gastos de Oficina | M19: =D19 -> 0.86 | N19: =CONCATENATE(F19," ",G19," ",H19," ",I19," ",J19," ",K19," ") -> Rogelio Gamez 20260211T04:49:55/Amazon Mexico\AV BLVD MANUEL A CAMACHO\CMX\11510 MEXMEX Amazon Sales Marketing 0
A20: TRX1303 | B20: #16 | C20: 46072.417 | D20: 300 | E20: MXN | F20: Rogelio Gamez | G20: ABTS 12911 PRADO NORTE CIUDAD DE MEX MEX | H20: Abts Prado Norte Ciudad De Mex Mex | I20: Tech&Product | J20: 0 | K20: 0 | L20: =VLOOKUP(B20,[1]Total!$B:$Q,16,0) -> 603.81.004 Gastos de Oficina | M20: =D20 -> 300 | N20: =CONCATENATE(F20," ",G20," ",H20," ",I20," ",J20," ",K20," ") -> Rogelio Gamez ABTS 12911 PRADO NORTE CIUDAD DE MEX MEX Abts Prado Norte Ciudad De Mex Mex Tech&Product 0 0
A21: TRX1313 | B21: #16 | C21: 46074.417 | D21: 10000 | E21: MXN | F21: Rogelio Gamez | G21: PAYU *GOOGLE ADS MIGUEL HIDALG MEX | H21: Google | I21: Office expenses | J21: 0 | K21: 0 | L21: =VLOOKUP(B21,[1]Total!$B:$Q,16,0) -> 603.81.004 Gastos de Oficina | M21: =D21 -> 10000 | N21: =CONCATENATE(F21," ",G21," ",H21," ",I21," ",J21," ",K21," ") -> Rogelio Gamez PAYU *GOOGLE ADS MIGUEL HIDALG MEX Google Office expenses 0 0
A22: TRX1077 | B22: #16 | C22: 46075.417 | D22: 377.09 | E22: USD | F22: Rogelio Gamez | G22: Box_UK London GBR | H22: Box_Uk London | I22: Tech&Product | J22: 0 | K22: 0 | L22: =VLOOKUP(B22,[1]Total!$B:$Q,16,0) -> 603.81.004 Gastos de Oficina | M22: =D22 -> 377.09 | N22: =CONCATENATE(F22," ",G22," ",H22," ",I22," ",J22," ",K22," ") -> Rogelio Gamez Box_UK London GBR Box_Uk London Tech&Product 0 0
A23: TRX1097 | B23: #16 | C23: 46076.417 | D23: 320.53 | E23: EUR | F23: Rogelio Gamez | G23: WEGLOT PARIS FRA | H23: Weglot Paris Fra | I23: Tech&Product | J23: 0 | K23: 0 | L23: =VLOOKUP(B23,[1]Total!$B:$Q,16,0) -> 603.81.004 Gastos de Oficina | M23: =D23 -> 320.53 | N23: =CONCATENATE(F23," ",G23," ",H23," ",I23," ",J23," ",K23," ") -> Rogelio Gamez WEGLOT PARIS FRA Weglot Paris Fra Tech&Product 0 0
A24: TRX1285 | B24: #66 | C24: 46056.417 | D24: 262 | E24: MXN | F24: Erik Castillo | G24: HAMBURGUESAS DIANA TIZAYUCA HGO MEX | H24: Hamburguesas Diana Tizayuca Hgo Mex | I24: Transaction cost | J24: Gasolina | K24: A18529 | L24: =VLOOKUP(B24,[1]Total!$B:$Q,16,0) -> 602.34.002 Gastos por visita tencica | M24: =D24 -> 262 | N24: =CONCATENATE(F24," ",G24," ",H24," ",I24," ",J24," ",K24," ") -> Erik Castillo HAMBURGUESAS DIANA TIZAYUCA HGO MEX Hamburguesas Diana Tizayuca Hgo Mex Transaction cost Gasolina A18529
A25: TRX1275 | B25: #66 | C25: 46057.417 | D25: 1214.65 | E25: MXN | F25: Erik Castillo | G25: ENERGETICOS ZAPATA 4 TIZAYUCA HGO MEX | H25: Energeticos Zapata 4 Tizayuca Hgo Mex | I25: Transaction cost | J25: Recarga de TAG | K25: AAAU-581966 | L25: =VLOOKUP(B25,[1]Total!$B:$Q,16,0) -> 602.34.002 Gastos por visita tencica | M25: =D25 -> 1214.65 | N25: =CONCATENATE(F25," ",G25," ",H25," ",I25," ",J25," ",K25," ") -> Erik Castillo ENERGETICOS ZAPATA 4 TIZAYUCA HGO MEX Energeticos Zapata 4 Tizayuca Hgo Mex Transaction cost Recarga de TAG AAAU-581966
A26: TRX1903 | B26: #66 | C26: 46059.417 | D26: 107.5 | E26: MXN | F26: Erik Castillo | G26: OXXOSAN ANTONIO 17 MEX CUAUTITLAN EM MEX | H26: Oxxosan Antonio 17 Mex Cuautitlan Em Mex | I26: Transaction cost | J26: Consumo con Personal Creaceric | K26: DOMBNTAAQH 15621 | L26: =VLOOKUP(B26,[1]Total!$B:$Q,16,0) -> 602.34.002 Gastos por visita tencica | M26: =D26 -> 107.5 | N26: =CONCATENATE(F26," ",G26," ",H26," ",I26," ",J26," ",K26," ") -> Erik Castillo OXXOSAN ANTONIO 17 MEX CUAUTITLAN EM MEX Oxxosan Antonio 17 Mex Cuautitlan Em Mex Transaction cost Consumo con Personal Creaceric DOMBNTAAQH 15621
A27: TRX1082 | B27: #66 | C27: 46060.417 | D27: 295 | E27: MXN | F27: Erik Castillo | G27: MERCADOPAGO *SELENEGH Tizayuca MEX | H27: Mercadopago | I27: Transaction cost | J27: Gasolina entrega de auto rentado | K27: A18601 | L27: =VLOOKUP(B27,[1]Total!$B:$Q,16,0) -> 602.34.002 Gastos por visita tencica | M27: =D27 -> 295 | N27: =CONCATENATE(F27," ",G27," ",H27," ",I27," ",J27," ",K27," ") -> Erik Castillo MERCADOPAGO *SELENEGH Tizayuca MEX Mercadopago Transaction cost Gasolina entrega de auto rentado A18601
A28: TRX1108 | B28: #66 | C28: 46060.417 | D28: 100 | E28: MXN | F28: Erik Castillo | G28: OXXO EJERCITO TIZAYUCA HGO MEX | H28: Oxxo | I28: Transaction cost | J28: Traslado | K28: No me facturo | L28: =VLOOKUP(B28,[1]Total!$B:$Q,16,0) -> 602.34.002 Gastos por visita tencica | M28: =D28 -> 100 | N28: =CONCATENATE(F28," ",G28," ",H28," ",I28," ",J28," ",K28," ") -> Erik Castillo OXXO EJERCITO TIZAYUCA HGO MEX Oxxo Transaction cost Traslado No me facturo
A29: TRX1603 | B29: #66 | C29: 46060.417 | D29: 375.5 | E29: MXN | F29: Erik Castillo | G29: BGA AURRERA TIZAYUCA TIZAYUCA HGO MEX | H29: Bga Aurrera Tizayuca Tizayuca Hgo Mex | I29: Transaction cost | J29: Recarga de auto sin renta | K29: AAAU-581966 | L29: =VLOOKUP(B29,[1]Total!$B:$Q,16,0) -> 602.34.002 Gastos por visita tencica | M29: =D29 -> 375.5 | N29: =CONCATENATE(F29," ",G29," ",H29," ",I29," ",J29," ",K29," ") -> Erik Castillo BGA AURRERA TIZAYUCA TIZAYUCA HGO MEX Bga Aurrera Tizayuca Tizayuca Hgo Mex Transaction cost Recarga de auto sin renta AAAU-581966
A30: TRX1660 | B30: #66 | C30: 46063.417 | D30: 1386.72 | E30: MXN | F30: Erik Castillo | G30: ENERGETICOS ZAPATA 1 TIZAYUCA HGO MEX | H30: Energeticos Zapata 1 Tizayuca Hgo Mex | I30: Transaction cost | J30: Consumo | K30: ya no alcance a facturar | L30: =VLOOKUP(B30,[1]Total!$B:$Q,16,0) -> 602.34.002 Gastos por visita tencica | M30: =D30 -> 1386.72 | N30: =CONCATENATE(F30," ",G30," ",H30," ",I30," ",J30," ",K30," ") -> Erik Castillo ENERGETICOS ZAPATA 1 TIZAYUCA HGO MEX Energeticos Zapata 1 Tizayuca Hgo Mex Transaction cost Consumo ya no alcance a facturar
A31: TRX1877 | B31: #66 | C31: 46063.417 | D31: 469 | E31: MXN | F31: Erik Castillo | G31: CASHI ECOMMERCE RC CIUDAD DE MEX MEX | H31: Cashi Ecommerce Rc Ciudad De Mex Mex | I31: Transaction cost | J31: Consumo | K31: IBABK342054 | L31: =VLOOKUP(B31,[1]Total!$B:$Q,16,0) -> 602.34.002 Gastos por visita tencica | M31: =D31 -> 469 | N31: =CONCATENATE(F31," ",G31," ",H31," ",I31," ",J31," ",K31," ") -> Erik Castillo CASHI ECOMMERCE RC CIUDAD DE MEX MEX Cashi Ecommerce Rc Ciudad De Mex Mex Transaction cost Consumo IBABK342054
A32: TRX1125 | B32: #66 | C32: 46063.417 | D32: 96.5 | E32: MXN | F32: Erik Castillo | G32: OXXO G ZAPATA PAC TIZAYUCA HGO MEX | H32: Oxxo | I32: Transaction cost | J32: Viaje a Veracruz ida y vuelta | K32: 151715038 | L32: =VLOOKUP(B32,[1]Total!$B:$Q,16,0) -> 602.34.002 Gastos por visita tencica | M32: =D32 -> 96.5 | N32: =CONCATENATE(F32," ",G32," ",H32," ",I32," ",J32," ",K32," ") -> Erik Castillo OXXO G ZAPATA PAC TIZAYUCA HGO MEX Oxxo Transaction cost Viaje a Veracruz ida y vuelta 151715038
A33: TRX1420 | B33: #66 | C33: 46064.417 | D33: 33 | E33: MXN | F33: Erik Castillo | G33: OXXO G ZAPATA PAC TIZAYUCA HGO MEX | H33: Oxxo | I33: Transaction cost | J33: Hotel Veracruz | K33: FA9310 | L33: =VLOOKUP(B33,[1]Total!$B:$Q,16,0) -> 602.34.002 Gastos por visita tencica | M33: =D33 -> 33 | N33: =CONCATENATE(F33," ",G33," ",H33," ",I33," ",J33," ",K33," ") -> Erik Castillo OXXO G ZAPATA PAC TIZAYUCA HGO MEX Oxxo Transaction cost Hotel Veracruz FA9310
A34: TRX1580 | B34: #66 | C34: 46064.417 | D34: 1014 | E34: MXN | F34: Erik Castillo | G34: OXXO G ZAPATA PAC TIZAYUCA HGO MEX | H34: Oxxo | I34: Transaction cost | J34: Electrico Vehiculo | K34: Folia A 24860 | L34: =VLOOKUP(B34,[1]Total!$B:$Q,16,0) -> 602.34.002 Gastos por visita tencica | M34: =D34 -> 1014 | N34: =CONCATENATE(F34," ",G34," ",H34," ",I34," ",J34," ",K34," ") -> Erik Castillo OXXO G ZAPATA PAC TIZAYUCA HGO MEX Oxxo Transaction cost Electrico Vehiculo Folia A 24860
A35: TRX1701 | B35: #66 | C35: 46065.417 | D35: 350 | E35: MXN | F35: Erik Castillo | G35: HAMBURGUESAS DIANA TIZAYUCA HGO MEX | H35: Hamburguesas Diana Tizayuca Hgo Mex | I35: Transaction cost | J35: Seguridad | K35: 544913E5-5BEB-49F1-A1A4-C7A64C00862C | L35: =VLOOKUP(B35,[1]Total!$B:$Q,16,0) -> 602.34.002 Gastos por visita tencica | M35: =D35 -> 350 | N35: =CONCATENATE(F35," ",G35," ",H35," ",I35," ",J35," ",K35," ") -> Erik Castillo HAMBURGUESAS DIANA TIZAYUCA HGO MEX Hamburguesas Diana Tizayuca Hgo Mex Transaction cost Seguridad 544913E5-5BEB-49F1-A1A4-C7A64C00862C
A36: TRX1647 | B36: #66 | C36: 46066.417 | D36: 139.7 | E36: MXN | F36: Erik Castillo | G36: WWO 2269 MP TIZAYUCA HGO MEX | H36: Wwo 2269 Mp Tizayuca Hgo Mex | I36: Transaction cost | J36: Gasolina | K36: A18797 | L36: =VLOOKUP(B36,[1]Total!$B:$Q,16,0) -> 602.34.002 Gastos por visita tencica | M36: =D36 -> 139.7 | N36: =CONCATENATE(F36," ",G36," ",H36," ",I36," ",J36," ",K36," ") -> Erik Castillo WWO 2269 MP TIZAYUCA HGO MEX Wwo 2269 Mp Tizayuca Hgo Mex Transaction cost Gasolina A18797
A37: TRX1498 | B37: #66 | C37: 46066.417 | D37: 407.98 | E37: MXN | F37: Erik Castillo | G37: FAR GUAD 2318 TIZAYUCA HGO MEX | H37: Far Guad 2318 Tizayuca Hgo Mex | I37: Transaction cost | J37: Recarga | K37: 7513083260122161507881 | L37: =VLOOKUP(B37,[1]Total!$B:$Q,16,0) -> 602.34.002 Gastos por visita tencica | M37: =D37 -> 407.98 | N37: =CONCATENATE(F37," ",G37," ",H37," ",I37," ",J37," ",K37," ") -> Erik Castillo FAR GUAD 2318 TIZAYUCA HGO MEX Far Guad 2318 Tizayuca Hgo Mex Transaction cost Recarga 7513083260122161507881
A38: TRX1294 | B38: #66 | C38: 46067.417 | D38: 1480.2 | E38: MXN | F38: Erik Castillo | G38: ENERGETICOS ZAPATA 3 TIZAYUCA HGO MEX | H38: Energeticos Zapata 3 Tizayuca Hgo Mex | I38: Transaction cost | J38: Consumo | K38: 7545056260122161139465 | L38: =VLOOKUP(B38,[1]Total!$B:$Q,16,0) -> 602.34.002 Gastos por visita tencica | M38: =D38 -> 1480.2 | N38: =CONCATENATE(F38," ",G38," ",H38," ",I38," ",J38," ",K38," ") -> Erik Castillo ENERGETICOS ZAPATA 3 TIZAYUCA HGO MEX Energeticos Zapata 3 Tizayuca Hgo Mex Transaction cost Consumo 7545056260122161139465
A39: TRX1835 | B39: #66 | C39: 46068.417 | D39: 149 | E39: MXN | F39: Erik Castillo | G39: OXXO G ZAPATA PAC TIZAYUCA HGO MEX | H39: Oxxo | I39: Transaction cost | J39: Consumo | K39: 182BFE68-095E-4026-B953-EA81B419CDD5 | L39: =VLOOKUP(B39,[1]Total!$B:$Q,16,0) -> 602.34.002 Gastos por visita tencica | M39: =D39 -> 149 | N39: =CONCATENATE(F39," ",G39," ",H39," ",I39," ",J39," ",K39," ") -> Erik Castillo OXXO G ZAPATA PAC TIZAYUCA HGO MEX Oxxo Transaction cost Consumo 182BFE68-095E-4026-B953-EA81B419CDD5
A40: TRX1753 | B40: #66 | C40: 46069.417 | D40: 245 | E40: MXN | F40: Erik Castillo | G40: OXXO FUENTES TIZAYUCA TIZAYUCA HGO MEX | H40: Oxxo | I40: Transaction cost | J40: Consumo para traslados | K40: ICAGL581003 | L40: =VLOOKUP(B40,[1]Total!$B:$Q,16,0) -> 602.34.002 Gastos por visita tencica | M40: =D40 -> 245 | N40: =CONCATENATE(F40," ",G40," ",H40," ",I40," ",J40," ",K40," ") -> Erik Castillo OXXO FUENTES TIZAYUCA TIZAYUCA HGO MEX Oxxo Transaction cost Consumo para traslados ICAGL581003
A41: TRX1050 | B41: #66 | C41: 46070.417 | D41: 350 | E41: MXN | F41: Erik Castillo | G41: CLIP MX*REST TAQUERIA TIZAYUCA MEX | H41: Clip Mx Rest Taqueria Tizayuca Mex | I41: Transaction cost | J41: Consulta de emergencia por caida | K41: B4695 | L41: =VLOOKUP(B41,[1]Total!$B:$Q,16,0) -> 602.34.002 Gastos por visita tencica | M41: =D41 -> 350 | N41: =CONCATENATE(F41," ",G41," ",H41," ",I41," ",J41," ",K41," ") -> Erik Castillo CLIP MX*REST TAQUERIA TIZAYUCA MEX Clip Mx Rest Taqueria Tizayuca Mex Transaction cost Consulta de emergencia por caida B4695
A42: TRX1830 | B42: #66 | C42: 46070.417 | D42: 348 | E42: MXN | F42: Erik Castillo | G42: BGA AURRERA TIZAYUCA TIZAYUCA HGO MEX | H42: Bga Aurrera Tizayuca Tizayuca Hgo Mex | I42: Transaction cost | J42: Recargo por cambio de vuelo | K42: 151715038 | L42: =VLOOKUP(B42,[1]Total!$B:$Q,16,0) -> 602.34.002 Gastos por visita tencica | M42: =D42 -> 348 | N42: =CONCATENATE(F42," ",G42," ",H42," ",I42," ",J42," ",K42," ") -> Erik Castillo BGA AURRERA TIZAYUCA TIZAYUCA HGO MEX Bga Aurrera Tizayuca Tizayuca Hgo Mex Transaction cost Recargo por cambio de vuelo 151715038
A43: TRX1860 | B43: #66 | C43: 46071.417 | D43: 210 | E43: MXN | F43: Erik Castillo | G43: MERCADOPAGO *SELENEGH Tizayuca MEX | H43: Mercadopago | I43: Transaction cost | J43: Gasolina | K43: A19044 | L43: =VLOOKUP(B43,[1]Total!$B:$Q,16,0) -> 602.34.002 Gastos por visita tencica | M43: =D43 -> 210 | N43: =CONCATENATE(F43," ",G43," ",H43," ",I43," ",J43," ",K43," ") -> Erik Castillo MERCADOPAGO *SELENEGH Tizayuca MEX Mercadopago Transaction cost Gasolina A19044
A44: TRX1985 | B44: #66 | C44: 46072.417 | D44: 171 | E44: MXN | F44: Erik Castillo | G44: OPER NEDARO CTRO LECHE TIZAYUCA HGO MEX | H44: Oper Nedaro Ctro Leche Tizayuca Hgo Mex | I44: Transaction cost | J44: Recarga de TAG | K44: BD6DD3C6-20F1-41D3-A763-01A934EA253C | L44: =VLOOKUP(B44,[1]Total!$B:$Q,16,0) -> 602.34.002 Gastos por visita tencica | M44: =D44 -> 171 | N44: =CONCATENATE(F44," ",G44," ",H44," ",I44," ",J44," ",K44," ") -> Erik Castillo OPER NEDARO CTRO LECHE TIZAYUCA HGO MEX Oper Nedaro Ctro Leche Tizayuca Hgo Mex Transaction cost Recarga de TAG BD6DD3C6-20F1-41D3-A763-01A934EA253C
A45: TRX1563 | B45: #66 | C45: 46073.417 | D45: 1428.96 | E45: MXN | F45: Erik Castillo | G45: ENERGETICOS ZAPATA 1 TIZAYUCA HGO MEX | H45: Energeticos Zapata 1 Tizayuca Hgo Mex | I45: Transaction cost | J45: Consumo | K45: A - 17521 | L45: =VLOOKUP(B45,[1]Total!$B:$Q,16,0) -> 602.34.002 Gastos por visita tencica | M45: =D45 -> 1428.96 | N45: =CONCATENATE(F45," ",G45," ",H45," ",I45," ",J45," ",K45," ") -> Erik Castillo ENERGETICOS ZAPATA 1 TIZAYUCA HGO MEX Energeticos Zapata 1 Tizayuca Hgo Mex Transaction cost Consumo A - 17521
A46: TRX1003 | B46: #66 | C46: 46073.417 | D46: 111.5 | E46: MXN | F46: Erik Castillo | G46: OXXOSAN ANTONIO 17 MEX CUAUTITLAN EM MEX | H46: Oxxosan Antonio 17 Mex Cuautitlan Em Mex | I46: Transaction cost | J46: Seguridad para vehiculo | K46: IBABK342781 | L46: =VLOOKUP(B46,[1]Total!$B:$Q,16,0) -> 602.34.002 Gastos por visita tencica | M46: =D46 -> 111.5 | N46: =CONCATENATE(F46," ",G46," ",H46," ",I46," ",J46," ",K46," ") -> Erik Castillo OXXOSAN ANTONIO 17 MEX CUAUTITLAN EM MEX Oxxosan Antonio 17 Mex Cuautitlan Em Mex Transaction cost Seguridad para vehiculo IBABK342781
A47: TRX1268 | B47: #66 | C47: 46073.417 | D47: 1014 | E47: MXN | F47: Erik Castillo | G47: OXXO G ZAPATA PAC TIZAYUCA HGO MEX | H47: Oxxo | I47: Transaction cost | J47: Comida con cliente Creaceric | K47: A8AB9CE6-B34D-4E86-9B88-655996A59DAD | L47: =VLOOKUP(B47,[1]Total!$B:$Q,16,0) -> 602.34.002 Gastos por visita tencica | M47: =D47 -> 1014 | N47: =CONCATENATE(F47," ",G47," ",H47," ",I47," ",J47," ",K47," ") -> Erik Castillo OXXO G ZAPATA PAC TIZAYUCA HGO MEX Oxxo Transaction cost Comida con cliente Creaceric A8AB9CE6-B34D-4E86-9B88-655996A59DAD
A48: TRX1033 | B48: #66 | C48: 46074.417 | D48: 185 | E48: MXN | F48: Erik Castillo | G48: MISC PITS TOL ZIT ALMOLOYA DE J MEX | H48: Misc Pits Tol Zit Almoloya De J Mex | I48: Transaction cost | J48: Gasolina | K48: A19227 | L48: =VLOOKUP(B48,[1]Total!$B:$Q,16,0) -> 602.34.002 Gastos por visita tencica | M48: =D48 -> 185 | N48: =CONCATENATE(F48," ",G48," ",H48," ",I48," ",J48," ",K48," ") -> Erik Castillo MISC PITS TOL ZIT ALMOLOYA DE J MEX Misc Pits Tol Zit Almoloya De J Mex Transaction cost Gasolina A19227
A49: TRX1067 | B49: #66 | C49: 46075.417 | D49: 1700 | E49: MXN | F49: Erik Castillo | G49: AUTO SERVICIO REVASA TIZAYUCA HGO MEX | H49: Auto Servicio Revasa Tizayuca Hgo Mex | I49: Transaction cost | J49: Consumo | K49: D0BB9880-904C-4847-A411-2E8A12244B57 | L49: =VLOOKUP(B49,[1]Total!$B:$Q,16,0) -> 602.34.002 Gastos por visita tencica | M49: =D49 -> 1700 | N49: =CONCATENATE(F49," ",G49," ",H49," ",I49," ",J49," ",K49," ") -> Erik Castillo AUTO SERVICIO REVASA TIZAYUCA HGO MEX Auto Servicio Revasa Tizayuca Hgo Mex Transaction cost Consumo D0BB9880-904C-4847-A411-2E8A12244B57
A50: TRX1143 | B50: #66 | C50: 46078.417 | D50: 659 | E50: MXN | F50: Erik Castillo | G50: KFC 549 LOPEZ PORTILLO COACALCO DE B MEX | H50: Kentucky Fried Chicken | I50: Transaction cost | J50: Consumo VEOLIA | K50: 7531889260130044529712 | L50: =VLOOKUP(B50,[1]Total!$B:$Q,16,0) -> 602.34.002 Gastos por visita tencica | M50: =D50 -> 659 | N50: =CONCATENATE(F50," ",G50," ",H50," ",I50," ",J50," ",K50," ") -> Erik Castillo KFC 549 LOPEZ PORTILLO COACALCO DE B MEX Kentucky Fried Chicken Transaction cost Consumo VEOLIA 7531889260130044529712
A51: TRX1176 | B51: #66 | C51: 46079.417 | D51: 1152.02 | E51: MXN | F51: Erik Castillo | G51: ENERGETICOS ZAPATA 4 TIZAYUCA HGO MEX | H51: Energeticos Zapata 4 Tizayuca Hgo Mex | I51: Transaction cost | J51: Consumo | K51: EB80B5ED-1544-4E81-AD9D-621FBA21CE3B | L51: =VLOOKUP(B51,[1]Total!$B:$Q,16,0) -> 602.34.002 Gastos por visita tencica | M51: =D51 -> 1152.02 | N51: =CONCATENATE(F51," ",G51," ",H51," ",I51," ",J51," ",K51," ") -> Erik Castillo ENERGETICOS ZAPATA 4 TIZAYUCA HGO MEX Energeticos Zapata 4 Tizayuca Hgo Mex Transaction cost Consumo EB80B5ED-1544-4E81-AD9D-621FBA21CE3B
A52: TRX1244 | B52: #66 | C52: 46080.417 | D52: 1017 | E52: MXN | F52: Erik Castillo | G52: OXXO EJERCITO TIZAYUCA HGO MEX | H52: Oxxo | I52: Transaction cost | J52: Consumo | K52: DOMBNTAAQH 15785 | L52: =VLOOKUP(B52,[1]Total!$B:$Q,16,0) -> 602.34.002 Gastos por visita tencica | M52: =D52 -> 1017 | N52: =CONCATENATE(F52," ",G52," ",H52," ",I52," ",J52," ",K52," ") -> Erik Castillo OXXO EJERCITO TIZAYUCA HGO MEX Oxxo Transaction cost Consumo DOMBNTAAQH 15785
A53: TRX1286 | B53: #2 | C53: 46056.417 | D53: 3642.61 | E53: USD | F53: Cesar Gonzales | G53: HASHICORP HCP SAN FRANCISCO USA | H53: Hashicorp | I53: Tech&Product | J53: 0 | K53: . | L53: =VLOOKUP(B53,[1]Total!$B:$Q,16,0) -> 603.38.002 Software y Sistemas | M53: =D53 -> 3642.61 | N53: =CONCATENATE(F53," ",G53," ",H53," ",I53," ",J53," ",K53," ") -> Cesar Gonzales HASHICORP HCP SAN FRANCISCO USA Hashicorp Tech&Product 0 .
A54: TRX1246 | B54: #2 | C54: 46058.417 | D54: 15105.29 | E54: MXN | F54: Cesar Gonzales | G54: PAYU *GOOGLE CLOUD MIGUEL HIDALG MEX | H54: Google Cloud | I54: Tech&Product | J54: 0 | K54: . | L54: =VLOOKUP(B54,[1]Total!$B:$Q,16,0) -> 603.38.002 Software y Sistemas | M54: =D54 -> 15105.29 | N54: =CONCATENATE(F54," ",G54," ",H54," ",I54," ",J54," ",K54," ") -> Cesar Gonzales PAYU *GOOGLE CLOUD MIGUEL HIDALG MEX Google Cloud Tech&Product 0 .
A55: TRX1242 | B55: #2 | C55: 46058.417 | D55: 957.38 | E55: MXN | F55: Cesar Gonzales | G55: PAYU *GOOGLE CLOUD MIGUEL HIDALG MEX | H55: Google Cloud | I55: Tech&Product | J55: 0 | K55: . | L55: =VLOOKUP(B55,[1]Total!$B:$Q,16,0) -> 603.38.002 Software y Sistemas | M55: =D55 -> 957.38 | N55: =CONCATENATE(F55," ",G55," ",H55," ",I55," ",J55," ",K55," ") -> Cesar Gonzales PAYU *GOOGLE CLOUD MIGUEL HIDALG MEX Google Cloud Tech&Product 0 .
A56: TRX1999 | B56: #2 | C56: 46059.417 | D56: 10214.06 | E56: USD | F56: Cesar Gonzales | G56: GITHUB, INC. SAN FRANCISCO USA | H56: Github | I56: Tech&Product | J56: 0 | K56: . | L56: =VLOOKUP(B56,[1]Total!$B:$Q,16,0) -> 603.38.002 Software y Sistemas | M56: =D56 -> 10214.06 | N56: =CONCATENATE(F56," ",G56," ",H56," ",I56," ",J56," ",K56," ") -> Cesar Gonzales GITHUB, INC. SAN FRANCISCO USA Github Tech&Product 0 .
A57: TRX1875 | B57: #2 | C57: 46063.417 | D57: 6524.63 | E57: USD | F57: Cesar Gonzales | G57: CURSOR, AI POWERED IDE NEW YORK USA | H57: Cursor Ai Powered Ide New York USA | I57: Tech&Product | J57: 0 | K57: . | L57: =VLOOKUP(B57,[1]Total!$B:$Q,16,0) -> 603.38.002 Software y Sistemas | M57: =D57 -> 6524.63 | N57: =CONCATENATE(F57," ",G57," ",H57," ",I57," ",J57," ",K57," ") -> Cesar Gonzales CURSOR, AI POWERED IDE NEW YORK USA Cursor Ai Powered Ide New York USA Tech&Product 0 .
A58: TRX1596 | B58: #2 | C58: 46065.417 | D58: 906.2 | E58: USD | F58: Cesar Gonzales | G58: CURSOR USAGE JAN NEW YORK USA | H58: Cursor Usage Jan New York USA | I58: Tech&Product | J58: 0 | K58: . | L58: =VLOOKUP(B58,[1]Total!$B:$Q,16,0) -> 603.38.002 Software y Sistemas | M58: =D58 -> 906.2 | N58: =CONCATENATE(F58," ",G58," ",H58," ",I58," ",J58," ",K58," ") -> Cesar Gonzales CURSOR USAGE JAN NEW YORK USA Cursor Usage Jan New York USA Tech&Product 0 .
A59: TRX1641 | B59: #2 | C59: 46065.417 | D59: 7115.29 | E59: USD | F59: Cesar Gonzales | G59: DATADOG, INC. NEW YORK USA | H59: Datadog | I59: Tech&Product | J59: 0 | K59: . | L59: =VLOOKUP(B59,[1]Total!$B:$Q,16,0) -> 603.38.002 Software y Sistemas | M59: =D59 -> 7115.29 | N59: =CONCATENATE(F59," ",G59," ",H59," ",I59," ",J59," ",K59," ") -> Cesar Gonzales DATADOG, INC. NEW YORK USA Datadog Tech&Product 0 .
A60: TRX1372 | B60: #2 | C60: 46066.417 | D60: 5964.72 | E60: MXN | F60: Cesar Gonzales | G60: STR*ODOO TECHNOLOGIES CIUDAD DE MEX MEX | H60: Str Odoo Technologies Ciudad De Mex Mex | I60: Tech&Product | J60: 0 | K60: . | L60: =VLOOKUP(B60,[1]Total!$B:$Q,16,0) -> 603.38.002 Software y Sistemas | M60: =D60 -> 5964.72 | N60: =CONCATENATE(F60," ",G60," ",H60," ",I60," ",J60," ",K60," ") -> Cesar Gonzales STR*ODOO TECHNOLOGIES CIUDAD DE MEX MEX Str Odoo Technologies Ciudad De Mex Mex Tech&Product 0 .
A61: TRX1245 | B61: #2 | C61: 46066.417 | D61: 1083.21 | E61: USD | F61: Cesar Gonzales | G61: AUGMENT CODE PALO ALTO USA | H61: Augment Code Palo Alto USA | I61: Tech&Product | J61: 0 | K61: . | L61: =VLOOKUP(B61,[1]Total!$B:$Q,16,0) -> 603.38.002 Software y Sistemas | M61: =D61 -> 1083.21 | N61: =CONCATENATE(F61," ",G61," ",H61," ",I61," ",J61," ",K61," ") -> Cesar Gonzales AUGMENT CODE PALO ALTO USA Augment Code Palo Alto USA Tech&Product 0 .
A62: TRX1378 | B62: #2 | C62: 46069.417 | D62: 14399.42 | E62: USD | F62: Cesar Gonzales | G62: AUTH0.COM SAN FRANCISCO USA | H62: Auth0 | I62: Tech&Product | J62: 0 | K62: . | L62: =VLOOKUP(B62,[1]Total!$B:$Q,16,0) -> 603.38.002 Software y Sistemas | M62: =D62 -> 14399.42 | N62: =CONCATENATE(F62," ",G62," ",H62," ",I62," ",J62," ",K62," ") -> Cesar Gonzales AUTH0.COM SAN FRANCISCO USA Auth0 Tech&Product 0 .
A63: TRX1821 | B63: #2 | C63: 46073.417 | D63: 471.63 | E63: USD | F63: Cesar Gonzales | G63: CURSOR, AI POWERED IDE NEW YORK USA | H63: Cursor Ai Powered Ide New York USA | I63: Tech&Product | J63: 0 | K63: . | L63: =VLOOKUP(B63,[1]Total!$B:$Q,16,0) -> 603.38.002 Software y Sistemas | M63: =D63 -> 471.63 | N63: =CONCATENATE(F63," ",G63," ",H63," ",I63," ",J63," ",K63," ") -> Cesar Gonzales CURSOR, AI POWERED IDE NEW YORK USA Cursor Ai Powered Ide New York USA Tech&Product 0 .
A64: TRX1080 | B64: #2 | C64: 46075.417 | D64: 2619.98 | E64: USD | F64: Cesar Gonzales | G64: ATLASSIAN SAN FRANCISCO USA | H64: Atlassian | I64: Tech&Product | J64: 0 | K64: . | L64: =VLOOKUP(B64,[1]Total!$B:$Q,16,0) -> 603.38.002 Software y Sistemas | M64: =D64 -> 2619.98 | N64: =CONCATENATE(F64," ",G64," ",H64," ",I64," ",J64," ",K64," ") -> Cesar Gonzales ATLASSIAN SAN FRANCISCO USA Atlassian Tech&Product 0 .
... A67: TRX1127 | B67: #2 | C67: 46077.417 | D67: 7106.33 | E67: USD | F67: Cesar Gonzales | G67: Microsoft-G142443073 msbill.info USA | H67: Microsoft | I67: Tech&Product | J67: 0 | K67: . | L67: =VLOOKUP(B67,[1]Total!$B:$Q,16,0) -> 603.38.002 Software y Sistemas | M67: =D67 -> 7106.33 | N67: =CONCATENATE(F67," ",G67," ",H67," ",I67," ",J67," ",K67," ") -> Cesar Gonzales Microsoft-G142443073 msbill.info USA Microsoft Tech&Product 0 .
A68: #N/A | B68: 0 | C68: 0 | D68: #N/A | E68: #N/A | F68: #N/A | G68: #N/A | H68: 0 | I68: G&A expenses | J68: Intern lunch w Nitisha.& Karn | K68: . | L68: =VLOOKUP(B68,[1]Total!$B:$Q,16,0) -> #N/A | M68: =D68 -> #N/A | N68: =CONCATENATE(F68," ",G68," ",H68," ",I68," ",J68," ",K68," ") -> #N/A #N/A 0 G&A expenses Intern lunch w Nitisha.& Karn .
A69: TRX1239 | B69: #3 | C69: 46058.417 | D69: 1130 | E69: MXN | F69: Cesar Uriel Romo Trillo | G69: HAMMER STRONG CIUDAD DE MEX MEX | H69: Hammer Strong Ciudad De Mex Mex | I69: Sales | J69: Compra de Pulidora y discos para obra Grajales Robles PO1129 | K69: TICKET | L69: =VLOOKUP(B69,[1]Total!$B:$Q,16,0) -> 603.81.006 Gastos Administativos de venta | M69: =D69 -> 1130 | N69: =CONCATENATE(F69," ",G69," ",H69," ",I69," ",J69," ",K69," ") -> Cesar Uriel Romo Trillo HAMMER STRONG CIUDAD DE MEX MEX Hammer Strong Ciudad De Mex Mex Sales Compra de Pulidora y discos para obra Grajales Robles PO1129 TICKET
A70: TRX1151 | B70: #3 | C70: 46059.417 | D70: 344.25 | E70: MXN | F70: Cesar Uriel Romo Trillo | G70: GAS JUVITA MEXICO DF MEX | H70: Gas Juvita Mexico Df Mex | I70: Sales | J70: Gasolina visita desmontaje de Grua Grajales Robles PO1129 | K70: TICKET | L70: =VLOOKUP(B70,[1]Total!$B:$Q,16,0) -> 603.81.006 Gastos Administativos de venta | M70: =D70 -> 344.25 | N70: =CONCATENATE(F70," ",G70," ",H70," ",I70," ",J70," ",K70," ") -> Cesar Uriel Romo Trillo GAS JUVITA MEXICO DF MEX Gas Juvita Mexico Df Mex Sales Gasolina visita desmontaje de Grua Grajales Robles PO1129 TICKET
A71: TRX1538 | B71: #3 | C71: 46060.417 | D71: 803.6 | E71: MXN | F71: Cesar Uriel Romo Trillo | G71: GASOLINERA COMB ERMITA CIUDAD DE MEX MEX | H71: Gasolinera Comb Ermita Ciudad De Mex Mex | I71: Sales | J71: Gasolina para Malacate Grajales Robles PO 1129 | K71: TICKET | L71: =VLOOKUP(B71,[1]Total!$B:$Q,16,0) -> 603.81.006 Gastos Administativos de venta | M71: =D71 -> 803.6 | N71: =CONCATENATE(F71," ",G71," ",H71," ",I71," ",J71," ",K71," ") -> Cesar Uriel Romo Trillo GASOLINERA COMB ERMITA CIUDAD DE MEX MEX Gasolinera Comb Ermita Ciudad De Mex Mex Sales Gasolina para Malacate Grajales Robles PO 1129 TICKET
A72: TRX1068 | B72: #3 | C72: 46065.417 | D72: 574 | E72: MXN | F72: Cesar Uriel Romo Trillo | G72: GASOLINERA COMB ERMITA CIUDAD DE MEX MEX | H72: Gasolinera Comb Ermita Ciudad De Mex Mex | I72: Sales | J72: Gasolina visita equipo Elvic PO1129 | K72: TICKET | L72: =VLOOKUP(B72,[1]Total!$B:$Q,16,0) -> 603.81.006 Gastos Administativos de venta | M72: =D72 -> 574 | N72: =CONCATENATE(F72," ",G72," ",H72," ",I72," ",J72," ",K72," ") -> Cesar Uriel Romo Trillo GASOLINERA COMB ERMITA CIUDAD DE MEX MEX Gasolinera Comb Ermita Ciudad De Mex Mex Sales Gasolina visita equipo Elvic PO1129 TICKET
A73: TRX1608 | B73: #3 | C73: 46065.417 | D73: 767 | E73: MXN | F73: Cesar Uriel Romo Trillo | G73: MAMA S PIZZA CIUDAD DE MEX MEX | H73: Mama S Pizza Ciudad De Mex Mex | I73: Sales | J73: Comida equipo Elvic PO 1129 | K73: TICKET | L73: =VLOOKUP(B73,[1]Total!$B:$Q,16,0) -> 603.81.006 Gastos Administativos de venta | M73: =D73 -> 767 | N73: =CONCATENATE(F73," ",G73," ",H73," ",I73," ",J73," ",K73," ") -> Cesar Uriel Romo Trillo MAMA S PIZZA CIUDAD DE MEX MEX Mama S Pizza Ciudad De Mex Mex Sales Comida equipo Elvic PO 1129 TICKET
A74: TRX1618 | B74: #3 | C74: 46071.417 | D74: 918.4 | E74: MXN | F74: Cesar Uriel Romo Trillo | G74: GASOLINERA COMB ERMITA CIUDAD DE MEX MEX | H74: Gasolinera Comb Ermita Ciudad De Mex Mex | I74: Sales | J74: Gasolina Visita deal nuevo Grupo GSA | K74: TICKET | L74: =VLOOKUP(B74,[1]Total!$B:$Q,16,0) -> 603.81.006 Gastos Administativos de venta | M74: =D74 -> 918.4 | N74: =CONCATENATE(F74," ",G74," ",H74," ",I74," ",J74," ",K74," ") -> Cesar Uriel Romo Trillo GASOLINERA COMB ERMITA CIUDAD DE MEX MEX Gasolinera Comb Ermita Ciudad De Mex Mex Sales Gasolina Visita deal nuevo Grupo GSA TICKET
A75: TRX1068 | B75: #3 | C75: 46075.417 | D75: 344.4 | E75: MXN | F75: Cesar Uriel Romo Trillo | G75: COMBUSTIBLE ERMITA CIUDAD DE MEX MEX | H75: Combustible Ermita Ciudad De Mex Mex | I75: Sales | J75: Gasolina Visita Grajales Robles PO 1129, visita obra Parque Churubusco (nuevo deal), Visita Syvasa Calidad RFQ 3254 | K75: TICKET | L75: =VLOOKUP(B75,[1]Total!$B:$Q,16,0) -> 603.81.006 Gastos Administativos de venta | M75: =D75 -> 344.4 | N75: =CONCATENATE(F75," ",G75," ",H75," ",I75," ",J75," ",K75," ") -> Cesar Uriel Romo Trillo COMBUSTIBLE ERMITA CIUDAD DE MEX MEX Combustible Ermita Ciudad De Mex Mex Sales Gasolina Visita Grajales Robles PO 1129, visita obra Parque Churubusco (nuevo deal), Visita Syvasa Calidad RFQ 3254 TICKET
A76: TRX1098 | B76: #3 | C76: 46076.417 | D76: 142.19 | E76: MXN | F76: Cesar Uriel Romo Trillo | G76: D LOCAL*REST DIDIFOOD CIUDAD DE MEX MEX | H76: D Local Rest Didifood Ciudad De Mex Mex | I76: Sales | J76: Compra de candado GRAJALES ROBLES PO 1129 | K76: TICKET | L76: =VLOOKUP(B76,[1]Total!$B:$Q,16,0) -> 603.81.006 Gastos Administativos de venta | M76: =D76 -> 142.19 | N76: =CONCATENATE(F76," ",G76," ",H76," ",I76," ",J76," ",K76," ") -> Cesar Uriel Romo Trillo D LOCAL*REST DIDIFOOD CIUDAD DE MEX MEX D Local Rest Didifood Ciudad De Mex Mex Sales Compra de candado GRAJALES ROBLES PO 1129 TICKET
A77: TRX1288 | B77: #4 | C77: 46056.417 | D77: 915.4 | E77: MXN | F77: Daniel Autrique Echeveste | G77: LPQ AICM T1 SALA 8 1 CIUDAD DE MEX MEX | H77: L | I77: Recruiting | J77: LinkedIn | K77: . | L77: =VLOOKUP(B77,[1]Total!$B:$Q,16,0) -> 603.81.002 Gastos corporativos ND | M77: =D77 -> 915.4 | N77: =CONCATENATE(F77," ",G77," ",H77," ",I77," ",J77," ",K77," ") -> Daniel Autrique Echeveste LPQ AICM T1 SALA 8 1 CIUDAD DE MEX MEX L Recruiting LinkedIn .
A78: TRX1279 | B78: #4 | C78: 46056.417 | D78: 704.7 | E78: USD | F78: Daniel Autrique Echeveste | G78: CURB MOBILITY ASTORIA USA | H78: Curb Mobility | I78: Sales | J78: Vuelo a chicago Radioflyer | K78: . | L78: =VLOOKUP(B78,[1]Total!$B:$Q,16,0) -> 603.81.002 Gastos corporativos ND | M78: =D78 -> 704.7 | N78: =CONCATENATE(F78," ",G78," ",H78," ",I78," ",J78," ",K78," ") -> Daniel Autrique Echeveste CURB MOBILITY ASTORIA USA Curb Mobility Sales Vuelo a chicago Radioflyer .
A79: TRX1272 | B79: #4 | C79: 46057.417 | D79: 1216.2 | E79: USD | F79: Daniel Autrique Echeveste | G79: TCOLV - Naughty Patt LAS VEGAS USA | H79: Tcolv Naughty Patt Las Vegas USA | I79: Sales | J79: 0 | K79: . | L79: =VLOOKUP(B79,[1]Total!$B:$Q,16,0) -> 603.81.002 Gastos corporativos ND | M79: =D79 -> 1216.2 | N79: =CONCATENATE(F79," ",G79," ",H79," ",I79," ",J79," ",K79," ") -> Daniel Autrique Echeveste TCOLV - Naughty Patt LAS VEGAS USA Tcolv Naughty Patt Las Vegas USA Sales 0 .
A80: TRX1271 | B80: #4 | C80: 46057.417 | D80: 476.1 | E80: USD | F80: Daniel Autrique Echeveste | G80: ZTRIP TAXI KANSAS CITY USA | H80: Ztrip Taxi Kansas City USA | I80: Sales | J80: 0 | K80: . | L80: =VLOOKUP(B80,[1]Total!$B:$Q,16,0) -> 603.81.002 Gastos corporativos ND | M80: =D80 -> 476.1 | N80: =CONCATENATE(F80," ",G80," ",H80," ",I80," ",J80," ",K80," ") -> Daniel Autrique Echeveste ZTRIP TAXI KANSAS CITY USA Ztrip Taxi Kansas City USA Sales 0 .
A81: TRX1197 | B81: #4 | C81: 46058.417 | D81: 11358 | E81: USD | F81: Daniel Autrique Echeveste | G81: WOLFGANG PUCK CUT LAS VEGAS USA | H81: Wolfgang Puck | I81: G&A expenses | J81: 0 | K81: . | L81: =VLOOKUP(B81,[1]Total!$B:$Q,16,0) -> 603.81.002 Gastos corporativos ND | M81: =D81 -> 11358 | N81: =CONCATENATE(F81," ",G81," ",H81," ",I81," ",J81," ",K81," ") -> Daniel Autrique Echeveste WOLFGANG PUCK CUT LAS VEGAS USA Wolfgang Puck G&A expenses 0 .
A82: TRX1193 | B82: #4 | C82: 46058.418 | D82: 181.58 | E82: USD | F82: Daniel Autrique Echeveste | G82: Viasat, Inc. 8669453258 USA | H82: Viasat | I82: Sales | J82: 0 | K82: . | L82: =VLOOKUP(B82,[1]Total!$B:$Q,16,0) -> 603.81.002 Gastos corporativos ND | M82: =D82 -> 181.58 | N82: =CONCATENATE(F82," ",G82," ",H82," ",I82," ",J82," ",K82," ") -> Daniel Autrique Echeveste Viasat, Inc. 8669453258 USA Viasat Sales 0 .
A83: TRX1576 | B83: #4 | C83: 46059.417 | D83: 13052.62 | E83: MXN | F83: Daniel Autrique Echeveste | G83: COSMOPOL-FRONT DESK LAS VEGAS USA | H83: Cosmopol Front Desk Las Vegas USA | I83: Sales | J83: 0 | K83: . | L83: =VLOOKUP(B83,[1]Total!$B:$Q,16,0) -> 603.81.002 Gastos corporativos ND | M83: =D83 -> 13052.62 | N83: =CONCATENATE(F83," ",G83," ",H83," ",I83," ",J83," ",K83," ") -> Daniel Autrique Echeveste COSMOPOL-FRONT DESK LAS VEGAS USA Cosmopol Front Desk Las Vegas USA Sales 0 .
A84: TRX1408 | B84: #4 | C84: 46060.417 | D84: 2196.88 | E84: USD | F84: Daniel Autrique Echeveste | G84: 20260203T00:00:00/COSMOPOL-FRONT DESK\3708 LAS VEGAS BLVD S\LAS VEGAS\89109 NV USA | H84: T :00/Cosmopol Front Desk\3708 Las Vegas Blvd S\Las Vegas\ Nv USA | I84: Sales | J84: 0 | K84: . | L84: =VLOOKUP(B84,[1]Total!$B:$Q,16,0) -> 603.81.002 Gastos corporativos ND | M84: =D84 -> 2196.88 | N84: =CONCATENATE(F84," ",G84," ",H84," ",I84," ",J84," ",K84," ") -> Daniel Autrique Echeveste 20260203T00:00:00/COSMOPOL-FRONT DESK\3708 LAS VEGAS BLVD S\LAS VEGAS\89109 NV USA T :00/Cosmopol Front Desk\3708 Las Vegas Blvd S\Las Vegas\ Nv USA Sales 0 .
A85: TRX1758 | B85: #4 | C85: 46061.417 | D85: 100 | E85: MXN | F85: Daniel Autrique Echeveste | G85: MEXPAGO*MUEVECIUDAD CIUDAD DE MEX MEX | H85: Mexpago Mueveciudad Ciudad De Mex Mex | I85: Sales | J85: 0 | K85: . | L85: =VLOOKUP(B85,[1]Total!$B:$Q,16,0) -> 603.81.002 Gastos corporativos ND | M85: =D85 -> 100 | N85: =CONCATENATE(F85," ",G85," ",H85," ",I85," ",J85," ",K85," ") -> Daniel Autrique Echeveste MEXPAGO*MUEVECIUDAD CIUDAD DE MEX MEX Mexpago Mueveciudad Ciudad De Mex Mex Sales 0 .
A86: TRX1501 | B86: #4 | C86: 46064.417 | D86: 870.55 | E86: MXN | F86: Daniel Autrique Echeveste | G86: REST ENO VIRREYES CIUDAD DE MEX MEX | H86: Rest Eno Virreyes Ciudad De Mex Mex | I86: 0 | J86: 0 | K86: . | L86: =VLOOKUP(B86,[1]Total!$B:$Q,16,0) -> 603.81.002 Gastos corporativos ND | M86: =D86 -> 870.55 | N86: =CONCATENATE(F86," ",G86," ",H86," ",I86," ",J86," ",K86," ") -> Daniel Autrique Echeveste REST ENO VIRREYES CIUDAD DE MEX MEX Rest Eno Virreyes Ciudad De Mex Mex 0 0 .
A87: TRX1629 | B87: #4 | C87: 46067.417 | D87: 5662.6 | E87: MXN | F87: Daniel Autrique Echeveste | G87: REST ZERU LOMAS CIUDAD DE MEX MEX | H87: Rest Zeru Lomas Ciudad De Mex Mex | I87: 0 | J87: 0 | K87: . | L87: =VLOOKUP(B87,[1]Total!$B:$Q,16,0) -> 603.81.002 Gastos corporativos ND | M87: =D87 -> 5662.6 | N87: =CONCATENATE(F87," ",G87," ",H87," ",I87," ",J87," ",K87," ") -> Daniel Autrique Echeveste REST ZERU LOMAS CIUDAD DE MEX MEX Rest Zeru Lomas Ciudad De Mex Mex 0 0 .
A88: TRX1043 | B88: #4 | C88: 46071.417 | D88: 1213.99 | E88: MXN | F88: Daniel Autrique Echeveste | G88: GASOL VALERO LOMALINDA CIUDAD DE MEX MEX | H88: Gasol Valero Lomalinda Ciudad De Mex Mex | I88: 0 | J88: 0 | K88: . | L88: =VLOOKUP(B88,[1]Total!$B:$Q,16,0) -> 603.81.002 Gastos corporativos ND | M88: =D88 -> 1213.99 | N88: =CONCATENATE(F88," ",G88," ",H88," ",I88," ",J88," ",K88," ") -> Daniel Autrique Echeveste GASOL VALERO LOMALINDA CIUDAD DE MEX MEX Gasol Valero Lomalinda Ciudad De Mex Mex 0 0 .
A89: TRX1219 | B89: #5 | C89: 46058.417 | D89: 70 | E89: MXN | F89: Fernanda Sanchez Ruiz | G89: DLO*UBER RIDE CIUDAD DE MEX MEX | H89: Uber | I89: Office expenses | J89: Snacks para la oficina | K89: . | L89: =VLOOKUP(B89,[1]Total!$B:$Q,16,0) -> 603.81.004 Gastos de Oficina | M89: =D89 -> 70 | N89: =CONCATENATE(F89," ",G89," ",H89," ",I89," ",J89," ",K89," ") -> Fernanda Sanchez Ruiz DLO*UBER RIDE CIUDAD DE MEX MEX Uber Office expenses Snacks para la oficina .
A90: TRX1206 | B90: #5 | C90: 46058.417 | D90: 1186.28 | E90: MXN | F90: Fernanda Sanchez Ruiz | G90: SAMS VENTA EN LINEA MEXICO DF MEX | H90: Sam's Club | I90: Office expenses | J90: 0 | K90: . | L90: =VLOOKUP(B90,[1]Total!$B:$Q,16,0) -> 603.81.004 Gastos de Oficina | M90: =D90 -> 1186.28 | N90: =CONCATENATE(F90," ",G90," ",H90," ",I90," ",J90," ",K90," ") -> Fernanda Sanchez Ruiz SAMS VENTA EN LINEA MEXICO DF MEX Sam's Club Office expenses 0 .
A91: TRX1628 | B91: #5 | C91: 46065.417 | D91: 1690.58 | E91: MXN | F91: Fernanda Sanchez Ruiz | G91: SAMS VENTA EN LINEA MEXICO DF MEX | H91: Sam's Club | I91: Office expenses | J91: Snacks para la oficina | K91: . | L91: =VLOOKUP(B91,[1]Total!$B:$Q,16,0) -> 603.81.004 Gastos de Oficina | M91: =D91 -> 1690.58 | N91: =CONCATENATE(F91," ",G91," ",H91," ",I91," ",J91," ",K91," ") -> Fernanda Sanchez Ruiz SAMS VENTA EN LINEA MEXICO DF MEX Sam's Club Office expenses Snacks para la oficina .
A92: TRX1890 | B92: #5 | C92: 46067.417 | D92: 317.52 | E92: MXN | F92: Fernanda Sanchez Ruiz | G92: UBER * EATS PENDING CMX MEX | H92: Uber Eats | I92: Office expenses | J92: Snacks para la oficina | K92: . | L92: =VLOOKUP(B92,[1]Total!$B:$Q,16,0) -> 603.81.004 Gastos de Oficina | M92: =D92 -> 317.52 | N92: =CONCATENATE(F92," ",G92," ",H92," ",I92," ",J92," ",K92," ") -> Fernanda Sanchez Ruiz UBER * EATS PENDING CMX MEX Uber Eats Office expenses Snacks para la oficina .
A93: TRX1251 | B93: #5 | C93: 46067.417 | D93: 939.38 | E93: MXN | F93: Fernanda Sanchez Ruiz | G93: UBER * EATS PENDING CMX MEX | H93: Uber Eats | I93: Office expenses | J93: Botiquin | K93: . | L93: =VLOOKUP(B93,[1]Total!$B:$Q,16,0) -> 603.81.004 Gastos de Oficina | M93: =D93 -> 939.38 | N93: =CONCATENATE(F93," ",G93," ",H93," ",I93," ",J93," ",K93," ") -> Fernanda Sanchez Ruiz UBER * EATS PENDING CMX MEX Uber Eats Office expenses Botiquin .
A94: TRX1643 | B94: #5 | C94: 46067.417 | D94: 20 | E94: MXN | F94: Fernanda Sanchez Ruiz | G94: UBER *EATS HELP.UBER.C CMX MEX | H94: Uber Eats | I94: Office expenses | J94: Refill de botiquin | K94: . | L94: =VLOOKUP(B94,[1]Total!$B:$Q,16,0) -> 603.81.004 Gastos de Oficina | M94: =D94 -> 20 | N94: =CONCATENATE(F94," ",G94," ",H94," ",I94," ",J94," ",K94," ") -> Fernanda Sanchez Ruiz UBER *EATS HELP.UBER.C CMX MEX Uber Eats Office expenses Refill de botiquin .
A95: TRX1775 | B95: #5 | C95: 46067.417 | D95: 3142.4 | E95: MXN | F95: Fernanda Sanchez Ruiz | G95: UBER * EATS PENDING CMX MEX | H95: Uber Eats | I95: 0 | J95: 0 | K95: . | L95: =VLOOKUP(B95,[1]Total!$B:$Q,16,0) -> 603.81.004 Gastos de Oficina | M95: =D95 -> 3142.4 | N95: =CONCATENATE(F95," ",G95," ",H95," ",I95," ",J95," ",K95," ") -> Fernanda Sanchez Ruiz UBER * EATS PENDING CMX MEX Uber Eats 0 0 .
A96: TRX1734 | B96: #5 | C96: 46067.417 | D96: 40 | E96: MXN | F96: Fernanda Sanchez Ruiz | G96: UBER *EATS HELP.UBER.C CMX MEX | H96: Uber Eats | I96: 0 | J96: 0 | K96: . | L96: =VLOOKUP(B96,[1]Total!$B:$Q,16,0) -> 603.81.004 Gastos de Oficina | M96: =D96 -> 40 | N96: =CONCATENATE(F96," ",G96," ",H96," ",I96," ",J96," ",K96," ") -> Fernanda Sanchez Ruiz UBER *EATS HELP.UBER.C CMX MEX Uber Eats 0 0 .
A97: TRX1953 | B97: #5 | C97: 46071.417 | D97: 1707.95 | E97: MXN | F97: Fernanda Sanchez Ruiz | G97: SAMS VENTA EN LINEA MEXICO DF MEX | H97: Sam's Club | I97: 0 | J97: 0 | K97: . | L97: =VLOOKUP(B97,[1]Total!$B:$Q,16,0) -> 603.81.004 Gastos de Oficina | M97: =D97 -> 1707.95 | N97: =CONCATENATE(F97," ",G97," ",H97," ",I97," ",J97," ",K97," ") -> Fernanda Sanchez Ruiz SAMS VENTA EN LINEA MEXICO DF MEX Sam's Club 0 0 .
A98: TRX1925 | B98: #5 | C98: 46072.417 | D98: 99.94 | E98: MXN | F98: Fernanda Sanchez Ruiz | G98: UBER * PENDING CMX MEX | H98: Uber | I98: 0 | J98: 0 | K98: . | L98: =VLOOKUP(B98,[1]Total!$B:$Q,16,0) -> 603.81.004 Gastos de Oficina | M98: =D98 -> 99.94 | N98: =CONCATENATE(F98," ",G98," ",H98," ",I98," ",J98," ",K98," ") -> Fernanda Sanchez Ruiz UBER * PENDING CMX MEX Uber 0 0 .
A99: TRX1228 | B99: #5 | C99: 46073.417 | D99: 38.68 | E99: MXN | F99: Fernanda Sanchez Ruiz | G99: UBER * PENDING CMX MEX | H99: Uber | I99: 0 | J99: 0 | K99: . | L99: =VLOOKUP(B99,[1]Total!$B:$Q,16,0) -> 603.81.004 Gastos de Oficina | M99: =D99 -> 38.68 | N99: =CONCATENATE(F99," ",G99," ",H99," ",I99," ",J99," ",K99," ") -> Fernanda Sanchez Ruiz UBER * PENDING CMX MEX Uber 0 0 .
A100: TRX1222 | B100: #5 | C100: 46073.417 | D100: 29.96 | E100: MXN | F100: Fernanda Sanchez Ruiz | G100: UBER * PENDING CMX MEX | H100: Uber | I100: 0 | J100: 0 | K100: . | L100: =VLOOKUP(B100,[1]Total!$B:$Q,16,0) -> 603.81.004 Gastos de Oficina | M100: =D100 -> 29.96 | N100: =CONCATENATE(F100," ",G100," ",H100," ",I100," ",J100," ",K100," ") -> Fernanda Sanchez Ruiz UBER * PENDING CMX MEX Uber 0 0 .
A101: TRX1222 | B101: #6 | C101: 46058.417 | D101: 1149 | E101: MXN | F101: Fernando Sanchez Toledano | G101: AVIS WEB MXN MERIDA YUC MEX | H101: Avis | I101: Transaction cost | J101: Transaction cost | K101: Gasolina recolección Fer Marcelo | L101: =VLOOKUP(B101,[1]Total!$B:$Q,16,0) -> 602.16.000 Transporte | M101: =D101 -> 1149 | N101: =CONCATENATE(F101," ",G101," ",H101," ",I101," ",J101," ",K101," ") -> Fernando Sanchez Toledano AVIS WEB MXN MERIDA YUC MEX Avis Transaction cost Transaction cost Gasolina recolección Fer Marcelo
A102: TRX1202 | B102: #6 | C102: 46058.417 | D102: 91 | E102: MXN | F102: Fernando Sanchez Toledano | G102: DLO*DIDI RIDES MEXICO MEX | H102: Didi Chuxing | I102: Transaction cost | J102: Transaction cost | K102: Comida visita fer Marcelo | L102: =VLOOKUP(B102,[1]Total!$B:$Q,16,0) -> 602.16.000 Transporte | M102: =D102 -> 91 | N102: =CONCATENATE(F102," ",G102," ",H102," ",I102," ",J102," ",K102," ") -> Fernando Sanchez Toledano DLO*DIDI RIDES MEXICO MEX Didi Chuxing Transaction cost Transaction cost Comida visita fer Marcelo
...

Sheet Consolidación de datos 
A1: CODI | B1: #id user | C1: Swipe Date | D1: Amount | E1: MONEDA | F1: User | G1: Descriptor | H1: Merchant Name | I1: Expense Type | J1: DESCRIPCION DEL CARGO | K1: FOLIO DE FACTURA
A2: =IFERROR(__xludf.DUMMYFUNCTION("{QUERY('#2 Cesar'!A12:K1000,""where A is not null"");QUERY('#3 Cesar Uriel'!A12:K1000,""where A is not null"");QUERY('#4 Daniel Autrique'!A12:K1000,""where A is not null"");QUERY('#5 Fernanda'!A12:K1000,""where A is not null"");QUERY('#6 Fernando Sanchez'"&"!A12:K1000,""where A is not null"");QUERY('#7 Isaac'!A12:K1000,""where A is not null"");QUERY('#8 Jose Ignacio'!A12:K1000,""where A is not null"");QUERY('#9 Jose Maria'!A12:K1000,""where A is not null"");QUERY('#11 Juan Carlos'!A12:K1000,""where A is not "&"null"");QUERY('#13 Miguel'!A12:K1000,""where A is not null"");QUERY('#14 Patricio. '!A12:K1000,""where A is not null"");QUERY('#16 Rogelio'!A12:K1000,""where A is not null"");QUERY('#17 Sebastian'!A12:K1000,""where A is not null"");QUERY('#19 Daniel Aleja"&"ndro Castillo R'!A12:K1000,""where A is not null"");QUERY('#20 Gerardo Guadalupe Ruiz Huer'!A12:K1000,""where A is not null"");QUERY('#21 Jesus Gonzalez Grana'!A12:K1000,""where A is not null"");QUERY('#24 Andres Camacho'!A12:K1000,""where A is not null"""&");QUERY('#25 Jorge Estrada'!A12:K1000,""where A is not null"");QUERY('#26 Alexandra Ballesteros'!A12:K1000,""where A is not null"");QUERY('#28 Fernando Villalobos'!A12:K1000,""where A is not null"");QUERY('#30 Manuel Ibarra'!A12:K1000,""where A is not nul"&"l"");QUERY(' #31 Emiliano Cavazos'!A12:K1000,""where A is not null"");QUERY('#34 Juan Pablo Ramos'!A12:K1000,""where A is not null"");QUERY('#35 Termis'!A12:K1000,""where A is not null"");QUERY('#37 Angel Pantoja'!A12:K1000,""where A is not null"");QUERY("&"'#40 Gabriela Zacarias'!A12:K1000,""where A is not null"");QUERY('#41 Jose Arechavala'!A12:K1000,""where A is not null"");QUERY('#42 Rodrigo Perea'!A12:K1000,""where A is not null"");QUERY('#43 Pablo Ortiz'!A12:K1000,""where A is not null"");QUERY('#44 JP"&" Hammerstein'!A12:K1000,""where A is not null"");QUERY('#45 Erick Cival'!A12:K1000,""where A is not null"");QUERY('#46 Kallie Parchman'!A12:K1000,""where A is not null"");QUERY('#48 Andres Preza'!A12:K1000,""where A is not null"");QUERY('#49 Jahaziel Gala"&"n'!A12:K1000,""where A is not null"");QUERY('#51 Saul Murillo'!A12:K1000,""where A is not null"");QUERY('#52 Tommaso Rivetti'!A12:K1000,""where A is not null"");QUERY('#53 Monserrat Benitez'!A12:K1000,""where A is not null"");QUERY('#55 Gerardo Madrid'!A1"&"2:K1000,""where A is not null"");QUERY('#56 Carlos Ivan Gonzalez Merino'!A12:K1000,""where A is not null"");QUERY('#54 Mario Castorela'!A12:K1000,""where A is not null"");QUERY('#58 Jose Rosas'!A12:K1000,""where A is not null"");QUERY('#59 Mario Guadarram"&"a'!A12:K1000,""where A is not null"");QUERY('#60 Carlos Aleman'!A12:K1000,""where A is not null"");QUERY('#61 Jorge Diaz'!A12:K1000,""where A is not null"");QUERY('#62 Jorge Rojas'!A12:K1000,""where A is not null"");QUERY('#63 Diego Morodo'!A12:K1000,""wh"&"ere A is not null"");QUERY('#64 Erik Castillo'!A12:K1000,""where A is not null"");QUERY('#65 Diana Miranda'!A12:K1000,""where A is not null"");QUERY('#66 Jorge Ramirez'!A12:K1000,""where A is not null"");QUERY('#67 Gustavo Rivas'!A12:K1000,""where A is no"&"t null"");QUERY('#68 Alfonso Bello'!A12:K1000,""where A is not null"");QUERY('#69 Cole Anderson'!A12:K1000,""where A is not null"")}"),"TRX1286") -> TRX1286 | B2: =IFERROR(__xludf.DUMMYFUNCTION("""COMPUTED_VALUE"""),"#2") -> #2 | C2: =IFERROR(__xludf.DUMMYFUNCTION("""COMPUTED_VALUE"""),46056.4166666666) -> 46056.417 | D2: =IFERROR(__xludf.DUMMYFUNCTION("""COMPUTED_VALUE"""),3642.61) -> 3642.61 | E2: =IFERROR(__xludf.DUMMYFUNCTION("""COMPUTED_VALUE"""),"USD") -> USD | F2: =IFERROR(__xludf.DUMMYFUNCTION("""COMPUTED_VALUE"""),"Cesar Gonzales") -> Cesar Gonzales | G2: =IFERROR(__xludf.DUMMYFUNCTION("""COMPUTED_VALUE"""),"HASHICORP HCP SAN FRANCISCO USA") -> HASHICORP HCP SAN FRANCISCO USA | H2: =IFERROR(__xludf.DUMMYFUNCTION("""COMPUTED_VALUE"""),"Hashicorp") -> Hashicorp | I2: =IFERROR(__xludf.DUMMYFUNCTION("""COMPUTED_VALUE"""),"Tech&Product") -> Tech&Product | K2: =IFERROR(__xludf.DUMMYFUNCTION("""COMPUTED_VALUE"""),".") -> . | S2: 344.91 | T2: =VLOOKUP(S2,D:F,3,FALSE) -> #N/A | V2: #16 | W2: =VLOOKUP(V2,B:F,5,FALSE()) -> Rogelio Gamez
A3: =IFERROR(__xludf.DUMMYFUNCTION("""COMPUTED_VALUE"""),"TRX1246") -> TRX1246 | B3: =IFERROR(__xludf.DUMMYFUNCTION("""COMPUTED_VALUE"""),"#2") -> #2 | C3: =IFERROR(__xludf.DUMMYFUNCTION("""COMPUTED_VALUE"""),46058.4166666666) -> 46058.417 | D3: =IFERROR(__xludf.DUMMYFUNCTION("""COMPUTED_VALUE"""),15105.29) -> 15105.29 | E3: =IFERROR(__xludf.DUMMYFUNCTION("""COMPUTED_VALUE"""),"MXN") -> MXN | F3: =IFERROR(__xludf.DUMMYFUNCTION("""COMPUTED_VALUE"""),"Cesar Gonzales") -> Cesar Gonzales | G3: =IFERROR(__xludf.DUMMYFUNCTION("""COMPUTED_VALUE"""),"PAYU *GOOGLE CLOUD MIGUEL HIDALG MEX") -> PAYU *GOOGLE CLOUD MIGUEL HIDALG MEX | H3: =IFERROR(__xludf.DUMMYFUNCTION("""COMPUTED_VALUE"""),"Google Cloud") -> Google Cloud | I3: =IFERROR(__xludf.DUMMYFUNCTION("""COMPUTED_VALUE"""),"Tech&Product") -> Tech&Product | K3: =IFERROR(__xludf.DUMMYFUNCTION("""COMPUTED_VALUE"""),".") -> . | S3: 2802.46 | T3: =VLOOKUP(S3,D:F,3,FALSE) -> #N/A | V3: #2 | W3: =VLOOKUP(V3,B:F,5,FALSE()) -> Cesar Gonzales
A4: =IFERROR(__xludf.DUMMYFUNCTION("""COMPUTED_VALUE"""),"TRX1242") -> TRX1242 | B4: =IFERROR(__xludf.DUMMYFUNCTION("""COMPUTED_VALUE"""),"#2") -> #2 | C4: =IFERROR(__xludf.DUMMYFUNCTION("""COMPUTED_VALUE"""),46058.4166666666) -> 46058.417 | D4: =IFERROR(__xludf.DUMMYFUNCTION("""COMPUTED_VALUE"""),957.38) -> 957.38 | E4: =IFERROR(__xludf.DUMMYFUNCTION("""COMPUTED_VALUE"""),"MXN") -> MXN | F4: =IFERROR(__xludf.DUMMYFUNCTION("""COMPUTED_VALUE"""),"Cesar Gonzales") -> Cesar Gonzales | G4: =IFERROR(__xludf.DUMMYFUNCTION("""COMPUTED_VALUE"""),"PAYU *GOOGLE CLOUD MIGUEL HIDALG MEX") -> PAYU *GOOGLE CLOUD MIGUEL HIDALG MEX | H4: =IFERROR(__xludf.DUMMYFUNCTION("""COMPUTED_VALUE"""),"Google Cloud") -> Google Cloud | I4: =IFERROR(__xludf.DUMMYFUNCTION("""COMPUTED_VALUE"""),"Tech&Product") -> Tech&Product | K4: =IFERROR(__xludf.DUMMYFUNCTION("""COMPUTED_VALUE"""),".") -> . | S4: 69 | T4: =VLOOKUP(S4,D:F,3,FALSE) -> Rodrigo Perea | V4: #8 | W4: =VLOOKUP(V4,B:F,5,FALSE()) -> Jose Ignacio Martinez Flemate
A5: =IFERROR(__xludf.DUMMYFUNCTION("""COMPUTED_VALUE"""),"TRX1999") -> TRX1999 | B5: =IFERROR(__xludf.DUMMYFUNCTION("""COMPUTED_VALUE"""),"#2") -> #2 | C5: =IFERROR(__xludf.DUMMYFUNCTION("""COMPUTED_VALUE"""),46059.4173611111) -> 46059.417 | D5: =IFERROR(__xludf.DUMMYFUNCTION("""COMPUTED_VALUE"""),10214.06) -> 10214.06 | E5: =IFERROR(__xludf.DUMMYFUNCTION("""COMPUTED_VALUE"""),"USD") -> USD | F5: =IFERROR(__xludf.DUMMYFUNCTION("""COMPUTED_VALUE"""),"Cesar Gonzales") -> Cesar Gonzales | G5: =IFERROR(__xludf.DUMMYFUNCTION("""COMPUTED_VALUE"""),"GITHUB, INC. SAN FRANCISCO USA") -> GITHUB, INC. SAN FRANCISCO USA | H5: =IFERROR(__xludf.DUMMYFUNCTION("""COMPUTED_VALUE"""),"Github") -> Github | I5: =IFERROR(__xludf.DUMMYFUNCTION("""COMPUTED_VALUE"""),"Tech&Product") -> Tech&Product | K5: =IFERROR(__xludf.DUMMYFUNCTION("""COMPUTED_VALUE"""),".") -> . | S5: 79.94 | T5: =VLOOKUP(S5,D:F,3,FALSE) -> #N/A | V5: #60 | W5: =VLOOKUP(V5,B:F,5,FALSE()) -> #N/A
A6: =IFERROR(__xludf.DUMMYFUNCTION("""COMPUTED_VALUE"""),"TRX1875") -> TRX1875 | B6: =IFERROR(__xludf.DUMMYFUNCTION("""COMPUTED_VALUE"""),"#2") -> #2 | C6: =IFERROR(__xludf.DUMMYFUNCTION("""COMPUTED_VALUE"""),46063.4166666666) -> 46063.417 | D6: =IFERROR(__xludf.DUMMYFUNCTION("""COMPUTED_VALUE"""),6524.63) -> 6524.63 | E6: =IFERROR(__xludf.DUMMYFUNCTION("""COMPUTED_VALUE"""),"USD") -> USD | F6: =IFERROR(__xludf.DUMMYFUNCTION("""COMPUTED_VALUE"""),"Cesar Gonzales") -> Cesar Gonzales | G6: =IFERROR(__xludf.DUMMYFUNCTION("""COMPUTED_VALUE"""),"CURSOR, AI POWERED IDE NEW YORK USA") -> CURSOR, AI POWERED IDE NEW YORK USA | H6: =IFERROR(__xludf.DUMMYFUNCTION("""COMPUTED_VALUE"""),"Cursor Ai Powered Ide New York USA") -> Cursor Ai Powered Ide New York USA | I6: =IFERROR(__xludf.DUMMYFUNCTION("""COMPUTED_VALUE"""),"Tech&Product") -> Tech&Product | K6: =IFERROR(__xludf.DUMMYFUNCTION("""COMPUTED_VALUE"""),".") -> . | S6: 199.98 | T6: =VLOOKUP(S6,D:F,3,FALSE) -> #N/A | V6: #56 | W6: =VLOOKUP(V6,B:F,5,FALSE()) -> Carlos Ivan Gonzalez Merino
A7: =IFERROR(__xludf.DUMMYFUNCTION("""COMPUTED_VALUE"""),"TRX1596") -> TRX1596 | B7: =IFERROR(__xludf.DUMMYFUNCTION("""COMPUTED_VALUE"""),"#2") -> #2 | C7: =IFERROR(__xludf.DUMMYFUNCTION("""COMPUTED_VALUE"""),46065.4173611111) -> 46065.417 | D7: =IFERROR(__xludf.DUMMYFUNCTION("""COMPUTED_VALUE"""),906.2) -> 906.2 | E7: =IFERROR(__xludf.DUMMYFUNCTION("""COMPUTED_VALUE"""),"USD") -> USD | F7: =IFERROR(__xludf.DUMMYFUNCTION("""COMPUTED_VALUE"""),"Cesar Gonzales") -> Cesar Gonzales | G7: =IFERROR(__xludf.DUMMYFUNCTION("""COMPUTED_VALUE"""),"CURSOR USAGE JAN NEW YORK USA") -> CURSOR USAGE JAN NEW YORK USA | H7: =IFERROR(__xludf.DUMMYFUNCTION("""COMPUTED_VALUE"""),"Cursor Usage Jan New York USA") -> Cursor Usage Jan New York USA | I7: =IFERROR(__xludf.DUMMYFUNCTION("""COMPUTED_VALUE"""),"Tech&Product") -> Tech&Product | K7: =IFERROR(__xludf.DUMMYFUNCTION("""COMPUTED_VALUE"""),".") -> . | S7: 335.57 | T7: =VLOOKUP(S7,D:F,3,FALSE) -> #N/A | V7: #68 | W7: =VLOOKUP(V7,B:F,5,FALSE()) -> Jorge Armando Ramirez Perez
A8: =IFERROR(__xludf.DUMMYFUNCTION("""COMPUTED_VALUE"""),"TRX1641") -> TRX1641 | B8: =IFERROR(__xludf.DUMMYFUNCTION("""COMPUTED_VALUE"""),"#2") -> #2 | C8: =IFERROR(__xludf.DUMMYFUNCTION("""COMPUTED_VALUE"""),46065.4173611111) -> 46065.417 | D8: =IFERROR(__xludf.DUMMYFUNCTION("""COMPUTED_VALUE"""),7115.29) -> 7115.29 | E8: =IFERROR(__xludf.DUMMYFUNCTION("""COMPUTED_VALUE"""),"USD") -> USD | F8: =IFERROR(__xludf.DUMMYFUNCTION("""COMPUTED_VALUE"""),"Cesar Gonzales") -> Cesar Gonzales | G8: =IFERROR(__xludf.DUMMYFUNCTION("""COMPUTED_VALUE"""),"DATADOG, INC. NEW YORK USA") -> DATADOG, INC. NEW YORK USA | H8: =IFERROR(__xludf.DUMMYFUNCTION("""COMPUTED_VALUE"""),"Datadog") -> Datadog | I8: =IFERROR(__xludf.DUMMYFUNCTION("""COMPUTED_VALUE"""),"Tech&Product") -> Tech&Product | K8: =IFERROR(__xludf.DUMMYFUNCTION("""COMPUTED_VALUE"""),".") -> . | S8: 374.78 | T8: =VLOOKUP(S8,D:F,3,FALSE) -> #N/A | V8: #43 | W8: =VLOOKUP(V8,B:F,5,FALSE()) -> #N/A
A9: =IFERROR(__xludf.DUMMYFUNCTION("""COMPUTED_VALUE"""),"TRX1372") -> TRX1372 | B9: =IFERROR(__xludf.DUMMYFUNCTION("""COMPUTED_VALUE"""),"#2") -> #2 | C9: =IFERROR(__xludf.DUMMYFUNCTION("""COMPUTED_VALUE"""),46066.4166666666) -> 46066.417 | D9: =IFERROR(__xludf.DUMMYFUNCTION("""COMPUTED_VALUE"""),5964.72) -> 5964.72 | E9: =IFERROR(__xludf.DUMMYFUNCTION("""COMPUTED_VALUE"""),"MXN") -> MXN | F9: =IFERROR(__xludf.DUMMYFUNCTION("""COMPUTED_VALUE"""),"Cesar Gonzales") -> Cesar Gonzales | G9: =IFERROR(__xludf.DUMMYFUNCTION("""COMPUTED_VALUE"""),"STR*ODOO TECHNOLOGIES CIUDAD DE MEX MEX") -> STR*ODOO TECHNOLOGIES CIUDAD DE MEX MEX | H9: =IFERROR(__xludf.DUMMYFUNCTION("""COMPUTED_VALUE"""),"Str Odoo Technologies Ciudad De Mex Mex") -> Str Odoo Technologies Ciudad De Mex Mex | I9: =IFERROR(__xludf.DUMMYFUNCTION("""COMPUTED_VALUE"""),"Tech&Product") -> Tech&Product | K9: =IFERROR(__xludf.DUMMYFUNCTION("""COMPUTED_VALUE"""),".") -> . | S9: 33 | T9: =VLOOKUP(S9,D:F,3,FALSE) -> Erik Castillo | V9: #26 | W9: =VLOOKUP(V9,B:F,5,FALSE()) -> Karen Alexandra Ballesteros Contreras
A10: =IFERROR(__xludf.DUMMYFUNCTION("""COMPUTED_VALUE"""),"TRX1245") -> TRX1245 | B10: =IFERROR(__xludf.DUMMYFUNCTION("""COMPUTED_VALUE"""),"#2") -> #2 | C10: =IFERROR(__xludf.DUMMYFUNCTION("""COMPUTED_VALUE"""),46066.4173611111) -> 46066.417 | D10: =IFERROR(__xludf.DUMMYFUNCTION("""COMPUTED_VALUE"""),1083.21) -> 1083.21 | E10: =IFERROR(__xludf.DUMMYFUNCTION("""COMPUTED_VALUE"""),"USD") -> USD | F10: =IFERROR(__xludf.DUMMYFUNCTION("""COMPUTED_VALUE"""),"Cesar Gonzales") -> Cesar Gonzales | G10: =IFERROR(__xludf.DUMMYFUNCTION("""COMPUTED_VALUE"""),"AUGMENT CODE PALO ALTO USA") -> AUGMENT CODE PALO ALTO USA | H10: =IFERROR(__xludf.DUMMYFUNCTION("""COMPUTED_VALUE"""),"Augment Code Palo Alto USA") -> Augment Code Palo Alto USA | I10: =IFERROR(__xludf.DUMMYFUNCTION("""COMPUTED_VALUE"""),"Tech&Product") -> Tech&Product | K10: =IFERROR(__xludf.DUMMYFUNCTION("""COMPUTED_VALUE"""),".") -> . | S10: 4126.16 | T10: =VLOOKUP(S10,D:F,3,FALSE) -> #N/A | V10: #30 | W10: =VLOOKUP(V10,B:F,5,FALSE()) -> Manuel Ibarra Cebreros
A11: =IFERROR(__xludf.DUMMYFUNCTION("""COMPUTED_VALUE"""),"TRX1378") -> TRX1378 | B11: =IFERROR(__xludf.DUMMYFUNCTION("""COMPUTED_VALUE"""),"#2") -> #2 | C11: =IFERROR(__xludf.DUMMYFUNCTION("""COMPUTED_VALUE"""),46069.4166666666) -> 46069.417 | D11: =IFERROR(__xludf.DUMMYFUNCTION("""COMPUTED_VALUE"""),14399.42) -> 14399.42 | E11: =IFERROR(__xludf.DUMMYFUNCTION("""COMPUTED_VALUE"""),"USD") -> USD | F11: =IFERROR(__xludf.DUMMYFUNCTION("""COMPUTED_VALUE"""),"Cesar Gonzales") -> Cesar Gonzales | G11: =IFERROR(__xludf.DUMMYFUNCTION("""COMPUTED_VALUE"""),"AUTH0.COM SAN FRANCISCO USA") -> AUTH0.COM SAN FRANCISCO USA | H11: =IFERROR(__xludf.DUMMYFUNCTION("""COMPUTED_VALUE"""),"Auth0") -> Auth0 | I11: =IFERROR(__xludf.DUMMYFUNCTION("""COMPUTED_VALUE"""),"Tech&Product") -> Tech&Product | K11: =IFERROR(__xludf.DUMMYFUNCTION("""COMPUTED_VALUE"""),".") -> . | S11: 78 | T11: =VLOOKUP(S11,D:F,3,FALSE) -> Karen Alexandra Ballesteros Contreras | V11: #66 | W11: =VLOOKUP(V11,B:F,5,FALSE()) -> Erik Castillo
A12: =IFERROR(__xludf.DUMMYFUNCTION("""COMPUTED_VALUE"""),"TRX1821") -> TRX1821 | B12: =IFERROR(__xludf.DUMMYFUNCTION("""COMPUTED_VALUE"""),"#2") -> #2 | C12: =IFERROR(__xludf.DUMMYFUNCTION("""COMPUTED_VALUE"""),46073.4173611111) -> 46073.417 | D12: =IFERROR(__xludf.DUMMYFUNCTION("""COMPUTED_VALUE"""),471.63) -> 471.63 | E12: =IFERROR(__xludf.DUMMYFUNCTION("""COMPUTED_VALUE"""),"USD") -> USD | F12: =IFERROR(__xludf.DUMMYFUNCTION("""COMPUTED_VALUE"""),"Cesar Gonzales") -> Cesar Gonzales | G12: =IFERROR(__xludf.DUMMYFUNCTION("""COMPUTED_VALUE"""),"CURSOR, AI POWERED IDE NEW YORK USA") -> CURSOR, AI POWERED IDE NEW YORK USA | H12: =IFERROR(__xludf.DUMMYFUNCTION("""COMPUTED_VALUE"""),"Cursor Ai Powered Ide New York USA") -> Cursor Ai Powered Ide New York USA | I12: =IFERROR(__xludf.DUMMYFUNCTION("""COMPUTED_VALUE"""),"Tech&Product") -> Tech&Product | K12: =IFERROR(__xludf.DUMMYFUNCTION("""COMPUTED_VALUE"""),".") -> . | S12: 176.59 | T12: =VLOOKUP(S12,D:F,3,FALSE) -> #N/A | V12: #40 | W12: =VLOOKUP(V12,B:F,5,FALSE()) -> Gabriela Zacarias Aguirre
A13: =IFERROR(__xludf.DUMMYFUNCTION("""COMPUTED_VALUE"""),"TRX1080") -> TRX1080 | B13: =IFERROR(__xludf.DUMMYFUNCTION("""COMPUTED_VALUE"""),"#2") -> #2 | C13: =IFERROR(__xludf.DUMMYFUNCTION("""COMPUTED_VALUE"""),46075.4173611111) -> 46075.417 | D13: =IFERROR(__xludf.DUMMYFUNCTION("""COMPUTED_VALUE"""),2619.98) -> 2619.98 | E13: =IFERROR(__xludf.DUMMYFUNCTION("""COMPUTED_VALUE"""),"USD") -> USD | F13: =IFERROR(__xludf.DUMMYFUNCTION("""COMPUTED_VALUE"""),"Cesar Gonzales") -> Cesar Gonzales | G13: =IFERROR(__xludf.DUMMYFUNCTION("""COMPUTED_VALUE"""),"ATLASSIAN SAN FRANCISCO USA") -> ATLASSIAN SAN FRANCISCO USA | H13: =IFERROR(__xludf.DUMMYFUNCTION("""COMPUTED_VALUE"""),"Atlassian") -> Atlassian | I13: =IFERROR(__xludf.DUMMYFUNCTION("""COMPUTED_VALUE"""),"Tech&Product") -> Tech&Product | K13: =IFERROR(__xludf.DUMMYFUNCTION("""COMPUTED_VALUE"""),".") -> . | S13: 152 | T13: =VLOOKUP(S13,D:F,3,FALSE) -> #N/A | V13: #53 | W13: =VLOOKUP(V13,B:F,5,FALSE()) -> Monserrat Benitez
A14: =IFERROR(__xludf.DUMMYFUNCTION("""COMPUTED_VALUE"""),"TRX1119") -> TRX1119 | B14: =IFERROR(__xludf.DUMMYFUNCTION("""COMPUTED_VALUE"""),"#2") -> #2 | C14: =IFERROR(__xludf.DUMMYFUNCTION("""COMPUTED_VALUE"""),46077.4166666666) -> 46077.417 | D14: =IFERROR(__xludf.DUMMYFUNCTION("""COMPUTED_VALUE"""),3853.97) -> 3853.97 | E14: =IFERROR(__xludf.DUMMYFUNCTION("""COMPUTED_VALUE"""),"USD") -> USD | F14: =IFERROR(__xludf.DUMMYFUNCTION("""COMPUTED_VALUE"""),"Cesar Gonzales") -> Cesar Gonzales | G14: =IFERROR(__xludf.DUMMYFUNCTION("""COMPUTED_VALUE"""),"RETOOL SAN FRANCISCO USA") -> RETOOL SAN FRANCISCO USA | H14: =IFERROR(__xludf.DUMMYFUNCTION("""COMPUTED_VALUE"""),"Retool") -> Retool | I14: =IFERROR(__xludf.DUMMYFUNCTION("""COMPUTED_VALUE"""),"Tech&Product") -> Tech&Product | K14: =IFERROR(__xludf.DUMMYFUNCTION("""COMPUTED_VALUE"""),".") -> . | S14: 99 | T14: =VLOOKUP(S14,D:F,3,FALSE) -> #N/A | V14: #67 | W14: =VLOOKUP(V14,B:F,5,FALSE()) -> #N/A
A15: =IFERROR(__xludf.DUMMYFUNCTION("""COMPUTED_VALUE"""),"TRX1124") -> TRX1124 | B15: =IFERROR(__xludf.DUMMYFUNCTION("""COMPUTED_VALUE"""),"#2") -> #2 | C15: =IFERROR(__xludf.DUMMYFUNCTION("""COMPUTED_VALUE"""),46077.4166666666) -> 46077.417 | D15: =IFERROR(__xludf.DUMMYFUNCTION("""COMPUTED_VALUE"""),8235.56) -> 8235.56 | E15: =IFERROR(__xludf.DUMMYFUNCTION("""COMPUTED_VALUE"""),"USD") -> USD | F15: =IFERROR(__xludf.DUMMYFUNCTION("""COMPUTED_VALUE"""),"Cesar Gonzales") -> Cesar Gonzales | G15: =IFERROR(__xludf.DUMMYFUNCTION("""COMPUTED_VALUE"""),"METABASE INC SPRING VALLEY USA") -> METABASE INC SPRING VALLEY USA | H15: =IFERROR(__xludf.DUMMYFUNCTION("""COMPUTED_VALUE"""),"Metabase") -> Metabase | I15: =IFERROR(__xludf.DUMMYFUNCTION("""COMPUTED_VALUE"""),"Tech&Product") -> Tech&Product | K15: =IFERROR(__xludf.DUMMYFUNCTION("""COMPUTED_VALUE"""),".") -> . | S15: 102 | T15: =VLOOKUP(S15,D:F,3,FALSE) -> #N/A | V15: #9 | W15: =VLOOKUP(V15,B:F,5,FALSE()) -> Jose Maria Garcia Hernandez
A16: =IFERROR(__xludf.DUMMYFUNCTION("""COMPUTED_VALUE"""),"TRX1127") -> TRX1127 | B16: =IFERROR(__xludf.DUMMYFUNCTION("""COMPUTED_VALUE"""),"#2") -> #2 | C16: =IFERROR(__xludf.DUMMYFUNCTION("""COMPUTED_VALUE"""),46077.4166666666) -> 46077.417 | D16: =IFERROR(__xludf.DUMMYFUNCTION("""COMPUTED_VALUE"""),7106.33) -> 7106.33 | E16: =IFERROR(__xludf.DUMMYFUNCTION("""COMPUTED_VALUE"""),"USD") -> USD | F16: =IFERROR(__xludf.DUMMYFUNCTION("""COMPUTED_VALUE"""),"Cesar Gonzales") -> Cesar Gonzales | G16: =IFERROR(__xludf.DUMMYFUNCTION("""COMPUTED_VALUE"""),"Microsoft-G142443073 msbill.info USA") -> Microsoft-G142443073 msbill.info USA | H16: =IFERROR(__xludf.DUMMYFUNCTION("""COMPUTED_VALUE"""),"Microsoft") -> Microsoft | I16: =IFERROR(__xludf.DUMMYFUNCTION("""COMPUTED_VALUE"""),"Tech&Product") -> Tech&Product | K16: =IFERROR(__xludf.DUMMYFUNCTION("""COMPUTED_VALUE"""),".") -> . | S16: 5296 | T16: =VLOOKUP(S16,D:F,3,FALSE) -> #N/A | V16: #13 | W16: =VLOOKUP(V16,B:F,5,FALSE()) -> Miguel De Lascurain
A17: =IFERROR(__xludf.DUMMYFUNCTION("""COMPUTED_VALUE"""),"TRX1239") -> TRX1239 | B17: =IFERROR(__xludf.DUMMYFUNCTION("""COMPUTED_VALUE"""),"#3") -> #3 | C17: =IFERROR(__xludf.DUMMYFUNCTION("""COMPUTED_VALUE"""),46058.4166666666) -> 46058.417 | D17: =IFERROR(__xludf.DUMMYFUNCTION("""COMPUTED_VALUE"""),1130) -> 1130 | E17: =IFERROR(__xludf.DUMMYFUNCTION("""COMPUTED_VALUE"""),"MXN") -> MXN | F17: =IFERROR(__xludf.DUMMYFUNCTION("""COMPUTED_VALUE"""),"Cesar Uriel Romo Trillo") -> Cesar Uriel Romo Trillo | G17: =IFERROR(__xludf.DUMMYFUNCTION("""COMPUTED_VALUE"""),"HAMMER STRONG CIUDAD DE MEX MEX") -> HAMMER STRONG CIUDAD DE MEX MEX | H17: =IFERROR(__xludf.DUMMYFUNCTION("""COMPUTED_VALUE"""),"Hammer Strong Ciudad De Mex Mex") -> Hammer Strong Ciudad De Mex Mex | I17: =IFERROR(__xludf.DUMMYFUNCTION("""COMPUTED_VALUE"""),"Sales") -> Sales | J17: =IFERROR(__xludf.DUMMYFUNCTION("""COMPUTED_VALUE"""),"Compra de Pulidora y discos para obra Grajales Robles PO1129") -> Compra de Pulidora y discos para obra Grajales Robles PO1129 | K17: =IFERROR(__xludf.DUMMYFUNCTION("""COMPUTED_VALUE"""),"TICKET") -> TICKET | S17: 102 | T17: =VLOOKUP(S17,D:F,3,FALSE) -> #N/A | V17: #64 | W17: =VLOOKUP(V17,B:F,5,FALSE()) -> Jorge Rojas
A18: =IFERROR(__xludf.DUMMYFUNCTION("""COMPUTED_VALUE"""),"TRX1151") -> TRX1151 | B18: =IFERROR(__xludf.DUMMYFUNCTION("""COMPUTED_VALUE"""),"#3") -> #3 | C18: =IFERROR(__xludf.DUMMYFUNCTION("""COMPUTED_VALUE"""),46059.4173611111) -> 46059.417 | D18: =IFERROR(__xludf.DUMMYFUNCTION("""COMPUTED_VALUE"""),344.25) -> 344.25 | E18: =IFERROR(__xludf.DUMMYFUNCTION("""COMPUTED_VALUE"""),"MXN") -> MXN | F18: =IFERROR(__xludf.DUMMYFUNCTION("""COMPUTED_VALUE"""),"Cesar Uriel Romo Trillo") -> Cesar Uriel Romo Trillo | G18: =IFERROR(__xludf.DUMMYFUNCTION("""COMPUTED_VALUE"""),"GAS JUVITA MEXICO DF MEX") -> GAS JUVITA MEXICO DF MEX | H18: =IFERROR(__xludf.DUMMYFUNCTION("""COMPUTED_VALUE"""),"Gas Juvita Mexico Df Mex") -> Gas Juvita Mexico Df Mex | I18: =IFERROR(__xludf.DUMMYFUNCTION("""COMPUTED_VALUE"""),"Sales") -> Sales | J18: =IFERROR(__xludf.DUMMYFUNCTION("""COMPUTED_VALUE"""),"Gasolina visita desmontaje de Grua Grajales Robles PO1129") -> Gasolina visita desmontaje de Grua Grajales Robles PO1129 | K18: =IFERROR(__xludf.DUMMYFUNCTION("""COMPUTED_VALUE"""),"TICKET") -> TICKET | S18: 12818 | T18: =VLOOKUP(S18,D:F,3,FALSE) -> #N/A | V18: #71 | W18: =VLOOKUP(V18,B:F,5,FALSE()) -> #N/A
A19: =IFERROR(__xludf.DUMMYFUNCTION("""COMPUTED_VALUE"""),"TRX1538") -> TRX1538 | B19: =IFERROR(__xludf.DUMMYFUNCTION("""COMPUTED_VALUE"""),"#3") -> #3 | C19: =IFERROR(__xludf.DUMMYFUNCTION("""COMPUTED_VALUE"""),46060.4173611111) -> 46060.417 | D19: =IFERROR(__xludf.DUMMYFUNCTION("""COMPUTED_VALUE"""),803.6) -> 803.6 | E19: =IFERROR(__xludf.DUMMYFUNCTION("""COMPUTED_VALUE"""),"MXN") -> MXN | F19: =IFERROR(__xludf.DUMMYFUNCTION("""COMPUTED_VALUE"""),"Cesar Uriel Romo Trillo") -> Cesar Uriel Romo Trillo | G19: =IFERROR(__xludf.DUMMYFUNCTION("""COMPUTED_VALUE"""),"GASOLINERA COMB ERMITA CIUDAD DE MEX MEX") -> GASOLINERA COMB ERMITA CIUDAD DE MEX MEX | H19: =IFERROR(__xludf.DUMMYFUNCTION("""COMPUTED_VALUE"""),"Gasolinera Comb Ermita Ciudad De Mex Mex") -> Gasolinera Comb Ermita Ciudad De Mex Mex | I19: =IFERROR(__xludf.DUMMYFUNCTION("""COMPUTED_VALUE"""),"Sales") -> Sales | J19: =IFERROR(__xludf.DUMMYFUNCTION("""COMPUTED_VALUE"""),"Gasolina para Malacate Grajales Robles PO 1129") -> Gasolina para Malacate Grajales Robles PO 1129 | K19: =IFERROR(__xludf.DUMMYFUNCTION("""COMPUTED_VALUE"""),"TICKET") -> TICKET | S19: 173.12 | T19: =VLOOKUP(S19,D:F,3,FALSE) -> #N/A | V19: #28 | W19: =VLOOKUP(V19,B:F,5,FALSE()) -> Fernando Villalobos Lara
A20: =IFERROR(__xludf.DUMMYFUNCTION("""COMPUTED_VALUE"""),"TRX1068") -> TRX1068 | B20: =IFERROR(__xludf.DUMMYFUNCTION("""COMPUTED_VALUE"""),"#3") -> #3 | C20: =IFERROR(__xludf.DUMMYFUNCTION("""COMPUTED_VALUE"""),46065.4173611111) -> 46065.417 | D20: =IFERROR(__xludf.DUMMYFUNCTION("""COMPUTED_VALUE"""),574) -> 574 | E20: =IFERROR(__xludf.DUMMYFUNCTION("""COMPUTED_VALUE"""),"MXN") -> MXN | F20: =IFERROR(__xludf.DUMMYFUNCTION("""COMPUTED_VALUE"""),"Cesar Uriel Romo Trillo") -> Cesar Uriel Romo Trillo | G20: =IFERROR(__xludf.DUMMYFUNCTION("""COMPUTED_VALUE"""),"GASOLINERA COMB ERMITA CIUDAD DE MEX MEX") -> GASOLINERA COMB ERMITA CIUDAD DE MEX MEX | H20: =IFERROR(__xludf.DUMMYFUNCTION("""COMPUTED_VALUE"""),"Gasolinera Comb Ermita Ciudad De Mex Mex") -> Gasolinera Comb Ermita Ciudad De Mex Mex | I20: =IFERROR(__xludf.DUMMYFUNCTION("""COMPUTED_VALUE"""),"Sales") -> Sales | J20: =IFERROR(__xludf.DUMMYFUNCTION("""COMPUTED_VALUE"""),"Gasolina visita equipo Elvic PO1129") -> Gasolina visita equipo Elvic PO1129 | K20: =IFERROR(__xludf.DUMMYFUNCTION("""COMPUTED_VALUE"""),"TICKET") -> TICKET | S20: 70 | T20: =VLOOKUP(S20,D:F,3,FALSE) -> Fernanda Sanchez Ruiz | V20: #41 | W20: =VLOOKUP(V20,B:F,5,FALSE()) -> Jose Arechavala
A21: =IFERROR(__xludf.DUMMYFUNCTION("""COMPUTED_VALUE"""),"TRX1608") -> TRX1608 | B21: =IFERROR(__xludf.DUMMYFUNCTION("""COMPUTED_VALUE"""),"#3") -> #3 | C21: =IFERROR(__xludf.DUMMYFUNCTION("""COMPUTED_VALUE"""),46065.4173611111) -> 46065.417 | D21: =IFERROR(__xludf.DUMMYFUNCTION("""COMPUTED_VALUE"""),767) -> 767 | E21: =IFERROR(__xludf.DUMMYFUNCTION("""COMPUTED_VALUE"""),"MXN") -> MXN | F21: =IFERROR(__xludf.DUMMYFUNCTION("""COMPUTED_VALUE"""),"Cesar Uriel Romo Trillo") -> Cesar Uriel Romo Trillo | G21: =IFERROR(__xludf.DUMMYFUNCTION("""COMPUTED_VALUE"""),"MAMA S PIZZA CIUDAD DE MEX MEX") -> MAMA S PIZZA CIUDAD DE MEX MEX | H21: =IFERROR(__xludf.DUMMYFUNCTION("""COMPUTED_VALUE"""),"Mama S Pizza Ciudad De Mex Mex") -> Mama S Pizza Ciudad De Mex Mex | I21: =IFERROR(__xludf.DUMMYFUNCTION("""COMPUTED_VALUE"""),"Sales") -> Sales | J21: =IFERROR(__xludf.DUMMYFUNCTION("""COMPUTED_VALUE"""),"Comida equipo Elvic PO 1129") -> Comida equipo Elvic PO 1129 | K21: =IFERROR(__xludf.DUMMYFUNCTION("""COMPUTED_VALUE"""),"TICKET") -> TICKET | S21: 309 | T21: =VLOOKUP(S21,D:F,3,FALSE) -> #N/A | V21: #51 | W21: =VLOOKUP(V21,B:F,5,FALSE()) -> #N/A
A22: =IFERROR(__xludf.DUMMYFUNCTION("""COMPUTED_VALUE"""),"TRX1618") -> TRX1618 | B22: =IFERROR(__xludf.DUMMYFUNCTION("""COMPUTED_VALUE"""),"#3") -> #3 | C22: =IFERROR(__xludf.DUMMYFUNCTION("""COMPUTED_VALUE"""),46071.4173611111) -> 46071.417 | D22: =IFERROR(__xludf.DUMMYFUNCTION("""COMPUTED_VALUE"""),918.4) -> 918.4 | E22: =IFERROR(__xludf.DUMMYFUNCTION("""COMPUTED_VALUE"""),"MXN") -> MXN | F22: =IFERROR(__xludf.DUMMYFUNCTION("""COMPUTED_VALUE"""),"Cesar Uriel Romo Trillo") -> Cesar Uriel Romo Trillo | G22: =IFERROR(__xludf.DUMMYFUNCTION("""COMPUTED_VALUE"""),"GASOLINERA COMB ERMITA CIUDAD DE MEX MEX") -> GASOLINERA COMB ERMITA CIUDAD DE MEX MEX | H22: =IFERROR(__xludf.DUMMYFUNCTION("""COMPUTED_VALUE"""),"Gasolinera Comb Ermita Ciudad De Mex Mex") -> Gasolinera Comb Ermita Ciudad De Mex Mex | I22: =IFERROR(__xludf.DUMMYFUNCTION("""COMPUTED_VALUE"""),"Sales") -> Sales | J22: =IFERROR(__xludf.DUMMYFUNCTION("""COMPUTED_VALUE"""),"Gasolina Visita deal nuevo Grupo GSA") -> Gasolina Visita deal nuevo Grupo GSA | K22: =IFERROR(__xludf.DUMMYFUNCTION("""COMPUTED_VALUE"""),"TICKET") -> TICKET | S22: 14141.37 | T22: =VLOOKUP(S22,D:F,3,FALSE) -> #N/A | V22: #55 | W22: =VLOOKUP(V22,B:F,5,FALSE()) -> Gerardo Madrid
A23: =IFERROR(__xludf.DUMMYFUNCTION("""COMPUTED_VALUE"""),"TRX1068") -> TRX1068 | B23: =IFERROR(__xludf.DUMMYFUNCTION("""COMPUTED_VALUE"""),"#3") -> #3 | C23: =IFERROR(__xludf.DUMMYFUNCTION("""COMPUTED_VALUE"""),46075.4166666666) -> 46075.417 | D23: =IFERROR(__xludf.DUMMYFUNCTION("""COMPUTED_VALUE"""),344.4) -> 344.4 | E23: =IFERROR(__xludf.DUMMYFUNCTION("""COMPUTED_VALUE"""),"MXN") -> MXN | F23: =IFERROR(__xludf.DUMMYFUNCTION("""COMPUTED_VALUE"""),"Cesar Uriel Romo Trillo") -> Cesar Uriel Romo Trillo | G23: =IFERROR(__xludf.DUMMYFUNCTION("""COMPUTED_VALUE"""),"COMBUSTIBLE ERMITA CIUDAD DE MEX MEX") -> COMBUSTIBLE ERMITA CIUDAD DE MEX MEX | H23: =IFERROR(__xludf.DUMMYFUNCTION("""COMPUTED_VALUE"""),"Combustible Ermita Ciudad De Mex Mex") -> Combustible Ermita Ciudad De Mex Mex | I23: =IFERROR(__xludf.DUMMYFUNCTION("""COMPUTED_VALUE"""),"Sales") -> Sales | J23: =IFERROR(__xludf.DUMMYFUNCTION("""COMPUTED_VALUE"""),"Gasolina Visita Grajales Robles PO 1129, visita obra Parque Churubusco (nuevo deal), Visita Syvasa Calidad RFQ 3254 ") -> Gasolina Visita Grajales Robles PO 1129, visita obra Parque Churubusco (nuevo deal), Visita Syvasa Calidad RFQ 3254 | K23: =IFERROR(__xludf.DUMMYFUNCTION("""COMPUTED_VALUE"""),"TICKET") -> TICKET | S23: 211.71 | T23: =VLOOKUP(S23,D:F,3,FALSE) -> #N/A | V23: #19 | W23: =VLOOKUP(V23,B:F,5,FALSE()) -> Daniel Alejandro Castillo Rivera
A24: =IFERROR(__xludf.DUMMYFUNCTION("""COMPUTED_VALUE"""),"TRX1098") -> TRX1098 | B24: =IFERROR(__xludf.DUMMYFUNCTION("""COMPUTED_VALUE"""),"#3") -> #3 | C24: =IFERROR(__xludf.DUMMYFUNCTION("""COMPUTED_VALUE"""),46076.4166666666) -> 46076.417 | D24: =IFERROR(__xludf.DUMMYFUNCTION("""COMPUTED_VALUE"""),142.19) -> 142.19 | E24: =IFERROR(__xludf.DUMMYFUNCTION("""COMPUTED_VALUE"""),"MXN") -> MXN | F24: =IFERROR(__xludf.DUMMYFUNCTION("""COMPUTED_VALUE"""),"Cesar Uriel Romo Trillo") -> Cesar Uriel Romo Trillo | G24: =IFERROR(__xludf.DUMMYFUNCTION("""COMPUTED_VALUE"""),"D LOCAL*REST DIDIFOOD CIUDAD DE MEX MEX") -> D LOCAL*REST DIDIFOOD CIUDAD DE MEX MEX | H24: =IFERROR(__xludf.DUMMYFUNCTION("""COMPUTED_VALUE"""),"D Local Rest Didifood Ciudad De Mex Mex") -> D Local Rest Didifood Ciudad De Mex Mex | I24: =IFERROR(__xludf.DUMMYFUNCTION("""COMPUTED_VALUE"""),"Sales") -> Sales | J24: =IFERROR(__xludf.DUMMYFUNCTION("""COMPUTED_VALUE"""),"Compra de candado GRAJALES ROBLES PO 1129") -> Compra de candado GRAJALES ROBLES PO 1129 | K24: =IFERROR(__xludf.DUMMYFUNCTION("""COMPUTED_VALUE"""),"TICKET") -> TICKET | S24: 217.63 | T24: =VLOOKUP(S24,D:F,3,FALSE) -> #N/A | V24: #31 | W24: =VLOOKUP(V24,B:F,5,FALSE()) -> Emiliano Cavazos
A25: =IFERROR(__xludf.DUMMYFUNCTION("""COMPUTED_VALUE"""),"TRX1288") -> TRX1288 | B25: =IFERROR(__xludf.DUMMYFUNCTION("""COMPUTED_VALUE"""),"#4") -> #4 | C25: =IFERROR(__xludf.DUMMYFUNCTION("""COMPUTED_VALUE"""),46056.4166666666) -> 46056.417 | D25: =IFERROR(__xludf.DUMMYFUNCTION("""COMPUTED_VALUE"""),915.4) -> 915.4 | E25: =IFERROR(__xludf.DUMMYFUNCTION("""COMPUTED_VALUE"""),"MXN") -> MXN | F25: =IFERROR(__xludf.DUMMYFUNCTION("""COMPUTED_VALUE"""),"Daniel Autrique Echeveste") -> Daniel Autrique Echeveste | G25: =IFERROR(__xludf.DUMMYFUNCTION("""COMPUTED_VALUE"""),"LPQ AICM T1 SALA 8 1 CIUDAD DE MEX MEX") -> LPQ AICM T1 SALA 8 1 CIUDAD DE MEX MEX | H25: =IFERROR(__xludf.DUMMYFUNCTION("""COMPUTED_VALUE"""),"L") -> L | I25: =IFERROR(__xludf.DUMMYFUNCTION("""COMPUTED_VALUE"""),"Recruiting") -> Recruiting | J25: =IFERROR(__xludf.DUMMYFUNCTION("""COMPUTED_VALUE"""),"LinkedIn") -> LinkedIn | K25: =IFERROR(__xludf.DUMMYFUNCTION("""COMPUTED_VALUE"""),".") -> . | S25: 314.35 | T25: =VLOOKUP(S25,D:F,3,FALSE) -> #N/A | V25: #24 | W25: =VLOOKUP(V25,B:F,5,FALSE()) -> Andres Camacho Herrera
A26: =IFERROR(__xludf.DUMMYFUNCTION("""COMPUTED_VALUE"""),"TRX1279") -> TRX1279 | B26: =IFERROR(__xludf.DUMMYFUNCTION("""COMPUTED_VALUE"""),"#4") -> #4 | C26: =IFERROR(__xludf.DUMMYFUNCTION("""COMPUTED_VALUE"""),46056.4166666666) -> 46056.417 | D26: =IFERROR(__xludf.DUMMYFUNCTION("""COMPUTED_VALUE"""),704.7) -> 704.7 | E26: =IFERROR(__xludf.DUMMYFUNCTION("""COMPUTED_VALUE"""),"USD") -> USD | F26: =IFERROR(__xludf.DUMMYFUNCTION("""COMPUTED_VALUE"""),"Daniel Autrique Echeveste") -> Daniel Autrique Echeveste | G26: =IFERROR(__xludf.DUMMYFUNCTION("""COMPUTED_VALUE"""),"CURB MOBILITY ASTORIA USA") -> CURB MOBILITY ASTORIA USA | H26: =IFERROR(__xludf.DUMMYFUNCTION("""COMPUTED_VALUE"""),"Curb Mobility") -> Curb Mobility | I26: =IFERROR(__xludf.DUMMYFUNCTION("""COMPUTED_VALUE"""),"Sales") -> Sales | J26: =IFERROR(__xludf.DUMMYFUNCTION("""COMPUTED_VALUE"""),"Vuelo a chicago Radioflyer") -> Vuelo a chicago Radioflyer | K26: =IFERROR(__xludf.DUMMYFUNCTION("""COMPUTED_VALUE"""),".") -> . | S26: 492.45 | T26: =VLOOKUP(S26,D:F,3,FALSE) -> #N/A | V26: #52 | W26: =VLOOKUP(V26,B:F,5,FALSE()) -> Tommaso Rivetti Vinea
A27: =IFERROR(__xludf.DUMMYFUNCTION("""COMPUTED_VALUE"""),"TRX1272") -> TRX1272 | B27: =IFERROR(__xludf.DUMMYFUNCTION("""COMPUTED_VALUE"""),"#4") -> #4 | C27: =IFERROR(__xludf.DUMMYFUNCTION("""COMPUTED_VALUE"""),46057.4166666666) -> 46057.417 | D27: =IFERROR(__xludf.DUMMYFUNCTION("""COMPUTED_VALUE"""),1216.2) -> 1216.2 | E27: =IFERROR(__xludf.DUMMYFUNCTION("""COMPUTED_VALUE"""),"USD") -> USD | F27: =IFERROR(__xludf.DUMMYFUNCTION("""COMPUTED_VALUE"""),"Daniel Autrique Echeveste") -> Daniel Autrique Echeveste | G27: =IFERROR(__xludf.DUMMYFUNCTION("""COMPUTED_VALUE"""),"TCOLV - Naughty Patt LAS VEGAS USA") -> TCOLV - Naughty Patt LAS VEGAS USA | H27: =IFERROR(__xludf.DUMMYFUNCTION("""COMPUTED_VALUE"""),"Tcolv Naughty Patt Las Vegas USA") -> Tcolv Naughty Patt Las Vegas USA | I27: =IFERROR(__xludf.DUMMYFUNCTION("""COMPUTED_VALUE"""),"Sales") -> Sales | K27: =IFERROR(__xludf.DUMMYFUNCTION("""COMPUTED_VALUE"""),".") -> . | S27: 69 | T27: =VLOOKUP(S27,D:F,3,FALSE) -> Rodrigo Perea | V27: #69 | W27: =VLOOKUP(V27,B:F,5,FALSE()) -> Gustavo Rivas
A28: =IFERROR(__xludf.DUMMYFUNCTION("""COMPUTED_VALUE"""),"TRX1271") -> TRX1271 | B28: =IFERROR(__xludf.DUMMYFUNCTION("""COMPUTED_VALUE"""),"#4") -> #4 | C28: =IFERROR(__xludf.DUMMYFUNCTION("""COMPUTED_VALUE"""),46057.4166666666) -> 46057.417 | D28: =IFERROR(__xludf.DUMMYFUNCTION("""COMPUTED_VALUE"""),476.1) -> 476.1 | E28: =IFERROR(__xludf.DUMMYFUNCTION("""COMPUTED_VALUE"""),"USD") -> USD | F28: =IFERROR(__xludf.DUMMYFUNCTION("""COMPUTED_VALUE"""),"Daniel Autrique Echeveste") -> Daniel Autrique Echeveste | G28: =IFERROR(__xludf.DUMMYFUNCTION("""COMPUTED_VALUE"""),"ZTRIP TAXI KANSAS CITY USA") -> ZTRIP TAXI KANSAS CITY USA | H28: =IFERROR(__xludf.DUMMYFUNCTION("""COMPUTED_VALUE"""),"Ztrip Taxi Kansas City USA") -> Ztrip Taxi Kansas City USA | I28: =IFERROR(__xludf.DUMMYFUNCTION("""COMPUTED_VALUE"""),"Sales") -> Sales | K28: =IFERROR(__xludf.DUMMYFUNCTION("""COMPUTED_VALUE"""),".") -> . | S28: 392.61 | T28: =VLOOKUP(S28,D:F,3,FALSE) -> #N/A | V28: #46 | W28: =VLOOKUP(V28,B:F,5,FALSE()) -> #N/A
A29: =IFERROR(__xludf.DUMMYFUNCTION("""COMPUTED_VALUE"""),"TRX1197") -> TRX1197 | B29: =IFERROR(__xludf.DUMMYFUNCTION("""COMPUTED_VALUE"""),"#4") -> #4 | C29: =IFERROR(__xludf.DUMMYFUNCTION("""COMPUTED_VALUE"""),46058.4173611111) -> 46058.417 | D29: =IFERROR(__xludf.DUMMYFUNCTION("""COMPUTED_VALUE"""),11358) -> 11358 | E29: =IFERROR(__xludf.DUMMYFUNCTION("""COMPUTED_VALUE"""),"USD") -> USD | F29: =IFERROR(__xludf.DUMMYFUNCTION("""COMPUTED_VALUE"""),"Daniel Autrique Echeveste") -> Daniel Autrique Echeveste | G29: =IFERROR(__xludf.DUMMYFUNCTION("""COMPUTED_VALUE"""),"WOLFGANG PUCK CUT LAS VEGAS USA") -> WOLFGANG PUCK CUT LAS VEGAS USA | H29: =IFERROR(__xludf.DUMMYFUNCTION("""COMPUTED_VALUE"""),"Wolfgang Puck") -> Wolfgang Puck | I29: =IFERROR(__xludf.DUMMYFUNCTION("""COMPUTED_VALUE"""),"G&A expenses") -> G&A expenses | K29: =IFERROR(__xludf.DUMMYFUNCTION("""COMPUTED_VALUE"""),".") -> . | S29: 5175.02 | T29: =VLOOKUP(S29,D:F,3,FALSE) -> #N/A | V29: #37 | W29: =VLOOKUP(V29,B:F,5,FALSE()) -> #N/A
A30: =IFERROR(__xludf.DUMMYFUNCTION("""COMPUTED_VALUE"""),"TRX1193") -> TRX1193 | B30: =IFERROR(__xludf.DUMMYFUNCTION("""COMPUTED_VALUE"""),"#4") -> #4 | C30: =IFERROR(__xludf.DUMMYFUNCTION("""COMPUTED_VALUE"""),46058.4180555555) -> 46058.418 | D30: =IFERROR(__xludf.DUMMYFUNCTION("""COMPUTED_VALUE"""),181.58) -> 181.58 | E30: =IFERROR(__xludf.DUMMYFUNCTION("""COMPUTED_VALUE"""),"USD") -> USD | F30: =IFERROR(__xludf.DUMMYFUNCTION("""COMPUTED_VALUE"""),"Daniel Autrique Echeveste") -> Daniel Autrique Echeveste | G30: =IFERROR(__xludf.DUMMYFUNCTION("""COMPUTED_VALUE"""),"Viasat, Inc. 8669453258 USA") -> Viasat, Inc. 8669453258 USA | H30: =IFERROR(__xludf.DUMMYFUNCTION("""COMPUTED_VALUE"""),"Viasat") -> Viasat | I30: =IFERROR(__xludf.DUMMYFUNCTION("""COMPUTED_VALUE"""),"Sales") -> Sales | K30: =IFERROR(__xludf.DUMMYFUNCTION("""COMPUTED_VALUE"""),".") -> . | S30: 2527.29 | T30: =VLOOKUP(S30,D:F,3,FALSE) -> #N/A | V30: #34 | W30: =VLOOKUP(V30,B:F,5,FALSE()) -> Juan Pablo Ramos Aranda
A31: =IFERROR(__xludf.DUMMYFUNCTION("""COMPUTED_VALUE"""),"TRX1576") -> TRX1576 | B31: =IFERROR(__xludf.DUMMYFUNCTION("""COMPUTED_VALUE"""),"#4") -> #4 | C31: =IFERROR(__xludf.DUMMYFUNCTION("""COMPUTED_VALUE"""),46059.4173611111) -> 46059.417 | D31: =IFERROR(__xludf.DUMMYFUNCTION("""COMPUTED_VALUE"""),13052.62) -> 13052.62 | E31: =IFERROR(__xludf.DUMMYFUNCTION("""COMPUTED_VALUE"""),"MXN") -> MXN | F31: =IFERROR(__xludf.DUMMYFUNCTION("""COMPUTED_VALUE"""),"Daniel Autrique Echeveste") -> Daniel Autrique Echeveste | G31: =IFERROR(__xludf.DUMMYFUNCTION("""COMPUTED_VALUE"""),"COSMOPOL-FRONT DESK LAS VEGAS USA") -> COSMOPOL-FRONT DESK LAS VEGAS USA | H31: =IFERROR(__xludf.DUMMYFUNCTION("""COMPUTED_VALUE"""),"Cosmopol Front Desk Las Vegas USA") -> Cosmopol Front Desk Las Vegas USA | I31: =IFERROR(__xludf.DUMMYFUNCTION("""COMPUTED_VALUE"""),"Sales") -> Sales | K31: =IFERROR(__xludf.DUMMYFUNCTION("""COMPUTED_VALUE"""),".") -> . | S31: 283.15 | T31: =VLOOKUP(S31,D:F,3,FALSE) -> #N/A | V31: #3 | W31: =VLOOKUP(V31,B:F,5,FALSE()) -> Cesar Uriel Romo Trillo
A32: =IFERROR(__xludf.DUMMYFUNCTION("""COMPUTED_VALUE"""),"TRX1408") -> TRX1408 | B32: =IFERROR(__xludf.DUMMYFUNCTION("""COMPUTED_VALUE"""),"#4") -> #4 | C32: =IFERROR(__xludf.DUMMYFUNCTION("""COMPUTED_VALUE"""),46060.4173611111) -> 46060.417 | D32: =IFERROR(__xludf.DUMMYFUNCTION("""COMPUTED_VALUE"""),2196.88) -> 2196.88 | E32: =IFERROR(__xludf.DUMMYFUNCTION("""COMPUTED_VALUE"""),"USD") -> USD | F32: =IFERROR(__xludf.DUMMYFUNCTION("""COMPUTED_VALUE"""),"Daniel Autrique Echeveste") -> Daniel Autrique Echeveste | G32: =IFERROR(__xludf.DUMMYFUNCTION("""COMPUTED_VALUE"""),"20260203T00:00:00/COSMOPOL-FRONT DESK\3708 LAS VEGAS BLVD S\LAS VEGAS\89109 NV USA") -> 20260203T00:00:00/COSMOPOL-FRONT DESK\3708 LAS VEGAS BLVD S\LAS VEGAS\89109 NV USA | H32: =IFERROR(__xludf.DUMMYFUNCTION("""COMPUTED_VALUE"""),"T :00/Cosmopol Front Desk\3708 Las Vegas Blvd S\Las Vegas\ Nv USA") -> T :00/Cosmopol Front Desk\3708 Las Vegas Blvd S\Las Vegas\ Nv USA | I32: =IFERROR(__xludf.DUMMYFUNCTION("""COMPUTED_VALUE"""),"Sales") -> Sales | K32: =IFERROR(__xludf.DUMMYFUNCTION("""COMPUTED_VALUE"""),".") -> . | S32: 402.99 | T32: =VLOOKUP(S32,D:F,3,FALSE) -> #N/A | V32: #42 | W32: =VLOOKUP(V32,B:F,5,FALSE()) -> Rodrigo Perea
A33: =IFERROR(__xludf.DUMMYFUNCTION("""COMPUTED_VALUE"""),"TRX1758") -> TRX1758 | B33: =IFERROR(__xludf.DUMMYFUNCTION("""COMPUTED_VALUE"""),"#4") -> #4 | C33: =IFERROR(__xludf.DUMMYFUNCTION("""COMPUTED_VALUE"""),46061.4166666666) -> 46061.417 | D33: =IFERROR(__xludf.DUMMYFUNCTION("""COMPUTED_VALUE"""),100) -> 100 | E33: =IFERROR(__xludf.DUMMYFUNCTION("""COMPUTED_VALUE"""),"MXN") -> MXN | F33: =IFERROR(__xludf.DUMMYFUNCTION("""COMPUTED_VALUE"""),"Daniel Autrique Echeveste") -> Daniel Autrique Echeveste | G33: =IFERROR(__xludf.DUMMYFUNCTION("""COMPUTED_VALUE"""),"MEXPAGO*MUEVECIUDAD CIUDAD DE MEX MEX") -> MEXPAGO*MUEVECIUDAD CIUDAD DE MEX MEX | H33: =IFERROR(__xludf.DUMMYFUNCTION("""COMPUTED_VALUE"""),"Mexpago Mueveciudad Ciudad De Mex Mex") -> Mexpago Mueveciudad Ciudad De Mex Mex | I33: =IFERROR(__xludf.DUMMYFUNCTION("""COMPUTED_VALUE"""),"Sales") -> Sales | K33: =IFERROR(__xludf.DUMMYFUNCTION("""COMPUTED_VALUE"""),".") -> . | S33: 502.62 | T33: =VLOOKUP(S33,D:F,3,FALSE) -> #N/A | V33: #6 | W33: =VLOOKUP(V33,B:F,5,FALSE()) -> Fernando Sanchez Toledano
A34: =IFERROR(__xludf.DUMMYFUNCTION("""COMPUTED_VALUE"""),"TRX1501") -> TRX1501 | B34: =IFERROR(__xludf.DUMMYFUNCTION("""COMPUTED_VALUE"""),"#4") -> #4 | C34: =IFERROR(__xludf.DUMMYFUNCTION("""COMPUTED_VALUE"""),46064.4166666666) -> 46064.417 | D34: =IFERROR(__xludf.DUMMYFUNCTION("""COMPUTED_VALUE"""),870.55) -> 870.55 | E34: =IFERROR(__xludf.DUMMYFUNCTION("""COMPUTED_VALUE"""),"MXN") -> MXN | F34: =IFERROR(__xludf.DUMMYFUNCTION("""COMPUTED_VALUE"""),"Daniel Autrique Echeveste") -> Daniel Autrique Echeveste | G34: =IFERROR(__xludf.DUMMYFUNCTION("""COMPUTED_VALUE"""),"REST ENO VIRREYES CIUDAD DE MEX MEX") -> REST ENO VIRREYES CIUDAD DE MEX MEX | H34: =IFERROR(__xludf.DUMMYFUNCTION("""COMPUTED_VALUE"""),"Rest Eno Virreyes Ciudad De Mex Mex") -> Rest Eno Virreyes Ciudad De Mex Mex | K34: =IFERROR(__xludf.DUMMYFUNCTION("""COMPUTED_VALUE"""),".") -> . | S34: 246.26 | T34: =VLOOKUP(S34,D:F,3,FALSE) -> #N/A | V34: #20 | W34: =VLOOKUP(V34,B:F,5,FALSE()) -> #N/A
A35: =IFERROR(__xludf.DUMMYFUNCTION("""COMPUTED_VALUE"""),"TRX1629") -> TRX1629 | B35: =IFERROR(__xludf.DUMMYFUNCTION("""COMPUTED_VALUE"""),"#4") -> #4 | C35: =IFERROR(__xludf.DUMMYFUNCTION("""COMPUTED_VALUE"""),46067.4166666666) -> 46067.417 | D35: =IFERROR(__xludf.DUMMYFUNCTION("""COMPUTED_VALUE"""),5662.6) -> 5662.6 | E35: =IFERROR(__xludf.DUMMYFUNCTION("""COMPUTED_VALUE"""),"MXN") -> MXN | F35: =IFERROR(__xludf.DUMMYFUNCTION("""COMPUTED_VALUE"""),"Daniel Autrique Echeveste") -> Daniel Autrique Echeveste | G35: =IFERROR(__xludf.DUMMYFUNCTION("""COMPUTED_VALUE"""),"REST ZERU LOMAS CIUDAD DE MEX MEX") -> REST ZERU LOMAS CIUDAD DE MEX MEX | H35: =IFERROR(__xludf.DUMMYFUNCTION("""COMPUTED_VALUE"""),"Rest Zeru Lomas Ciudad De Mex Mex") -> Rest Zeru Lomas Ciudad De Mex Mex | K35: =IFERROR(__xludf.DUMMYFUNCTION("""COMPUTED_VALUE"""),".") -> . | S35: 251.27 | T35: =VLOOKUP(S35,D:F,3,FALSE) -> #N/A | V35: #58 | W35: =VLOOKUP(V35,B:F,5,FALSE()) -> Jose Rosas Ortiz
A36: =IFERROR(__xludf.DUMMYFUNCTION("""COMPUTED_VALUE"""),"TRX1043") -> TRX1043 | B36: =IFERROR(__xludf.DUMMYFUNCTION("""COMPUTED_VALUE"""),"#4") -> #4 | C36: =IFERROR(__xludf.DUMMYFUNCTION("""COMPUTED_VALUE"""),46071.4173611111) -> 46071.417 | D36: =IFERROR(__xludf.DUMMYFUNCTION("""COMPUTED_VALUE"""),1213.99) -> 1213.99 | E36: =IFERROR(__xludf.DUMMYFUNCTION("""COMPUTED_VALUE"""),"MXN") -> MXN | F36: =IFERROR(__xludf.DUMMYFUNCTION("""COMPUTED_VALUE"""),"Daniel Autrique Echeveste") -> Daniel Autrique Echeveste | G36: =IFERROR(__xludf.DUMMYFUNCTION("""COMPUTED_VALUE"""),"GASOL VALERO LOMALINDA CIUDAD DE MEX MEX") -> GASOL VALERO LOMALINDA CIUDAD DE MEX MEX | H36: =IFERROR(__xludf.DUMMYFUNCTION("""COMPUTED_VALUE"""),"Gasol Valero Lomalinda Ciudad De Mex Mex") -> Gasol Valero Lomalinda Ciudad De Mex Mex | K36: =IFERROR(__xludf.DUMMYFUNCTION("""COMPUTED_VALUE"""),".") -> . | S36: 6677 | T36: =VLOOKUP(S36,D:F,3,FALSE) -> #N/A | V36: #35 | W36: =VLOOKUP(V36,B:F,5,FALSE()) -> Termis
A37: =IFERROR(__xludf.DUMMYFUNCTION("""COMPUTED_VALUE"""),"TRX1219") -> TRX1219 | B37: =IFERROR(__xludf.DUMMYFUNCTION("""COMPUTED_VALUE"""),"#5") -> #5 | C37: =IFERROR(__xludf.DUMMYFUNCTION("""COMPUTED_VALUE"""),46058.4173611111) -> 46058.417 | D37: =IFERROR(__xludf.DUMMYFUNCTION("""COMPUTED_VALUE"""),70) -> 70 | E37: =IFERROR(__xludf.DUMMYFUNCTION("""COMPUTED_VALUE"""),"MXN") -> MXN | F37: =IFERROR(__xludf.DUMMYFUNCTION("""COMPUTED_VALUE"""),"Fernanda Sanchez Ruiz") -> Fernanda Sanchez Ruiz | G37: =IFERROR(__xludf.DUMMYFUNCTION("""COMPUTED_VALUE"""),"DLO*UBER RIDE CIUDAD DE MEX MEX") -> DLO*UBER RIDE CIUDAD DE MEX MEX | H37: =IFERROR(__xludf.DUMMYFUNCTION("""COMPUTED_VALUE"""),"Uber") -> Uber | I37: =IFERROR(__xludf.DUMMYFUNCTION("""COMPUTED_VALUE"""),"Office expenses") -> Office expenses | J37: =IFERROR(__xludf.DUMMYFUNCTION("""COMPUTED_VALUE"""),"Snacks para la oficina") -> Snacks para la oficina | K37: =IFERROR(__xludf.DUMMYFUNCTION("""COMPUTED_VALUE"""),".") -> . | S37: 3781.76 | T37: =VLOOKUP(S37,D:F,3,FALSE) -> #N/A | V37: #49 | W37: =VLOOKUP(V37,B:F,5,FALSE()) -> Jahaziel Galan
A38: =IFERROR(__xludf.DUMMYFUNCTION("""COMPUTED_VALUE"""),"TRX1206") -> TRX1206 | B38: =IFERROR(__xludf.DUMMYFUNCTION("""COMPUTED_VALUE"""),"#5") -> #5 | C38: =IFERROR(__xludf.DUMMYFUNCTION("""COMPUTED_VALUE"""),46058.4173611111) -> 46058.417 | D38: =IFERROR(__xludf.DUMMYFUNCTION("""COMPUTED_VALUE"""),1186.28) -> 1186.28 | E38: =IFERROR(__xludf.DUMMYFUNCTION("""COMPUTED_VALUE"""),"MXN") -> MXN | F38: =IFERROR(__xludf.DUMMYFUNCTION("""COMPUTED_VALUE"""),"Fernanda Sanchez Ruiz") -> Fernanda Sanchez Ruiz | G38: =IFERROR(__xludf.DUMMYFUNCTION("""COMPUTED_VALUE"""),"SAMS VENTA EN LINEA MEXICO DF MEX") -> SAMS VENTA EN LINEA MEXICO DF MEX | H38: =IFERROR(__xludf.DUMMYFUNCTION("""COMPUTED_VALUE"""),"Sam's Club") -> Sam's Club | I38: =IFERROR(__xludf.DUMMYFUNCTION("""COMPUTED_VALUE"""),"Office expenses") -> Office expenses | K38: =IFERROR(__xludf.DUMMYFUNCTION("""COMPUTED_VALUE"""),".") -> . | S38: 332.45 | T38: =VLOOKUP(S38,D:F,3,FALSE) -> #N/A | V38: #45 | W38: =VLOOKUP(V38,B:F,5,FALSE()) -> #N/A
A39: =IFERROR(__xludf.DUMMYFUNCTION("""COMPUTED_VALUE"""),"TRX1628") -> TRX1628 | B39: =IFERROR(__xludf.DUMMYFUNCTION("""COMPUTED_VALUE"""),"#5") -> #5 | C39: =IFERROR(__xludf.DUMMYFUNCTION("""COMPUTED_VALUE"""),46065.4173611111) -> 46065.417 | D39: =IFERROR(__xludf.DUMMYFUNCTION("""COMPUTED_VALUE"""),1690.58) -> 1690.58 | E39: =IFERROR(__xludf.DUMMYFUNCTION("""COMPUTED_VALUE"""),"MXN") -> MXN | F39: =IFERROR(__xludf.DUMMYFUNCTION("""COMPUTED_VALUE"""),"Fernanda Sanchez Ruiz") -> Fernanda Sanchez Ruiz | G39: =IFERROR(__xludf.DUMMYFUNCTION("""COMPUTED_VALUE"""),"SAMS VENTA EN LINEA MEXICO DF MEX") -> SAMS VENTA EN LINEA MEXICO DF MEX | H39: =IFERROR(__xludf.DUMMYFUNCTION("""COMPUTED_VALUE"""),"Sam's Club") -> Sam's Club | I39: =IFERROR(__xludf.DUMMYFUNCTION("""COMPUTED_VALUE"""),"Office expenses") -> Office expenses | J39: =IFERROR(__xludf.DUMMYFUNCTION("""COMPUTED_VALUE"""),"Snacks para la oficina") -> Snacks para la oficina | K39: =IFERROR(__xludf.DUMMYFUNCTION("""COMPUTED_VALUE"""),".") -> . | S39: 135.94 | T39: =VLOOKUP(S39,D:F,3,FALSE) -> #N/A | V39: #4 | W39: =VLOOKUP(V39,B:F,5,FALSE()) -> Daniel Autrique Echeveste
A40: =IFERROR(__xludf.DUMMYFUNCTION("""COMPUTED_VALUE"""),"TRX1890") -> TRX1890 | B40: =IFERROR(__xludf.DUMMYFUNCTION("""COMPUTED_VALUE"""),"#5") -> #5 | C40: =IFERROR(__xludf.DUMMYFUNCTION("""COMPUTED_VALUE"""),46067.4166666666) -> 46067.417 | D40: =IFERROR(__xludf.DUMMYFUNCTION("""COMPUTED_VALUE"""),317.52) -> 317.52 | E40: =IFERROR(__xludf.DUMMYFUNCTION("""COMPUTED_VALUE"""),"MXN") -> MXN | F40: =IFERROR(__xludf.DUMMYFUNCTION("""COMPUTED_VALUE"""),"Fernanda Sanchez Ruiz") -> Fernanda Sanchez Ruiz | G40: =IFERROR(__xludf.DUMMYFUNCTION("""COMPUTED_VALUE"""),"UBER * EATS PENDING CMX MEX") -> UBER * EATS PENDING CMX MEX | H40: =IFERROR(__xludf.DUMMYFUNCTION("""COMPUTED_VALUE"""),"Uber Eats") -> Uber Eats | I40: =IFERROR(__xludf.DUMMYFUNCTION("""COMPUTED_VALUE"""),"Office expenses") -> Office expenses | J40: =IFERROR(__xludf.DUMMYFUNCTION("""COMPUTED_VALUE"""),"Snacks para la oficina") -> Snacks para la oficina | K40: =IFERROR(__xludf.DUMMYFUNCTION("""COMPUTED_VALUE"""),".") -> . | S40: 940 | T40: =VLOOKUP(S40,D:F,3,FALSE) -> #N/A | V40: #17 | W40: =VLOOKUP(V40,B:F,5,FALSE()) -> #N/A
A41: =IFERROR(__xludf.DUMMYFUNCTION("""COMPUTED_VALUE"""),"TRX1251") -> TRX1251 | B41: =IFERROR(__xludf.DUMMYFUNCTION("""COMPUTED_VALUE"""),"#5") -> #5 | C41: =IFERROR(__xludf.DUMMYFUNCTION("""COMPUTED_VALUE"""),46067.4166666666) -> 46067.417 | D41: =IFERROR(__xludf.DUMMYFUNCTION("""COMPUTED_VALUE"""),939.38) -> 939.38 | E41: =IFERROR(__xludf.DUMMYFUNCTION("""COMPUTED_VALUE"""),"MXN") -> MXN | F41: =IFERROR(__xludf.DUMMYFUNCTION("""COMPUTED_VALUE"""),"Fernanda Sanchez Ruiz") -> Fernanda Sanchez Ruiz | G41: =IFERROR(__xludf.DUMMYFUNCTION("""COMPUTED_VALUE"""),"UBER * EATS PENDING CMX MEX") -> UBER * EATS PENDING CMX MEX | H41: =IFERROR(__xludf.DUMMYFUNCTION("""COMPUTED_VALUE"""),"Uber Eats") -> Uber Eats | I41: =IFERROR(__xludf.DUMMYFUNCTION("""COMPUTED_VALUE"""),"Office expenses") -> Office expenses | J41: =IFERROR(__xludf.DUMMYFUNCTION("""COMPUTED_VALUE"""),"Botiquin ") -> Botiquin | K41: =IFERROR(__xludf.DUMMYFUNCTION("""COMPUTED_VALUE"""),".") -> . | S41: 719.91 | T41: =VLOOKUP(S41,D:F,3,FALSE) -> #N/A | V41: #70 | W41: =VLOOKUP(V41,B:F,5,FALSE()) -> Alfonso Bello
A42: =IFERROR(__xludf.DUMMYFUNCTION("""COMPUTED_VALUE"""),"TRX1643") -> TRX1643 | B42: =IFERROR(__xludf.DUMMYFUNCTION("""COMPUTED_VALUE"""),"#5") -> #5 | C42: =IFERROR(__xludf.DUMMYFUNCTION("""COMPUTED_VALUE"""),46067.4166666666) -> 46067.417 | D42: =IFERROR(__xludf.DUMMYFUNCTION("""COMPUTED_VALUE"""),20) -> 20 | E42: =IFERROR(__xludf.DUMMYFUNCTION("""COMPUTED_VALUE"""),"MXN") -> MXN | F42: =IFERROR(__xludf.DUMMYFUNCTION("""COMPUTED_VALUE"""),"Fernanda Sanchez Ruiz") -> Fernanda Sanchez Ruiz | G42: =IFERROR(__xludf.DUMMYFUNCTION("""COMPUTED_VALUE"""),"UBER *EATS HELP.UBER.C CMX MEX") -> UBER *EATS HELP.UBER.C CMX MEX | H42: =IFERROR(__xludf.DUMMYFUNCTION("""COMPUTED_VALUE"""),"Uber Eats") -> Uber Eats | I42: =IFERROR(__xludf.DUMMYFUNCTION("""COMPUTED_VALUE"""),"Office expenses") -> Office expenses | J42: =IFERROR(__xludf.DUMMYFUNCTION("""COMPUTED_VALUE"""),"Refill de botiquin") -> Refill de botiquin | K42: =IFERROR(__xludf.DUMMYFUNCTION("""COMPUTED_VALUE"""),".") -> . | S42: 1399.33 | T42: =VLOOKUP(S42,D:F,3,FALSE) -> #N/A | V42: #11 | W42: =VLOOKUP(V42,B:F,5,FALSE()) -> #N/A
A43: =IFERROR(__xludf.DUMMYFUNCTION("""COMPUTED_VALUE"""),"TRX1775") -> TRX1775 | B43: =IFERROR(__xludf.DUMMYFUNCTION("""COMPUTED_VALUE"""),"#5") -> #5 | C43: =IFERROR(__xludf.DUMMYFUNCTION("""COMPUTED_VALUE"""),46067.4166666666) -> 46067.417 | D43: =IFERROR(__xludf.DUMMYFUNCTION("""COMPUTED_VALUE"""),3142.4) -> 3142.4 | E43: =IFERROR(__xludf.DUMMYFUNCTION("""COMPUTED_VALUE"""),"MXN") -> MXN | F43: =IFERROR(__xludf.DUMMYFUNCTION("""COMPUTED_VALUE"""),"Fernanda Sanchez Ruiz") -> Fernanda Sanchez Ruiz | G43: =IFERROR(__xludf.DUMMYFUNCTION("""COMPUTED_VALUE"""),"UBER * EATS PENDING CMX MEX") -> UBER * EATS PENDING CMX MEX | H43: =IFERROR(__xludf.DUMMYFUNCTION("""COMPUTED_VALUE"""),"Uber Eats") -> Uber Eats | K43: =IFERROR(__xludf.DUMMYFUNCTION("""COMPUTED_VALUE"""),".") -> . | S43: 1000 | T43: =VLOOKUP(S43,D:F,3,FALSE) -> Fernando Sanchez Toledano | V43: #7 | W43: =VLOOKUP(V43,B:F,5,FALSE()) -> Isaac Mendoza Ruiz
A44: =IFERROR(__xludf.DUMMYFUNCTION("""COMPUTED_VALUE"""),"TRX1734") -> TRX1734 | B44: =IFERROR(__xludf.DUMMYFUNCTION("""COMPUTED_VALUE"""),"#5") -> #5 | C44: =IFERROR(__xludf.DUMMYFUNCTION("""COMPUTED_VALUE"""),46067.4166666666) -> 46067.417 | D44: =IFERROR(__xludf.DUMMYFUNCTION("""COMPUTED_VALUE"""),40) -> 40 | E44: =IFERROR(__xludf.DUMMYFUNCTION("""COMPUTED_VALUE"""),"MXN") -> MXN | F44: =IFERROR(__xludf.DUMMYFUNCTION("""COMPUTED_VALUE"""),"Fernanda Sanchez Ruiz") -> Fernanda Sanchez Ruiz | G44: =IFERROR(__xludf.DUMMYFUNCTION("""COMPUTED_VALUE"""),"UBER *EATS HELP.UBER.C CMX MEX") -> UBER *EATS HELP.UBER.C CMX MEX | H44: =IFERROR(__xludf.DUMMYFUNCTION("""COMPUTED_VALUE"""),"Uber Eats") -> Uber Eats | K44: =IFERROR(__xludf.DUMMYFUNCTION("""COMPUTED_VALUE"""),".") -> . | S44: 280 | T44: =VLOOKUP(S44,D:F,3,FALSE) -> Carlos Ivan Gonzalez Merino | V44: #54 | W44: =VLOOKUP(V44,B:F,5,FALSE()) -> #N/A
A45: =IFERROR(__xludf.DUMMYFUNCTION("""COMPUTED_VALUE"""),"TRX1953") -> TRX1953 | B45: =IFERROR(__xludf.DUMMYFUNCTION("""COMPUTED_VALUE"""),"#5") -> #5 | C45: =IFERROR(__xludf.DUMMYFUNCTION("""COMPUTED_VALUE"""),46071.4166666666) -> 46071.417 | D45: =IFERROR(__xludf.DUMMYFUNCTION("""COMPUTED_VALUE"""),1707.95) -> 1707.95 | E45: =IFERROR(__xludf.DUMMYFUNCTION("""COMPUTED_VALUE"""),"MXN") -> MXN | F45: =IFERROR(__xludf.DUMMYFUNCTION("""COMPUTED_VALUE"""),"Fernanda Sanchez Ruiz") -> Fernanda Sanchez Ruiz | G45: =IFERROR(__xludf.DUMMYFUNCTION("""COMPUTED_VALUE"""),"SAMS VENTA EN LINEA MEXICO DF MEX") -> SAMS VENTA EN LINEA MEXICO DF MEX | H45: =IFERROR(__xludf.DUMMYFUNCTION("""COMPUTED_VALUE"""),"Sam's Club") -> Sam's Club | K45: =IFERROR(__xludf.DUMMYFUNCTION("""COMPUTED_VALUE"""),".") -> . | S45: 174.53 | T45: =VLOOKUP(S45,D:F,3,FALSE) -> #N/A | V45: #25 | W45: =VLOOKUP(V45,B:F,5,FALSE()) -> #N/A
A46: =IFERROR(__xludf.DUMMYFUNCTION("""COMPUTED_VALUE"""),"TRX1925") -> TRX1925 | B46: =IFERROR(__xludf.DUMMYFUNCTION("""COMPUTED_VALUE"""),"#5") -> #5 | C46: =IFERROR(__xludf.DUMMYFUNCTION("""COMPUTED_VALUE"""),46072.4166666666) -> 46072.417 | D46: =IFERROR(__xludf.DUMMYFUNCTION("""COMPUTED_VALUE"""),99.94) -> 99.94 | E46: =IFERROR(__xludf.DUMMYFUNCTION("""COMPUTED_VALUE"""),"MXN") -> MXN | F46: =IFERROR(__xludf.DUMMYFUNCTION("""COMPUTED_VALUE"""),"Fernanda Sanchez Ruiz") -> Fernanda Sanchez Ruiz | G46: =IFERROR(__xludf.DUMMYFUNCTION("""COMPUTED_VALUE"""),"UBER * PENDING CMX MEX") -> UBER * PENDING CMX MEX | H46: =IFERROR(__xludf.DUMMYFUNCTION("""COMPUTED_VALUE"""),"Uber") -> Uber | K46: =IFERROR(__xludf.DUMMYFUNCTION("""COMPUTED_VALUE"""),".") -> . | S46: 105.49 | T46: =VLOOKUP(S46,D:F,3,FALSE) -> #N/A | V46: #5 | W46: =VLOOKUP(V46,B:F,5,FALSE()) -> Fernanda Sanchez Ruiz
A47: =IFERROR(__xludf.DUMMYFUNCTION("""COMPUTED_VALUE"""),"TRX1228") -> TRX1228 | B47: =IFERROR(__xludf.DUMMYFUNCTION("""COMPUTED_VALUE"""),"#5") -> #5 | C47: =IFERROR(__xludf.DUMMYFUNCTION("""COMPUTED_VALUE"""),46073.4166666666) -> 46073.417 | D47: =IFERROR(__xludf.DUMMYFUNCTION("""COMPUTED_VALUE"""),38.68) -> 38.68 | E47: =IFERROR(__xludf.DUMMYFUNCTION("""COMPUTED_VALUE"""),"MXN") -> MXN | F47: =IFERROR(__xludf.DUMMYFUNCTION("""COMPUTED_VALUE"""),"Fernanda Sanchez Ruiz") -> Fernanda Sanchez Ruiz | G47: =IFERROR(__xludf.DUMMYFUNCTION("""COMPUTED_VALUE"""),"UBER * PENDING CMX MEX") -> UBER * PENDING CMX MEX | H47: =IFERROR(__xludf.DUMMYFUNCTION("""COMPUTED_VALUE"""),"Uber") -> Uber | K47: =IFERROR(__xludf.DUMMYFUNCTION("""COMPUTED_VALUE"""),".") -> . | S47: 79.95 | T47: =VLOOKUP(S47,D:F,3,FALSE) -> Isaac Mendoza Ruiz | V47: #21 | W47: =VLOOKUP(V47,B:F,5,FALSE()) -> Jesus Gonzalez Grana
A48: =IFERROR(__xludf.DUMMYFUNCTION("""COMPUTED_VALUE"""),"TRX1222") -> TRX1222 | B48: =IFERROR(__xludf.DUMMYFUNCTION("""COMPUTED_VALUE"""),"#5") -> #5 | C48: =IFERROR(__xludf.DUMMYFUNCTION("""COMPUTED_VALUE"""),46073.4166666666) -> 46073.417 | D48: =IFERROR(__xludf.DUMMYFUNCTION("""COMPUTED_VALUE"""),29.96) -> 29.96 | E48: =IFERROR(__xludf.DUMMYFUNCTION("""COMPUTED_VALUE"""),"MXN") -> MXN | F48: =IFERROR(__xludf.DUMMYFUNCTION("""COMPUTED_VALUE"""),"Fernanda Sanchez Ruiz") -> Fernanda Sanchez Ruiz | G48: =IFERROR(__xludf.DUMMYFUNCTION("""COMPUTED_VALUE"""),"UBER * PENDING CMX MEX") -> UBER * PENDING CMX MEX | H48: =IFERROR(__xludf.DUMMYFUNCTION("""COMPUTED_VALUE"""),"Uber") -> Uber | K48: =IFERROR(__xludf.DUMMYFUNCTION("""COMPUTED_VALUE"""),".") -> . | S48: 282.07 | T48: =VLOOKUP(S48,D:F,3,FALSE) -> #N/A | V48: #48 | W48: =VLOOKUP(V48,B:F,5,FALSE()) -> #N/A
A49: =IFERROR(__xludf.DUMMYFUNCTION("""COMPUTED_VALUE"""),"TRX1222") -> TRX1222 | B49: =IFERROR(__xludf.DUMMYFUNCTION("""COMPUTED_VALUE"""),"#6") -> #6 | C49: =IFERROR(__xludf.DUMMYFUNCTION("""COMPUTED_VALUE"""),46058.4173611111) -> 46058.417 | D49: =IFERROR(__xludf.DUMMYFUNCTION("""COMPUTED_VALUE"""),1149) -> 1149 | E49: =IFERROR(__xludf.DUMMYFUNCTION("""COMPUTED_VALUE"""),"MXN") -> MXN | F49: =IFERROR(__xludf.DUMMYFUNCTION("""COMPUTED_VALUE"""),"Fernando Sanchez Toledano") -> Fernando Sanchez Toledano | G49: =IFERROR(__xludf.DUMMYFUNCTION("""COMPUTED_VALUE"""),"AVIS WEB MXN MERIDA YUC MEX") -> AVIS WEB MXN MERIDA YUC MEX | H49: =IFERROR(__xludf.DUMMYFUNCTION("""COMPUTED_VALUE"""),"Avis") -> Avis | I49: =IFERROR(__xludf.DUMMYFUNCTION("""COMPUTED_VALUE"""),"Transaction cost") -> Transaction cost | J49: =IFERROR(__xludf.DUMMYFUNCTION("""COMPUTED_VALUE"""),"Transaction cost") -> Transaction cost | K49: =IFERROR(__xludf.DUMMYFUNCTION("""COMPUTED_VALUE"""),"Gasolina recolección Fer Marcelo") -> Gasolina recolección Fer Marcelo | S49: 142.86 | T49: =VLOOKUP(S49,D:F,3,FALSE) -> #N/A | V49: #14 | W49: =VLOOKUP(V49,B:F,5,FALSE()) -> Patricio Servitje Azcarraga
A50: =IFERROR(__xludf.DUMMYFUNCTION("""COMPUTED_VALUE"""),"TRX1202") -> TRX1202 | B50: =IFERROR(__xludf.DUMMYFUNCTION("""COMPUTED_VALUE"""),"#6") -> #6 | C50: =IFERROR(__xludf.DUMMYFUNCTION("""COMPUTED_VALUE"""),46058.4173611111) -> 46058.417 | D50: =IFERROR(__xludf.DUMMYFUNCTION("""COMPUTED_VALUE"""),91) -> 91 | E50: =IFERROR(__xludf.DUMMYFUNCTION("""COMPUTED_VALUE"""),"MXN") -> MXN | F50: =IFERROR(__xludf.DUMMYFUNCTION("""COMPUTED_VALUE"""),"Fernando Sanchez Toledano") -> Fernando Sanchez Toledano | G50: =IFERROR(__xludf.DUMMYFUNCTION("""COMPUTED_VALUE"""),"DLO*DIDI RIDES MEXICO MEX") -> DLO*DIDI RIDES MEXICO MEX | H50: =IFERROR(__xludf.DUMMYFUNCTION("""COMPUTED_VALUE"""),"Didi Chuxing") -> Didi Chuxing | I50: =IFERROR(__xludf.DUMMYFUNCTION("""COMPUTED_VALUE"""),"Transaction cost") -> Transaction cost | J50: =IFERROR(__xludf.DUMMYFUNCTION("""COMPUTED_VALUE"""),"Transaction cost") -> Transaction cost | K50: =IFERROR(__xludf.DUMMYFUNCTION("""COMPUTED_VALUE"""),"Comida visita fer Marcelo ") -> Comida visita fer Marcelo | S50: 1500 | T50: =VLOOKUP(S50,D:F,3,FALSE) -> #N/A | V50: #61 | W50: =VLOOKUP(V50,B:F,5,FALSE()) -> #N/A
A51: =IFERROR(__xludf.DUMMYFUNCTION("""COMPUTED_VALUE"""),"TRX1176") -> TRX1176 | B51: =IFERROR(__xludf.DUMMYFUNCTION("""COMPUTED_VALUE"""),"#6") -> #6 | C51: =IFERROR(__xludf.DUMMYFUNCTION("""COMPUTED_VALUE"""),46059.4166666666) -> 46059.417 | D51: =IFERROR(__xludf.DUMMYFUNCTION("""COMPUTED_VALUE"""),791.04) -> 791.04 | E51: =IFERROR(__xludf.DUMMYFUNCTION("""COMPUTED_VALUE"""),"MXN") -> MXN | F51: =IFERROR(__xludf.DUMMYFUNCTION("""COMPUTED_VALUE"""),"Fernando Sanchez Toledano") -> Fernando Sanchez Toledano | G51: =IFERROR(__xludf.DUMMYFUNCTION("""COMPUTED_VALUE"""),"GAS COGA LOM CHA MIT 2 CIUDAD DE MEX MEX") -> GAS COGA LOM CHA MIT 2 CIUDAD DE MEX MEX | H51: =IFERROR(__xludf.DUMMYFUNCTION("""COMPUTED_VALUE"""),"Gas Coga Lom Cha Mit 2 Ciudad De Mex Mex") -> Gas Coga Lom Cha Mit 2 Ciudad De Mex Mex | I51: =IFERROR(__xludf.DUMMYFUNCTION("""COMPUTED_VALUE"""),"Transaction cost") -> Transaction cost | J51: =IFERROR(__xludf.DUMMYFUNCTION("""COMPUTED_VALUE"""),"Transaction cost") -> Transaction cost | K51: =IFERROR(__xludf.DUMMYFUNCTION("""COMPUTED_VALUE"""),"Recarga de tag") -> Recarga de tag | S51: 449 | T51: =VLOOKUP(S51,D:F,3,FALSE) -> #N/A | V51: #44 | W51: =VLOOKUP(V51,B:F,5,FALSE()) -> JP Hammerstein
A52: =IFERROR(__xludf.DUMMYFUNCTION("""COMPUTED_VALUE"""),"TRX1155") -> TRX1155 | B52: =IFERROR(__xludf.DUMMYFUNCTION("""COMPUTED_VALUE"""),"#6") -> #6 | C52: =IFERROR(__xludf.DUMMYFUNCTION("""COMPUTED_VALUE"""),46059.4173611111) -> 46059.417 | D52: =IFERROR(__xludf.DUMMYFUNCTION("""COMPUTED_VALUE"""),193) -> 193 | E52: =IFERROR(__xludf.DUMMYFUNCTION("""COMPUTED_VALUE"""),"MXN") -> MXN | F52: =IFERROR(__xludf.DUMMYFUNCTION("""COMPUTED_VALUE"""),"Fernando Sanchez Toledano") -> Fernando Sanchez Toledano | G52: =IFERROR(__xludf.DUMMYFUNCTION("""COMPUTED_VALUE"""),"OXXO SAN IGNACIO QRF POLOTITLAN EM MEX") -> OXXO SAN IGNACIO QRF POLOTITLAN EM MEX | H52: =IFERROR(__xludf.DUMMYFUNCTION("""COMPUTED_VALUE"""),"Oxxo") -> Oxxo | I52: =IFERROR(__xludf.DUMMYFUNCTION("""COMPUTED_VALUE"""),"Transaction cost") -> Transaction cost | J52: =IFERROR(__xludf.DUMMYFUNCTION("""COMPUTED_VALUE"""),"Transaction cost") -> Transaction cost | K52: =IFERROR(__xludf.DUMMYFUNCTION("""COMPUTED_VALUE"""),"Gasolina, entrega en Deacero ") -> Gasolina, entrega en Deacero | S52: 84.85 | T52: =VLOOKUP(S52,D:F,3,FALSE) -> #N/A
A53: =IFERROR(__xludf.DUMMYFUNCTION("""COMPUTED_VALUE"""),"TRX1149") -> TRX1149 | B53: =IFERROR(__xludf.DUMMYFUNCTION("""COMPUTED_VALUE"""),"#6") -> #6 | C53: =IFERROR(__xludf.DUMMYFUNCTION("""COMPUTED_VALUE"""),46059.4173611111) -> 46059.417 | D53: =IFERROR(__xludf.DUMMYFUNCTION("""COMPUTED_VALUE"""),1000) -> 1000 | E53: =IFERROR(__xludf.DUMMYFUNCTION("""COMPUTED_VALUE"""),"MXN") -> MXN | F53: =IFERROR(__xludf.DUMMYFUNCTION("""COMPUTED_VALUE"""),"Fernando Sanchez Toledano") -> Fernando Sanchez Toledano | G53: =IFERROR(__xludf.DUMMYFUNCTION("""COMPUTED_VALUE"""),"CASHI ECOMMERCE RC CIUDAD DE MEX MEX") -> CASHI ECOMMERCE RC CIUDAD DE MEX MEX | H53: =IFERROR(__xludf.DUMMYFUNCTION("""COMPUTED_VALUE"""),"Cashi Ecommerce Rc Ciudad De Mex Mex") -> Cashi Ecommerce Rc Ciudad De Mex Mex | I53: =IFERROR(__xludf.DUMMYFUNCTION("""COMPUTED_VALUE"""),"Transaction cost") -> Transaction cost | J53: =IFERROR(__xludf.DUMMYFUNCTION("""COMPUTED_VALUE"""),"Transaction cost") -> Transaction cost | K53: =IFERROR(__xludf.DUMMYFUNCTION("""COMPUTED_VALUE"""),"Comida, entrega en Deacero ") -> Comida, entrega en Deacero | S53: 3610.38 | T53: =VLOOKUP(S53,D:F,3,FALSE) -> #N/A
A54: =IFERROR(__xludf.DUMMYFUNCTION("""COMPUTED_VALUE"""),"TRX1732") -> TRX1732 | B54: =IFERROR(__xludf.DUMMYFUNCTION("""COMPUTED_VALUE"""),"#6") -> #6 | C54: =IFERROR(__xludf.DUMMYFUNCTION("""COMPUTED_VALUE"""),46059.4173611111) -> 46059.417 | D54: =IFERROR(__xludf.DUMMYFUNCTION("""COMPUTED_VALUE"""),186) -> 186 | E54: =IFERROR(__xludf.DUMMYFUNCTION("""COMPUTED_VALUE"""),"MXN") -> MXN | F54: =IFERROR(__xludf.DUMMYFUNCTION("""COMPUTED_VALUE"""),"Fernando Sanchez Toledano") -> Fernando Sanchez Toledano | G54: =IFERROR(__xludf.DUMMYFUNCTION("""COMPUTED_VALUE"""),"OXXOMICROPARQUE QRF QUERETARO QRO MEX") -> OXXOMICROPARQUE QRF QUERETARO QRO MEX | H54: =IFERROR(__xludf.DUMMYFUNCTION("""COMPUTED_VALUE"""),"Oxxomicroparque Qrf Queretaro Qro Mex") -> Oxxomicroparque Qrf Queretaro Qro Mex | I54: =IFERROR(__xludf.DUMMYFUNCTION("""COMPUTED_VALUE"""),"Transaction cost") -> Transaction cost | J54: =IFERROR(__xludf.DUMMYFUNCTION("""COMPUTED_VALUE"""),"Transaction cost") -> Transaction cost | K54: =IFERROR(__xludf.DUMMYFUNCTION("""COMPUTED_VALUE"""),"Comida, entrega en Deacero ") -> Comida, entrega en Deacero | S54: 5920 | T54: =VLOOKUP(S54,D:F,3,FALSE) -> #N/A
A55: =IFERROR(__xludf.DUMMYFUNCTION("""COMPUTED_VALUE"""),"TRX1815") -> TRX1815 | B55: =IFERROR(__xludf.DUMMYFUNCTION("""COMPUTED_VALUE"""),"#6") -> #6 | C55: =IFERROR(__xludf.DUMMYFUNCTION("""COMPUTED_VALUE"""),46059.4173611111) -> 46059.417 | D55: =IFERROR(__xludf.DUMMYFUNCTION("""COMPUTED_VALUE"""),1545.3) -> 1545.3 | E55: =IFERROR(__xludf.DUMMYFUNCTION("""COMPUTED_VALUE"""),"MXN") -> MXN | F55: =IFERROR(__xludf.DUMMYFUNCTION("""COMPUTED_VALUE"""),"Fernando Sanchez Toledano") -> Fernando Sanchez Toledano | G55: =IFERROR(__xludf.DUMMYFUNCTION("""COMPUTED_VALUE"""),"GAS SERVI BOUL TEOLOYUCAN EM MEX") -> GAS SERVI BOUL TEOLOYUCAN EM MEX | H55: =IFERROR(__xludf.DUMMYFUNCTION("""COMPUTED_VALUE"""),"Gas Servi Boul Teoloyucan Em Mex") -> Gas Servi Boul Teoloyucan Em Mex | I55: =IFERROR(__xludf.DUMMYFUNCTION("""COMPUTED_VALUE"""),"Transaction cost") -> Transaction cost | J55: =IFERROR(__xludf.DUMMYFUNCTION("""COMPUTED_VALUE"""),"Transaction cost") -> Transaction cost | K55: =IFERROR(__xludf.DUMMYFUNCTION("""COMPUTED_VALUE"""),"Gasolina, entrega en SALJAMEX ") -> Gasolina, entrega en SALJAMEX | S55: 390 | T55: =VLOOKUP(S55,D:F,3,FALSE) -> #N/A
A56: =IFERROR(__xludf.DUMMYFUNCTION("""COMPUTED_VALUE"""),"TRX1939") -> TRX1939 | B56: =IFERROR(__xludf.DUMMYFUNCTION("""COMPUTED_VALUE"""),"#6") -> #6 | C56: =IFERROR(__xludf.DUMMYFUNCTION("""COMPUTED_VALUE"""),46059.4173611111) -> 46059.417 | D56: =IFERROR(__xludf.DUMMYFUNCTION("""COMPUTED_VALUE"""),1912.76) -> 1912.76 | E56: =IFERROR(__xludf.DUMMYFUNCTION("""COMPUTED_VALUE"""),"MXN") -> MXN | F56: =IFERROR(__xludf.DUMMYFUNCTION("""COMPUTED_VALUE"""),"Fernando Sanchez Toledano") -> Fernando Sanchez Toledano | G56: =IFERROR(__xludf.DUMMYFUNCTION("""COMPUTED_VALUE"""),"GASOL LOS APASEO APASEO EL ALT MEX") -> GASOL LOS APASEO APASEO EL ALT MEX | H56: =IFERROR(__xludf.DUMMYFUNCTION("""COMPUTED_VALUE"""),"Gasol Los Apaseo Apaseo El Alt Mex") -> Gasol Los Apaseo Apaseo El Alt Mex | I56: =IFERROR(__xludf.DUMMYFUNCTION("""COMPUTED_VALUE"""),"Transaction cost") -> Transaction cost | J56: =IFERROR(__xludf.DUMMYFUNCTION("""COMPUTED_VALUE"""),"Transaction cost") -> Transaction cost | S56: 405 | T56: =VLOOKUP(S56,D:F,3,FALSE) -> #N/A
A57: =IFERROR(__xludf.DUMMYFUNCTION("""COMPUTED_VALUE"""),"TRX1504") -> TRX1504 | B57: =IFERROR(__xludf.DUMMYFUNCTION("""COMPUTED_VALUE"""),"#6") -> #6 | C57: =IFERROR(__xludf.DUMMYFUNCTION("""COMPUTED_VALUE"""),46060.4166666666) -> 46060.417 | D57: =IFERROR(__xludf.DUMMYFUNCTION("""COMPUTED_VALUE"""),2216.15) -> 2216.15 | E57: =IFERROR(__xludf.DUMMYFUNCTION("""COMPUTED_VALUE"""),"MXN") -> MXN | F57: =IFERROR(__xludf.DUMMYFUNCTION("""COMPUTED_VALUE"""),"Fernando Sanchez Toledano") -> Fernando Sanchez Toledano | G57: =IFERROR(__xludf.DUMMYFUNCTION("""COMPUTED_VALUE"""),"AVIS MXN MERIDA YUC MEX") -> AVIS MXN MERIDA YUC MEX | H57: =IFERROR(__xludf.DUMMYFUNCTION("""COMPUTED_VALUE"""),"Avis Rent A Car") -> Avis Rent A Car | I57: =IFERROR(__xludf.DUMMYFUNCTION("""COMPUTED_VALUE"""),"Transaction cost") -> Transaction cost | J57: =IFERROR(__xludf.DUMMYFUNCTION("""COMPUTED_VALUE"""),"Transaction cost") -> Transaction cost | K57: =IFERROR(__xludf.DUMMYFUNCTION("""COMPUTED_VALUE"""),"Recolección Fer Marcelo ") -> Recolección Fer Marcelo | S57: 12782.67 | T57: =VLOOKUP(S57,D:F,3,FALSE) -> #N/A
A58: =IFERROR(__xludf.DUMMYFUNCTION("""COMPUTED_VALUE"""),"TRX1380") -> TRX1380 | B58: =IFERROR(__xludf.DUMMYFUNCTION("""COMPUTED_VALUE"""),"#6") -> #6 | C58: =IFERROR(__xludf.DUMMYFUNCTION("""COMPUTED_VALUE"""),46060.4166666666) -> 46060.417 | D58: =IFERROR(__xludf.DUMMYFUNCTION("""COMPUTED_VALUE"""),248) -> 248 | E58: =IFERROR(__xludf.DUMMYFUNCTION("""COMPUTED_VALUE"""),"MXN") -> MXN | F58: =IFERROR(__xludf.DUMMYFUNCTION("""COMPUTED_VALUE"""),"Fernando Sanchez Toledano") -> Fernando Sanchez Toledano | G58: =IFERROR(__xludf.DUMMYFUNCTION("""COMPUTED_VALUE"""),"KFC 1100 PIN TLACOPA TOLUCA EM MEX") -> KFC 1100 PIN TLACOPA TOLUCA EM MEX | H58: =IFERROR(__xludf.DUMMYFUNCTION("""COMPUTED_VALUE"""),"Kentucky Fried Chicken") -> Kentucky Fried Chicken | I58: =IFERROR(__xludf.DUMMYFUNCTION("""COMPUTED_VALUE"""),"Transaction cost") -> Transaction cost | J58: =IFERROR(__xludf.DUMMYFUNCTION("""COMPUTED_VALUE"""),"Transaction cost") -> Transaction cost | K58: =IFERROR(__xludf.DUMMYFUNCTION("""COMPUTED_VALUE"""),"Gasolina recolección Fer Marcelo") -> Gasolina recolección Fer Marcelo | S58: 6743.27 | T58: =VLOOKUP(S58,D:F,3,FALSE) -> #N/A
A59: =IFERROR(__xludf.DUMMYFUNCTION("""COMPUTED_VALUE"""),"TRX1533") -> TRX1533 | B59: =IFERROR(__xludf.DUMMYFUNCTION("""COMPUTED_VALUE"""),"#6") -> #6 | C59: =IFERROR(__xludf.DUMMYFUNCTION("""COMPUTED_VALUE"""),46070.4166666666) -> 46070.417 | D59: =IFERROR(__xludf.DUMMYFUNCTION("""COMPUTED_VALUE"""),38.53) -> 38.53 | E59: =IFERROR(__xludf.DUMMYFUNCTION("""COMPUTED_VALUE"""),"MXN") -> MXN | F59: =IFERROR(__xludf.DUMMYFUNCTION("""COMPUTED_VALUE"""),"Fernando Sanchez Toledano") -> Fernando Sanchez Toledano | G59: =IFERROR(__xludf.DUMMYFUNCTION("""COMPUTED_VALUE"""),"DLO DIDI RIDES MX CIUDAD DE MEX MEX") -> DLO DIDI RIDES MX CIUDAD DE MEX MEX | H59: =IFERROR(__xludf.DUMMYFUNCTION("""COMPUTED_VALUE"""),"Didi Chuxing") -> Didi Chuxing | I59: =IFERROR(__xludf.DUMMYFUNCTION("""COMPUTED_VALUE"""),"Transaction cost") -> Transaction cost | J59: =IFERROR(__xludf.DUMMYFUNCTION("""COMPUTED_VALUE"""),"Transaction cost") -> Transaction cost | K59: =IFERROR(__xludf.DUMMYFUNCTION("""COMPUTED_VALUE"""),"Parquímetro") -> Parquímetro | S59: 1101.6 | T59: =VLOOKUP(S59,D:F,3,FALSE) -> #N/A
A60: =IFERROR(__xludf.DUMMYFUNCTION("""COMPUTED_VALUE"""),"TRX1493") -> TRX1493 | B60: =IFERROR(__xludf.DUMMYFUNCTION("""COMPUTED_VALUE"""),"#6") -> #6 | C60: =IFERROR(__xludf.DUMMYFUNCTION("""COMPUTED_VALUE"""),46070.4166666666) -> 46070.417 | D60: =IFERROR(__xludf.DUMMYFUNCTION("""COMPUTED_VALUE"""),132) -> 132 | E60: =IFERROR(__xludf.DUMMYFUNCTION("""COMPUTED_VALUE"""),"MXN") -> MXN | F60: =IFERROR(__xludf.DUMMYFUNCTION("""COMPUTED_VALUE"""),"Fernando Sanchez Toledano") -> Fernando Sanchez Toledano | G60: =IFERROR(__xludf.DUMMYFUNCTION("""COMPUTED_VALUE"""),"DLO DIDI RIDES MX CIUDAD DE MEX MEX") -> DLO DIDI RIDES MX CIUDAD DE MEX MEX | H60: =IFERROR(__xludf.DUMMYFUNCTION("""COMPUTED_VALUE"""),"Didi Chuxing") -> Didi Chuxing | I60: =IFERROR(__xludf.DUMMYFUNCTION("""COMPUTED_VALUE"""),"Transaction cost") -> Transaction cost | J60: =IFERROR(__xludf.DUMMYFUNCTION("""COMPUTED_VALUE"""),"Transaction cost") -> Transaction cost | K60: =IFERROR(__xludf.DUMMYFUNCTION("""COMPUTED_VALUE"""),"Recarga de tag") -> Recarga de tag | S60: 1050.6 | T60: =VLOOKUP(S60,D:F,3,FALSE) -> #N/A
A61: =IFERROR(__xludf.DUMMYFUNCTION("""COMPUTED_VALUE"""),"TRX1351") -> TRX1351 | B61: =IFERROR(__xludf.DUMMYFUNCTION("""COMPUTED_VALUE"""),"#6") -> #6 | C61: =IFERROR(__xludf.DUMMYFUNCTION("""COMPUTED_VALUE"""),46071.4166666666) -> 46071.417 | D61: =IFERROR(__xludf.DUMMYFUNCTION("""COMPUTED_VALUE"""),76) -> 76 | E61: =IFERROR(__xludf.DUMMYFUNCTION("""COMPUTED_VALUE"""),"MXN") -> MXN | F61: =IFERROR(__xludf.DUMMYFUNCTION("""COMPUTED_VALUE"""),"Fernando Sanchez Toledano") -> Fernando Sanchez Toledano | G61: =IFERROR(__xludf.DUMMYFUNCTION("""COMPUTED_VALUE"""),"DLO DIDI RIDES MX CIUDAD DE MEX MEX") -> DLO DIDI RIDES MX CIUDAD DE MEX MEX | H61: =IFERROR(__xludf.DUMMYFUNCTION("""COMPUTED_VALUE"""),"Didi Chuxing") -> Didi Chuxing | I61: =IFERROR(__xludf.DUMMYFUNCTION("""COMPUTED_VALUE"""),"Transaction cost") -> Transaction cost | J61: =IFERROR(__xludf.DUMMYFUNCTION("""COMPUTED_VALUE"""),"Transaction cost") -> Transaction cost | K61: =IFERROR(__xludf.DUMMYFUNCTION("""COMPUTED_VALUE"""),"Gasolina, entrega en Deacero ") -> Gasolina, entrega en Deacero | S61: 1130.72 | T61: =VLOOKUP(S61,D:F,3,FALSE) -> #N/A
A62: =IFERROR(__xludf.DUMMYFUNCTION("""COMPUTED_VALUE"""),"TRX1066") -> TRX1066 | B62: =IFERROR(__xludf.DUMMYFUNCTION("""COMPUTED_VALUE"""),"#6") -> #6 | C62: =IFERROR(__xludf.DUMMYFUNCTION("""COMPUTED_VALUE"""),46071.4166666666) -> 46071.417 | D62: =IFERROR(__xludf.DUMMYFUNCTION("""COMPUTED_VALUE"""),196) -> 196 | E62: =IFERROR(__xludf.DUMMYFUNCTION("""COMPUTED_VALUE"""),"MXN") -> MXN | F62: =IFERROR(__xludf.DUMMYFUNCTION("""COMPUTED_VALUE"""),"Fernando Sanchez Toledano") -> Fernando Sanchez Toledano | G62: =IFERROR(__xludf.DUMMYFUNCTION("""COMPUTED_VALUE"""),"OXXO JAJALPA TLC OCOYOACAC EM MEX") -> OXXO JAJALPA TLC OCOYOACAC EM MEX | H62: =IFERROR(__xludf.DUMMYFUNCTION("""COMPUTED_VALUE"""),"Oxxo") -> Oxxo | I62: =IFERROR(__xludf.DUMMYFUNCTION("""COMPUTED_VALUE"""),"Transaction cost") -> Transaction cost | J62: =IFERROR(__xludf.DUMMYFUNCTION("""COMPUTED_VALUE"""),"Transaction cost") -> Transaction cost | K62: =IFERROR(__xludf.DUMMYFUNCTION("""COMPUTED_VALUE"""),"Aceite camioneta") -> Aceite camioneta | S62: 155 | T62: =VLOOKUP(S62,D:F,3,FALSE) -> #N/A
A63: =IFERROR(__xludf.DUMMYFUNCTION("""COMPUTED_VALUE"""),"TRX1690") -> TRX1690 | B63: =IFERROR(__xludf.DUMMYFUNCTION("""COMPUTED_VALUE"""),"#6") -> #6 | C63: =IFERROR(__xludf.DUMMYFUNCTION("""COMPUTED_VALUE"""),46071.4166666666) -> 46071.417 | D63: =IFERROR(__xludf.DUMMYFUNCTION("""COMPUTED_VALUE"""),1000) -> 1000 | E63: =IFERROR(__xludf.DUMMYFUNCTION("""COMPUTED_VALUE"""),"MXN") -> MXN | F63: =IFERROR(__xludf.DUMMYFUNCTION("""COMPUTED_VALUE"""),"Fernando Sanchez Toledano") -> Fernando Sanchez Toledano | G63: =IFERROR(__xludf.DUMMYFUNCTION("""COMPUTED_VALUE"""),"CASHI ECOMMERCE RC CIUDAD DE MEX MEX") -> CASHI ECOMMERCE RC CIUDAD DE MEX MEX | H63: =IFERROR(__xludf.DUMMYFUNCTION("""COMPUTED_VALUE"""),"Cashi Ecommerce Rc Ciudad De Mex Mex") -> Cashi Ecommerce Rc Ciudad De Mex Mex | I63: =IFERROR(__xludf.DUMMYFUNCTION("""COMPUTED_VALUE"""),"Transaction cost") -> Transaction cost | J63: =IFERROR(__xludf.DUMMYFUNCTION("""COMPUTED_VALUE"""),"Transaction cost") -> Transaction cost | K63: =IFERROR(__xludf.DUMMYFUNCTION("""COMPUTED_VALUE"""),"Comida entrega en deacero") -> Comida entrega en deacero | S63: 5660.42 | T63: =VLOOKUP(S63,D:F,3,FALSE) -> #N/A
A64: =IFERROR(__xludf.DUMMYFUNCTION("""COMPUTED_VALUE"""),"TRX1102") -> TRX1102 | B64: =IFERROR(__xludf.DUMMYFUNCTION("""COMPUTED_VALUE"""),"#6") -> #6 | C64: =IFERROR(__xludf.DUMMYFUNCTION("""COMPUTED_VALUE"""),46071.4166666666) -> 46071.417 | D64: =IFERROR(__xludf.DUMMYFUNCTION("""COMPUTED_VALUE"""),1233.86) -> 1233.86 | E64: =IFERROR(__xludf.DUMMYFUNCTION("""COMPUTED_VALUE"""),"MXN") -> MXN | F64: =IFERROR(__xludf.DUMMYFUNCTION("""COMPUTED_VALUE"""),"Fernando Sanchez Toledano") -> Fernando Sanchez Toledano | G64: =IFERROR(__xludf.DUMMYFUNCTION("""COMPUTED_VALUE"""),"AVIS WEB MXN MERIDA YUC MEX") -> AVIS WEB MXN MERIDA YUC MEX | H64: =IFERROR(__xludf.DUMMYFUNCTION("""COMPUTED_VALUE"""),"Avis") -> Avis | I64: =IFERROR(__xludf.DUMMYFUNCTION("""COMPUTED_VALUE"""),"Transaction cost") -> Transaction cost | J64: =IFERROR(__xludf.DUMMYFUNCTION("""COMPUTED_VALUE"""),"Transaction cost") -> Transaction cost | K64: =IFERROR(__xludf.DUMMYFUNCTION("""COMPUTED_VALUE"""),"Comida entrega en Deacero") -> Comida entrega en Deacero | S64: 247.26 | T64: =VLOOKUP(S64,D:F,3,FALSE) -> #N/A
A65: =IFERROR(__xludf.DUMMYFUNCTION("""COMPUTED_VALUE"""),"TRX1139") -> TRX1139 | B65: =IFERROR(__xludf.DUMMYFUNCTION("""COMPUTED_VALUE"""),"#6") -> #6 | C65: =IFERROR(__xludf.DUMMYFUNCTION("""COMPUTED_VALUE"""),46071.4173611111) -> 46071.417 | D65: =IFERROR(__xludf.DUMMYFUNCTION("""COMPUTED_VALUE"""),283) -> 283 | E65: =IFERROR(__xludf.DUMMYFUNCTION("""COMPUTED_VALUE"""),"MXN") -> MXN | F65: =IFERROR(__xludf.DUMMYFUNCTION("""COMPUTED_VALUE"""),"Fernando Sanchez Toledano") -> Fernando Sanchez Toledano | G65: =IFERROR(__xludf.DUMMYFUNCTION("""COMPUTED_VALUE"""),"BK ALFREDO DEL MAZO TOLUCA EM MEX") -> BK ALFREDO DEL MAZO TOLUCA EM MEX | H65: =IFERROR(__xludf.DUMMYFUNCTION("""COMPUTED_VALUE"""),"Bk Alfredo Del Mazo Toluca Em Mex") -> Bk Alfredo Del Mazo Toluca Em Mex | I65: =IFERROR(__xludf.DUMMYFUNCTION("""COMPUTED_VALUE"""),"Transaction cost") -> Transaction cost | J65: =IFERROR(__xludf.DUMMYFUNCTION("""COMPUTED_VALUE"""),"Transaction cost") -> Transaction cost | K65: =IFERROR(__xludf.DUMMYFUNCTION("""COMPUTED_VALUE"""),"Gasolina recolección en wonderdesk") -> Gasolina recolección en wonderdesk | S65: 487 | T65: =VLOOKUP(S65,D:F,3,FALSE) -> #N/A
A66: =IFERROR(__xludf.DUMMYFUNCTION("""COMPUTED_VALUE"""),"TRX1843") -> TRX1843 | B66: =IFERROR(__xludf.DUMMYFUNCTION("""COMPUTED_VALUE"""),"#6") -> #6 | C66: =IFERROR(__xludf.DUMMYFUNCTION("""COMPUTED_VALUE"""),46072.4166666666) -> 46072.417 | D66: =IFERROR(__xludf.DUMMYFUNCTION("""COMPUTED_VALUE"""),410.25) -> 410.25 | E66: =IFERROR(__xludf.DUMMYFUNCTION("""COMPUTED_VALUE"""),"MXN") -> MXN | F66: =IFERROR(__xludf.DUMMYFUNCTION("""COMPUTED_VALUE"""),"Fernando Sanchez Toledano") -> Fernando Sanchez Toledano | G66: =IFERROR(__xludf.DUMMYFUNCTION("""COMPUTED_VALUE"""),"GAS COGA LOM CHA MIT 2 CIUDAD DE MEX MEX") -> GAS COGA LOM CHA MIT 2 CIUDAD DE MEX MEX | H66: =IFERROR(__xludf.DUMMYFUNCTION("""COMPUTED_VALUE"""),"Gas Coga Lom Cha Mit 2 Ciudad De Mex Mex") -> Gas Coga Lom Cha Mit 2 Ciudad De Mex Mex | I66: =IFERROR(__xludf.DUMMYFUNCTION("""COMPUTED_VALUE"""),"Transaction cost") -> Transaction cost | J66: =IFERROR(__xludf.DUMMYFUNCTION("""COMPUTED_VALUE"""),"Transaction cost") -> Transaction cost | K66: =IFERROR(__xludf.DUMMYFUNCTION("""COMPUTED_VALUE"""),"Comoda, recolección en Fer Marcelo") -> Comoda, recolección en Fer Marcelo | S66: 228.85 | T66: =VLOOKUP(S66,D:F,3,FALSE) -> #N/A
A67: =IFERROR(__xludf.DUMMYFUNCTION("""COMPUTED_VALUE"""),"TRX1234") -> TRX1234 | B67: =IFERROR(__xludf.DUMMYFUNCTION("""COMPUTED_VALUE"""),"#6") -> #6 | C67: =IFERROR(__xludf.DUMMYFUNCTION("""COMPUTED_VALUE"""),46072.4166666666) -> 46072.417 | D67: =IFERROR(__xludf.DUMMYFUNCTION("""COMPUTED_VALUE"""),145) -> 145 | E67: =IFERROR(__xludf.DUMMYFUNCTION("""COMPUTED_VALUE"""),"MXN") -> MXN | F67: =IFERROR(__xludf.DUMMYFUNCTION("""COMPUTED_VALUE"""),"Fernando Sanchez Toledano") -> Fernando Sanchez Toledano | G67: =IFERROR(__xludf.DUMMYFUNCTION("""COMPUTED_VALUE"""),"DLO DIDI RIDES MX CIUDAD DE MEX MEX") -> DLO DIDI RIDES MX CIUDAD DE MEX MEX | H67: =IFERROR(__xludf.DUMMYFUNCTION("""COMPUTED_VALUE"""),"Didi Chuxing") -> Didi Chuxing | I67: =IFERROR(__xludf.DUMMYFUNCTION("""COMPUTED_VALUE"""),"Transaction cost") -> Transaction cost | J67: =IFERROR(__xludf.DUMMYFUNCTION("""COMPUTED_VALUE"""),"Transaction cost") -> Transaction cost | K67: =IFERROR(__xludf.DUMMYFUNCTION("""COMPUTED_VALUE"""),"Recarga de tag") -> Recarga de tag | S67: 118.32 | T67: =VLOOKUP(S67,D:F,3,FALSE) -> #N/A
A68: =IFERROR(__xludf.DUMMYFUNCTION("""COMPUTED_VALUE"""),"TRX1712") -> TRX1712 | B68: =IFERROR(__xludf.DUMMYFUNCTION("""COMPUTED_VALUE"""),"#6") -> #6 | C68: =IFERROR(__xludf.DUMMYFUNCTION("""COMPUTED_VALUE"""),46072.4166666666) -> 46072.417 | D68: =IFERROR(__xludf.DUMMYFUNCTION("""COMPUTED_VALUE"""),190) -> 190 | E68: =IFERROR(__xludf.DUMMYFUNCTION("""COMPUTED_VALUE"""),"MXN") -> MXN | F68: =IFERROR(__xludf.DUMMYFUNCTION("""COMPUTED_VALUE"""),"Fernando Sanchez Toledano") -> Fernando Sanchez Toledano | G68: =IFERROR(__xludf.DUMMYFUNCTION("""COMPUTED_VALUE"""),"OXXOMICROPARQUE QRF QUERETARO QRO MEX") -> OXXOMICROPARQUE QRF QUERETARO QRO MEX | H68: =IFERROR(__xludf.DUMMYFUNCTION("""COMPUTED_VALUE"""),"Oxxomicroparque Qrf Queretaro Qro Mex") -> Oxxomicroparque Qrf Queretaro Qro Mex | I68: =IFERROR(__xludf.DUMMYFUNCTION("""COMPUTED_VALUE"""),"Transaction cost") -> Transaction cost | J68: =IFERROR(__xludf.DUMMYFUNCTION("""COMPUTED_VALUE"""),"Transaction cost") -> Transaction cost | K68: =IFERROR(__xludf.DUMMYFUNCTION("""COMPUTED_VALUE"""),"Gasolina entrega en Deacero, PROSI ") -> Gasolina entrega en Deacero, PROSI | S68: 1366.99 | T68: =VLOOKUP(S68,D:F,3,FALSE) -> #N/A
A69: =IFERROR(__xludf.DUMMYFUNCTION("""COMPUTED_VALUE"""),"TRX1764") -> TRX1764 | B69: =IFERROR(__xludf.DUMMYFUNCTION("""COMPUTED_VALUE"""),"#6") -> #6 | C69: =IFERROR(__xludf.DUMMYFUNCTION("""COMPUTED_VALUE"""),46072.4166666666) -> 46072.417 | D69: =IFERROR(__xludf.DUMMYFUNCTION("""COMPUTED_VALUE"""),500) -> 500 | E69: =IFERROR(__xludf.DUMMYFUNCTION("""COMPUTED_VALUE"""),"MXN") -> MXN | F69: =IFERROR(__xludf.DUMMYFUNCTION("""COMPUTED_VALUE"""),"Fernando Sanchez Toledano") -> Fernando Sanchez Toledano | G69: =IFERROR(__xludf.DUMMYFUNCTION("""COMPUTED_VALUE"""),"CASHI ECOMMERCE RC CIUDAD DE MEX MEX") -> CASHI ECOMMERCE RC CIUDAD DE MEX MEX | H69: =IFERROR(__xludf.DUMMYFUNCTION("""COMPUTED_VALUE"""),"Cashi Ecommerce Rc Ciudad De Mex Mex") -> Cashi Ecommerce Rc Ciudad De Mex Mex | I69: =IFERROR(__xludf.DUMMYFUNCTION("""COMPUTED_VALUE"""),"Transaction cost") -> Transaction cost | J69: =IFERROR(__xludf.DUMMYFUNCTION("""COMPUTED_VALUE"""),"Transaction cost") -> Transaction cost | K69: =IFERROR(__xludf.DUMMYFUNCTION("""COMPUTED_VALUE"""),"Comida entrega en Deacero") -> Comida entrega en Deacero | S69: 2240.15 | T69: =VLOOKUP(S69,D:F,3,FALSE) -> #N/A
A70: =IFERROR(__xludf.DUMMYFUNCTION("""COMPUTED_VALUE"""),"TRX1610") -> TRX1610 | B70: =IFERROR(__xludf.DUMMYFUNCTION("""COMPUTED_VALUE"""),"#6") -> #6 | C70: =IFERROR(__xludf.DUMMYFUNCTION("""COMPUTED_VALUE"""),46072.4173611111) -> 46072.417 | D70: =IFERROR(__xludf.DUMMYFUNCTION("""COMPUTED_VALUE"""),2139.51) -> 2139.51 | E70: =IFERROR(__xludf.DUMMYFUNCTION("""COMPUTED_VALUE"""),"MXN") -> MXN | F70: =IFERROR(__xludf.DUMMYFUNCTION("""COMPUTED_VALUE"""),"Fernando Sanchez Toledano") -> Fernando Sanchez Toledano | G70: =IFERROR(__xludf.DUMMYFUNCTION("""COMPUTED_VALUE"""),"AVIS MXN MERIDA YUC MEX") -> AVIS MXN MERIDA YUC MEX | H70: =IFERROR(__xludf.DUMMYFUNCTION("""COMPUTED_VALUE"""),"Avis Rent A Car") -> Avis Rent A Car | I70: =IFERROR(__xludf.DUMMYFUNCTION("""COMPUTED_VALUE"""),"Transaction cost") -> Transaction cost | J70: =IFERROR(__xludf.DUMMYFUNCTION("""COMPUTED_VALUE"""),"Transaction cost") -> Transaction cost | S70: 768612.13 | T70: =VLOOKUP(S70,D:F,3,FALSE) -> #N/A
A71: =IFERROR(__xludf.DUMMYFUNCTION("""COMPUTED_VALUE"""),"TRX1314") -> TRX1314 | B71: =IFERROR(__xludf.DUMMYFUNCTION("""COMPUTED_VALUE"""),"#6") -> #6 | C71: =IFERROR(__xludf.DUMMYFUNCTION("""COMPUTED_VALUE"""),46072.4173611111) -> 46072.417 | D71: =IFERROR(__xludf.DUMMYFUNCTION("""COMPUTED_VALUE"""),1485.35) -> 1485.35 | E71: =IFERROR(__xludf.DUMMYFUNCTION("""COMPUTED_VALUE"""),"MXN") -> MXN | F71: =IFERROR(__xludf.DUMMYFUNCTION("""COMPUTED_VALUE"""),"Fernando Sanchez Toledano") -> Fernando Sanchez Toledano | G71: =IFERROR(__xludf.DUMMYFUNCTION("""COMPUTED_VALUE"""),"SERVI FER TECAMAC TECAMAC EM MEX") -> SERVI FER TECAMAC TECAMAC EM MEX | H71: =IFERROR(__xludf.DUMMYFUNCTION("""COMPUTED_VALUE"""),"Servi Fer Tecamac Tecamac Em Mex") -> Servi Fer Tecamac Tecamac Em Mex | I71: =IFERROR(__xludf.DUMMYFUNCTION("""COMPUTED_VALUE"""),"Transaction cost") -> Transaction cost | J71: =IFERROR(__xludf.DUMMYFUNCTION("""COMPUTED_VALUE"""),"Transaction cost") -> Transaction cost | S71: 198 | T71: =VLOOKUP(S71,D:F,3,FALSE) -> #N/A
A72: =IFERROR(__xludf.DUMMYFUNCTION("""COMPUTED_VALUE"""),"TRX1083") -> TRX1083 | B72: =IFERROR(__xludf.DUMMYFUNCTION("""COMPUTED_VALUE"""),"#6") -> #6 | C72: =IFERROR(__xludf.DUMMYFUNCTION("""COMPUTED_VALUE"""),46075.4173611111) -> 46075.417 | D72: =IFERROR(__xludf.DUMMYFUNCTION("""COMPUTED_VALUE"""),1479) -> 1479 | E72: =IFERROR(__xludf.DUMMYFUNCTION("""COMPUTED_VALUE"""),"MXN") -> MXN | F72: =IFERROR(__xludf.DUMMYFUNCTION("""COMPUTED_VALUE"""),"Fernando Sanchez Toledano") -> Fernando Sanchez Toledano | G72: =IFERROR(__xludf.DUMMYFUNCTION("""COMPUTED_VALUE"""),"SERVICIO HERRADURA HUIXQUILUCAN MEX") -> SERVICIO HERRADURA HUIXQUILUCAN MEX | H72: =IFERROR(__xludf.DUMMYFUNCTION("""COMPUTED_VALUE"""),"Servicio Herradura Huixquilucan Mex") -> Servicio Herradura Huixquilucan Mex | I72: =IFERROR(__xludf.DUMMYFUNCTION("""COMPUTED_VALUE"""),"Transaction cost") -> Transaction cost | J72: =IFERROR(__xludf.DUMMYFUNCTION("""COMPUTED_VALUE"""),"Transaction cost") -> Transaction cost | S72: 556.6 | T72: =VLOOKUP(S72,D:F,3,FALSE) -> #N/A
A73: =IFERROR(__xludf.DUMMYFUNCTION("""COMPUTED_VALUE"""),"TRX1291") -> TRX1291 | B73: =IFERROR(__xludf.DUMMYFUNCTION("""COMPUTED_VALUE"""),"#7") -> #7 | C73: =IFERROR(__xludf.DUMMYFUNCTION("""COMPUTED_VALUE"""),46056.4166666666) -> 46056.417 | D73: =IFERROR(__xludf.DUMMYFUNCTION("""COMPUTED_VALUE"""),341.6) -> 341.6 | E73: =IFERROR(__xludf.DUMMYFUNCTION("""COMPUTED_VALUE"""),"MXN") -> MXN | F73: =IFERROR(__xludf.DUMMYFUNCTION("""COMPUTED_VALUE"""),"Isaac Mendoza Ruiz") -> Isaac Mendoza Ruiz | G73: =IFERROR(__xludf.DUMMYFUNCTION("""COMPUTED_VALUE"""),"UBER * EATS PENDING CMX MEX") -> UBER * EATS PENDING CMX MEX | H73: =IFERROR(__xludf.DUMMYFUNCTION("""COMPUTED_VALUE"""),"Uber Eats") -> Uber Eats | I73: =IFERROR(__xludf.DUMMYFUNCTION("""COMPUTED_VALUE"""),"Office expenses") -> Office expenses | J73: =IFERROR(__xludf.DUMMYFUNCTION("""COMPUTED_VALUE"""),"MTY ATP + Maken") -> MTY ATP + Maken | K73: =IFERROR(__xludf.DUMMYFUNCTION("""COMPUTED_VALUE"""),".") -> . | S73: 160.25 | T73: =VLOOKUP(S73,D:F,3,FALSE) -> #N/A
A74: =IFERROR(__xludf.DUMMYFUNCTION("""COMPUTED_VALUE"""),"TRX1156") -> TRX1156 | B74: =IFERROR(__xludf.DUMMYFUNCTION("""COMPUTED_VALUE"""),"#7") -> #7 | C74: =IFERROR(__xludf.DUMMYFUNCTION("""COMPUTED_VALUE"""),46059.4173611111) -> 46059.417 | D74: =IFERROR(__xludf.DUMMYFUNCTION("""COMPUTED_VALUE"""),120) -> 120 | E74: =IFERROR(__xludf.DUMMYFUNCTION("""COMPUTED_VALUE"""),"MXN") -> MXN | F74: =IFERROR(__xludf.DUMMYFUNCTION("""COMPUTED_VALUE"""),"Isaac Mendoza Ruiz") -> Isaac Mendoza Ruiz | G74: =IFERROR(__xludf.DUMMYFUNCTION("""COMPUTED_VALUE"""),"EL SAZON DE MAMA CIUDAD DE MEX MEX") -> EL SAZON DE MAMA CIUDAD DE MEX MEX | H74: =IFERROR(__xludf.DUMMYFUNCTION("""COMPUTED_VALUE"""),"El Sazon De Mama Ciudad De Mex Mex") -> El Sazon De Mama Ciudad De Mex Mex | I74: =IFERROR(__xludf.DUMMYFUNCTION("""COMPUTED_VALUE"""),"Office expenses") -> Office expenses | J74: =IFERROR(__xludf.DUMMYFUNCTION("""COMPUTED_VALUE"""),"MTY ATP + Maken") -> MTY ATP + Maken | K74: =IFERROR(__xludf.DUMMYFUNCTION("""COMPUTED_VALUE"""),".") -> . | S74: 228 | T74: =VLOOKUP(S74,D:F,3,FALSE) -> Karen Alexandra Ballesteros Contreras
A75: =IFERROR(__xludf.DUMMYFUNCTION("""COMPUTED_VALUE"""),"TRX1160") -> TRX1160 | B75: =IFERROR(__xludf.DUMMYFUNCTION("""COMPUTED_VALUE"""),"#7") -> #7 | C75: =IFERROR(__xludf.DUMMYFUNCTION("""COMPUTED_VALUE"""),46060.4166666666) -> 46060.417 | D75: =IFERROR(__xludf.DUMMYFUNCTION("""COMPUTED_VALUE"""),276.69) -> 276.69 | E75: =IFERROR(__xludf.DUMMYFUNCTION("""COMPUTED_VALUE"""),"MXN") -> MXN | F75: =IFERROR(__xludf.DUMMYFUNCTION("""COMPUTED_VALUE"""),"Isaac Mendoza Ruiz") -> Isaac Mendoza Ruiz | G75: =IFERROR(__xludf.DUMMYFUNCTION("""COMPUTED_VALUE"""),"UBER * PENDING CMX MEX") -> UBER * PENDING CMX MEX | H75: =IFERROR(__xludf.DUMMYFUNCTION("""COMPUTED_VALUE"""),"Uber") -> Uber | I75: =IFERROR(__xludf.DUMMYFUNCTION("""COMPUTED_VALUE"""),"Office expenses") -> Office expenses | J75: =IFERROR(__xludf.DUMMYFUNCTION("""COMPUTED_VALUE"""),"Viaje Puebla - Industrias Norm") -> Viaje Puebla - Industrias Norm | K75: =IFERROR(__xludf.DUMMYFUNCTION("""COMPUTED_VALUE"""),".") -> . | S75: 90.42 | T75: =VLOOKUP(S75,D:F,3,FALSE) -> #N/A
A76: =IFERROR(__xludf.DUMMYFUNCTION("""COMPUTED_VALUE"""),"TRX1059") -> TRX1059 | B76: =IFERROR(__xludf.DUMMYFUNCTION("""COMPUTED_VALUE"""),"#7") -> #7 | C76: =IFERROR(__xludf.DUMMYFUNCTION("""COMPUTED_VALUE"""),46064.4166666666) -> 46064.417 | D76: =IFERROR(__xludf.DUMMYFUNCTION("""COMPUTED_VALUE"""),334.12) -> 334.12 | E76: =IFERROR(__xludf.DUMMYFUNCTION("""COMPUTED_VALUE"""),"MXN") -> MXN | F76: =IFERROR(__xludf.DUMMYFUNCTION("""COMPUTED_VALUE"""),"Isaac Mendoza Ruiz") -> Isaac Mendoza Ruiz | G76: =IFERROR(__xludf.DUMMYFUNCTION("""COMPUTED_VALUE"""),"UBER * PENDING CMX MEX") -> UBER * PENDING CMX MEX | H76: =IFERROR(__xludf.DUMMYFUNCTION("""COMPUTED_VALUE"""),"Uber") -> Uber | I76: =IFERROR(__xludf.DUMMYFUNCTION("""COMPUTED_VALUE"""),"Office expenses") -> Office expenses | J76: =IFERROR(__xludf.DUMMYFUNCTION("""COMPUTED_VALUE"""),"MTY ATP + Maken") -> MTY ATP + Maken | K76: =IFERROR(__xludf.DUMMYFUNCTION("""COMPUTED_VALUE"""),".") -> . | S76: 97.05 | T76: =VLOOKUP(S76,D:F,3,FALSE) -> #N/A
A77: =IFERROR(__xludf.DUMMYFUNCTION("""COMPUTED_VALUE"""),"TRX1154") -> TRX1154 | B77: =IFERROR(__xludf.DUMMYFUNCTION("""COMPUTED_VALUE"""),"#7") -> #7 | C77: =IFERROR(__xludf.DUMMYFUNCTION("""COMPUTED_VALUE"""),46064.4166666666) -> 46064.417 | D77: =IFERROR(__xludf.DUMMYFUNCTION("""COMPUTED_VALUE"""),65.79) -> 65.79 | E77: =IFERROR(__xludf.DUMMYFUNCTION("""COMPUTED_VALUE"""),"MXN") -> MXN | F77: =IFERROR(__xludf.DUMMYFUNCTION("""COMPUTED_VALUE"""),"Isaac Mendoza Ruiz") -> Isaac Mendoza Ruiz | G77: =IFERROR(__xludf.DUMMYFUNCTION("""COMPUTED_VALUE"""),"UBER *TRIP HELP.UBER.C CMX MEX") -> UBER *TRIP HELP.UBER.C CMX MEX | H77: =IFERROR(__xludf.DUMMYFUNCTION("""COMPUTED_VALUE"""),"Uber") -> Uber | I77: =IFERROR(__xludf.DUMMYFUNCTION("""COMPUTED_VALUE"""),"Office expenses") -> Office expenses | J77: =IFERROR(__xludf.DUMMYFUNCTION("""COMPUTED_VALUE"""),"MTY ATP + Maken") -> MTY ATP + Maken | K77: =IFERROR(__xludf.DUMMYFUNCTION("""COMPUTED_VALUE"""),".") -> . | S77: 659.71 | T77: =VLOOKUP(S77,D:F,3,FALSE) -> #N/A
A78: =IFERROR(__xludf.DUMMYFUNCTION("""COMPUTED_VALUE"""),"TRX1113") -> TRX1113 | B78: =IFERROR(__xludf.DUMMYFUNCTION("""COMPUTED_VALUE"""),"#7") -> #7 | C78: =IFERROR(__xludf.DUMMYFUNCTION("""COMPUTED_VALUE"""),46077.4166666666) -> 46077.417 | D78: =IFERROR(__xludf.DUMMYFUNCTION("""COMPUTED_VALUE"""),69.98) -> 69.98 | E78: =IFERROR(__xludf.DUMMYFUNCTION("""COMPUTED_VALUE"""),"MXN") -> MXN | F78: =IFERROR(__xludf.DUMMYFUNCTION("""COMPUTED_VALUE"""),"Isaac Mendoza Ruiz") -> Isaac Mendoza Ruiz | G78: =IFERROR(__xludf.DUMMYFUNCTION("""COMPUTED_VALUE"""),"DLO*Uber CDMX MEX") -> DLO*Uber CDMX MEX | H78: =IFERROR(__xludf.DUMMYFUNCTION("""COMPUTED_VALUE"""),"Uber") -> Uber | I78: =IFERROR(__xludf.DUMMYFUNCTION("""COMPUTED_VALUE"""),"Office expenses") -> Office expenses | J78: =IFERROR(__xludf.DUMMYFUNCTION("""COMPUTED_VALUE"""),"MTY ATP + Maken") -> MTY ATP + Maken | K78: =IFERROR(__xludf.DUMMYFUNCTION("""COMPUTED_VALUE"""),".") -> . | S78: 566.82 | T78: =VLOOKUP(S78,D:F,3,FALSE) -> #N/A
A79: =IFERROR(__xludf.DUMMYFUNCTION("""COMPUTED_VALUE"""),"TRX1129") -> TRX1129 | B79: =IFERROR(__xludf.DUMMYFUNCTION("""COMPUTED_VALUE"""),"#7") -> #7 | C79: =IFERROR(__xludf.DUMMYFUNCTION("""COMPUTED_VALUE"""),46078.4166666666) -> 46078.417 | D79: =IFERROR(__xludf.DUMMYFUNCTION("""COMPUTED_VALUE"""),79.95) -> 79.95 | E79: =IFERROR(__xludf.DUMMYFUNCTION("""COMPUTED_VALUE"""),"MXN") -> MXN | F79: =IFERROR(__xludf.DUMMYFUNCTION("""COMPUTED_VALUE"""),"Isaac Mendoza Ruiz") -> Isaac Mendoza Ruiz | G79: =IFERROR(__xludf.DUMMYFUNCTION("""COMPUTED_VALUE"""),"UBER * PENDING CMX MEX") -> UBER * PENDING CMX MEX | H79: =IFERROR(__xludf.DUMMYFUNCTION("""COMPUTED_VALUE"""),"Uber") -> Uber | I79: =IFERROR(__xludf.DUMMYFUNCTION("""COMPUTED_VALUE"""),"Office expenses") -> Office expenses | J79: =IFERROR(__xludf.DUMMYFUNCTION("""COMPUTED_VALUE"""),"Viaje Puebla - Industrias Norm") -> Viaje Puebla - Industrias Norm | K79: =IFERROR(__xludf.DUMMYFUNCTION("""COMPUTED_VALUE"""),".") -> . | S79: 4979 | T79: =VLOOKUP(S79,D:F,3,FALSE) -> #N/A
A80: =IFERROR(__xludf.DUMMYFUNCTION("""COMPUTED_VALUE"""),"TRX1251") -> TRX1251 | B80: =IFERROR(__xludf.DUMMYFUNCTION("""COMPUTED_VALUE"""),"#8") -> #8 | C80: =IFERROR(__xludf.DUMMYFUNCTION("""COMPUTED_VALUE"""),46058.4166666666) -> 46058.417 | D80: =IFERROR(__xludf.DUMMYFUNCTION("""COMPUTED_VALUE"""),489.95) -> 489.95 | E80: =IFERROR(__xludf.DUMMYFUNCTION("""COMPUTED_VALUE"""),"MXN") -> MXN | F80: =IFERROR(__xludf.DUMMYFUNCTION("""COMPUTED_VALUE"""),"Jose Ignacio Martinez Flemate") -> Jose Ignacio Martinez Flemate | G80: =IFERROR(__xludf.DUMMYFUNCTION("""COMPUTED_VALUE"""),"UBER *TRIP HELP.UBER.C CMX MEX") -> UBER *TRIP HELP.UBER.C CMX MEX | H80: =IFERROR(__xludf.DUMMYFUNCTION("""COMPUTED_VALUE"""),"Uber") -> Uber | I80: =IFERROR(__xludf.DUMMYFUNCTION("""COMPUTED_VALUE"""),"Transaction cost") -> Transaction cost | J80: =IFERROR(__xludf.DUMMYFUNCTION("""COMPUTED_VALUE"""),"UBER PARA DEJAR HERRAMIENTA DE INSTALACION PO2023 - SAFE IN THE BOX") -> UBER PARA DEJAR HERRAMIENTA DE INSTALACION PO2023 - SAFE IN THE BOX | K80: =IFERROR(__xludf.DUMMYFUNCTION("""COMPUTED_VALUE"""),".") -> . | S80: 72.86 | T80: =VLOOKUP(S80,D:F,3,FALSE) -> #N/A
A81: =IFERROR(__xludf.DUMMYFUNCTION("""COMPUTED_VALUE"""),"TRX1201") -> TRX1201 | B81: =IFERROR(__xludf.DUMMYFUNCTION("""COMPUTED_VALUE"""),"#8") -> #8 | C81: =IFERROR(__xludf.DUMMYFUNCTION("""COMPUTED_VALUE"""),46058.4173611111) -> 46058.417 | D81: =IFERROR(__xludf.DUMMYFUNCTION("""COMPUTED_VALUE"""),744.75) -> 744.75 | E81: =IFERROR(__xludf.DUMMYFUNCTION("""COMPUTED_VALUE"""),"MXN") -> MXN | F81: =IFERROR(__xludf.DUMMYFUNCTION("""COMPUTED_VALUE"""),"Jose Ignacio Martinez Flemate") -> Jose Ignacio Martinez Flemate | G81: =IFERROR(__xludf.DUMMYFUNCTION("""COMPUTED_VALUE"""),"FAR GUAD 1052 TECAMAC EM MEX") -> FAR GUAD 1052 TECAMAC EM MEX | H81: =IFERROR(__xludf.DUMMYFUNCTION("""COMPUTED_VALUE"""),"Far Guad 1052 Tecamac Em Mex") -> Far Guad 1052 Tecamac Em Mex | I81: =IFERROR(__xludf.DUMMYFUNCTION("""COMPUTED_VALUE"""),"Transaction cost") -> Transaction cost | J81: =IFERROR(__xludf.DUMMYFUNCTION("""COMPUTED_VALUE"""),"PAGO A CUENTA DE UN GASTO DE GASOLINA QUE NO PASO CON LA JEEVES PO2165 - ENSAMBLE UF/CEB MECANICO") -> PAGO A CUENTA DE UN GASTO DE GASOLINA QUE NO PASO CON LA JEEVES PO2165 - ENSAMBLE UF/CEB MECANICO | K81: =IFERROR(__xludf.DUMMYFUNCTION("""COMPUTED_VALUE"""),".") -> . | S81: 78.69 | T81: =VLOOKUP(S81,D:F,3,FALSE) -> #N/A
A82: =IFERROR(__xludf.DUMMYFUNCTION("""COMPUTED_VALUE"""),"TRX1198") -> TRX1198 | B82: =IFERROR(__xludf.DUMMYFUNCTION("""COMPUTED_VALUE"""),"#8") -> #8 | C82: =IFERROR(__xludf.DUMMYFUNCTION("""COMPUTED_VALUE"""),46058.4173611111) -> 46058.417 | D82: =IFERROR(__xludf.DUMMYFUNCTION("""COMPUTED_VALUE"""),91) -> 91 | E82: =IFERROR(__xludf.DUMMYFUNCTION("""COMPUTED_VALUE"""),"MXN") -> MXN | F82: =IFERROR(__xludf.DUMMYFUNCTION("""COMPUTED_VALUE"""),"Jose Ignacio Martinez Flemate") -> Jose Ignacio Martinez Flemate | G82: =IFERROR(__xludf.DUMMYFUNCTION("""COMPUTED_VALUE"""),"OXXOSAN ANTONIO 17 MEX CUAUTITLAN EM MEX") -> OXXOSAN ANTONIO 17 MEX CUAUTITLAN EM MEX | H82: =IFERROR(__xludf.DUMMYFUNCTION("""COMPUTED_VALUE"""),"Oxxosan Antonio 17 Mex Cuautitlan Em Mex") -> Oxxosan Antonio 17 Mex Cuautitlan Em Mex | I82: =IFERROR(__xludf.DUMMYFUNCTION("""COMPUTED_VALUE"""),"Transaction cost") -> Transaction cost | J82: =IFERROR(__xludf.DUMMYFUNCTION("""COMPUTED_VALUE"""),"COMIDA PO2165 - ENSAMBLE UF/CEB MECANICO") -> COMIDA PO2165 - ENSAMBLE UF/CEB MECANICO | K82: =IFERROR(__xludf.DUMMYFUNCTION("""COMPUTED_VALUE"""),".") -> . | S82: 569.96 | T82: =VLOOKUP(S82,D:F,3,FALSE) -> #N/A
A83: =IFERROR(__xludf.DUMMYFUNCTION("""COMPUTED_VALUE"""),"TRX1676") -> TRX1676 | B83: =IFERROR(__xludf.DUMMYFUNCTION("""COMPUTED_VALUE"""),"#8") -> #8 | C83: =IFERROR(__xludf.DUMMYFUNCTION("""COMPUTED_VALUE"""),46060.4173611111) -> 46060.417 | D83: =IFERROR(__xludf.DUMMYFUNCTION("""COMPUTED_VALUE"""),60.5) -> 60.5 | E83: =IFERROR(__xludf.DUMMYFUNCTION("""COMPUTED_VALUE"""),"MXN") -> MXN | F83: =IFERROR(__xludf.DUMMYFUNCTION("""COMPUTED_VALUE"""),"Jose Ignacio Martinez Flemate") -> Jose Ignacio Martinez Flemate | G83: =IFERROR(__xludf.DUMMYFUNCTION("""COMPUTED_VALUE"""),"OXXOSAN ANTONIO 17 MEX CUAUTITLAN EM MEX") -> OXXOSAN ANTONIO 17 MEX CUAUTITLAN EM MEX | H83: =IFERROR(__xludf.DUMMYFUNCTION("""COMPUTED_VALUE"""),"Oxxosan Antonio 17 Mex Cuautitlan Em Mex") -> Oxxosan Antonio 17 Mex Cuautitlan Em Mex | I83: =IFERROR(__xludf.DUMMYFUNCTION("""COMPUTED_VALUE"""),"Transaction cost") -> Transaction cost | J83: =IFERROR(__xludf.DUMMYFUNCTION("""COMPUTED_VALUE"""),"COMIDA PO2165 - ENSAMBLE UF/CEB MECANICO") -> COMIDA PO2165 - ENSAMBLE UF/CEB MECANICO | K83: =IFERROR(__xludf.DUMMYFUNCTION("""COMPUTED_VALUE"""),".") -> . | S83: 1951.14 | T83: =VLOOKUP(S83,D:F,3,FALSE) -> #N/A
A84: =IFERROR(__xludf.DUMMYFUNCTION("""COMPUTED_VALUE"""),"TRX1340") -> TRX1340 | B84: =IFERROR(__xludf.DUMMYFUNCTION("""COMPUTED_VALUE"""),"#8") -> #8 | C84: =IFERROR(__xludf.DUMMYFUNCTION("""COMPUTED_VALUE"""),46061.4166666666) -> 46061.417 | D84: =IFERROR(__xludf.DUMMYFUNCTION("""COMPUTED_VALUE"""),320) -> 320 | E84: =IFERROR(__xludf.DUMMYFUNCTION("""COMPUTED_VALUE"""),"MXN") -> MXN | F84: =IFERROR(__xludf.DUMMYFUNCTION("""COMPUTED_VALUE"""),"Jose Ignacio Martinez Flemate") -> Jose Ignacio Martinez Flemate | G84: =IFERROR(__xludf.DUMMYFUNCTION("""COMPUTED_VALUE"""),"MERCADOPAGO *DOSGARDE Tultitln MEX") -> MERCADOPAGO *DOSGARDE Tultitln MEX | H84: =IFERROR(__xludf.DUMMYFUNCTION("""COMPUTED_VALUE"""),"Mercadopago") -> Mercadopago | I84: =IFERROR(__xludf.DUMMYFUNCTION("""COMPUTED_VALUE"""),"Transaction cost") -> Transaction cost | J84: =IFERROR(__xludf.DUMMYFUNCTION("""COMPUTED_VALUE"""),"CASETAS VISITA VISITA A ESCATO PO2165 - ENSAMBLE UF/CEB MECANICO") -> CASETAS VISITA VISITA A ESCATO PO2165 - ENSAMBLE UF/CEB MECANICO | K84: =IFERROR(__xludf.DUMMYFUNCTION("""COMPUTED_VALUE"""),".") -> . | S84: 415 | T84: =VLOOKUP(S84,D:F,3,FALSE) -> #N/A
A85: =IFERROR(__xludf.DUMMYFUNCTION("""COMPUTED_VALUE"""),"TRX2021") -> TRX2021 | B85: =IFERROR(__xludf.DUMMYFUNCTION("""COMPUTED_VALUE"""),"#8") -> #8 | C85: =IFERROR(__xludf.DUMMYFUNCTION("""COMPUTED_VALUE"""),46063.4166666666) -> 46063.417 | D85: =IFERROR(__xludf.DUMMYFUNCTION("""COMPUTED_VALUE"""),802.27) -> 802.27 | E85: =IFERROR(__xludf.DUMMYFUNCTION("""COMPUTED_VALUE"""),"MXN") -> MXN | F85: =IFERROR(__xludf.DUMMYFUNCTION("""COMPUTED_VALUE"""),"Jose Ignacio Martinez Flemate") -> Jose Ignacio Martinez Flemate | G85: =IFERROR(__xludf.DUMMYFUNCTION("""COMPUTED_VALUE"""),"SERV ALISAS LERMA EM MEX") -> SERV ALISAS LERMA EM MEX | H85: =IFERROR(__xludf.DUMMYFUNCTION("""COMPUTED_VALUE"""),"Serv Alisas Lerma Em Mex") -> Serv Alisas Lerma Em Mex | I85: =IFERROR(__xludf.DUMMYFUNCTION("""COMPUTED_VALUE"""),"Transaction cost") -> Transaction cost | J85: =IFERROR(__xludf.DUMMYFUNCTION("""COMPUTED_VALUE"""),"GASOLINA VISITA A CAMI PO2165 - ENSAMBLE UF/CEB MECANICO") -> GASOLINA VISITA A CAMI PO2165 - ENSAMBLE UF/CEB MECANICO | K85: =IFERROR(__xludf.DUMMYFUNCTION("""COMPUTED_VALUE"""),".") -> . | S85: 50.8 | T85: =VLOOKUP(S85,D:F,3,FALSE) -> #N/A
A86: =IFERROR(__xludf.DUMMYFUNCTION("""COMPUTED_VALUE"""),"TRX1336") -> TRX1336 | B86: =IFERROR(__xludf.DUMMYFUNCTION("""COMPUTED_VALUE"""),"#8") -> #8 | C86: =IFERROR(__xludf.DUMMYFUNCTION("""COMPUTED_VALUE"""),46065.4166666666) -> 46065.417 | D86: =IFERROR(__xludf.DUMMYFUNCTION("""COMPUTED_VALUE"""),947) -> 947 | E86: =IFERROR(__xludf.DUMMYFUNCTION("""COMPUTED_VALUE"""),"MXN") -> MXN | F86: =IFERROR(__xludf.DUMMYFUNCTION("""COMPUTED_VALUE"""),"Jose Ignacio Martinez Flemate") -> Jose Ignacio Martinez Flemate | G86: =IFERROR(__xludf.DUMMYFUNCTION("""COMPUTED_VALUE"""),"OFFICE MAX TECAMAC TECAMAC MEX") -> OFFICE MAX TECAMAC TECAMAC MEX | H86: =IFERROR(__xludf.DUMMYFUNCTION("""COMPUTED_VALUE"""),"Office Depot") -> Office Depot | I86: =IFERROR(__xludf.DUMMYFUNCTION("""COMPUTED_VALUE"""),"Transaction cost") -> Transaction cost | J86: =IFERROR(__xludf.DUMMYFUNCTION("""COMPUTED_VALUE"""),"PAPELERIA PARA DOSSIER DE CALIDAD PO2165 - ENSAMBLE UF/CEB MECANICO") -> PAPELERIA PARA DOSSIER DE CALIDAD PO2165 - ENSAMBLE UF/CEB MECANICO | K86: =IFERROR(__xludf.DUMMYFUNCTION("""COMPUTED_VALUE"""),".") -> . | S86: 234 | T86: =VLOOKUP(S86,D:F,3,FALSE) -> #N/A
A87: =IFERROR(__xludf.DUMMYFUNCTION("""COMPUTED_VALUE"""),"TRX1714") -> TRX1714 | B87: =IFERROR(__xludf.DUMMYFUNCTION("""COMPUTED_VALUE"""),"#8") -> #8 | C87: =IFERROR(__xludf.DUMMYFUNCTION("""COMPUTED_VALUE"""),46065.4173611111) -> 46065.417 | D87: =IFERROR(__xludf.DUMMYFUNCTION("""COMPUTED_VALUE"""),145) -> 145 | E87: =IFERROR(__xludf.DUMMYFUNCTION("""COMPUTED_VALUE"""),"MXN") -> MXN | F87: =IFERROR(__xludf.DUMMYFUNCTION("""COMPUTED_VALUE"""),"Jose Ignacio Martinez Flemate") -> Jose Ignacio Martinez Flemate | G87: =IFERROR(__xludf.DUMMYFUNCTION("""COMPUTED_VALUE"""),"HOME DEPOT TECAMAC TECAMAC EM MEX") -> HOME DEPOT TECAMAC TECAMAC EM MEX | H87: =IFERROR(__xludf.DUMMYFUNCTION("""COMPUTED_VALUE"""),"The Home Depot") -> The Home Depot | I87: =IFERROR(__xludf.DUMMYFUNCTION("""COMPUTED_VALUE"""),"Transaction cost") -> Transaction cost | J87: =IFERROR(__xludf.DUMMYFUNCTION("""COMPUTED_VALUE"""),"PLUMONES PARA MARCAJE DE ESTRUCTURA PO2165 - ENSAMBLE UF/CEB MECANICO") -> PLUMONES PARA MARCAJE DE ESTRUCTURA PO2165 - ENSAMBLE UF/CEB MECANICO | K87: =IFERROR(__xludf.DUMMYFUNCTION("""COMPUTED_VALUE"""),".") -> . | S87: 438 | T87: =VLOOKUP(S87,D:F,3,FALSE) -> Carlos Ivan Gonzalez Merino
A88: =IFERROR(__xludf.DUMMYFUNCTION("""COMPUTED_VALUE"""),"TRX1943") -> TRX1943 | B88: =IFERROR(__xludf.DUMMYFUNCTION("""COMPUTED_VALUE"""),"#8") -> #8 | C88: =IFERROR(__xludf.DUMMYFUNCTION("""COMPUTED_VALUE"""),46065.4173611111) -> 46065.417 | D88: =IFERROR(__xludf.DUMMYFUNCTION("""COMPUTED_VALUE"""),114) -> 114 | E88: =IFERROR(__xludf.DUMMYFUNCTION("""COMPUTED_VALUE"""),"MXN") -> MXN | F88: =IFERROR(__xludf.DUMMYFUNCTION("""COMPUTED_VALUE"""),"Jose Ignacio Martinez Flemate") -> Jose Ignacio Martinez Flemate | G88: =IFERROR(__xludf.DUMMYFUNCTION("""COMPUTED_VALUE"""),"OXXOSAN ANTONIO 17 MEX CUAUTITLAN EM MEX") -> OXXOSAN ANTONIO 17 MEX CUAUTITLAN EM MEX | H88: =IFERROR(__xludf.DUMMYFUNCTION("""COMPUTED_VALUE"""),"Oxxosan Antonio 17 Mex Cuautitlan Em Mex") -> Oxxosan Antonio 17 Mex Cuautitlan Em Mex | I88: =IFERROR(__xludf.DUMMYFUNCTION("""COMPUTED_VALUE"""),"Transaction cost") -> Transaction cost | J88: =IFERROR(__xludf.DUMMYFUNCTION("""COMPUTED_VALUE"""),"COMIDA PO2165 - ENSAMBLE UF/CEB MECANICO") -> COMIDA PO2165 - ENSAMBLE UF/CEB MECANICO | K88: =IFERROR(__xludf.DUMMYFUNCTION("""COMPUTED_VALUE"""),".") -> . | S88: 612.7 | T88: =VLOOKUP(S88,D:F,3,FALSE) -> #N/A
A89: =IFERROR(__xludf.DUMMYFUNCTION("""COMPUTED_VALUE"""),"TRX1930") -> TRX1930 | B89: =IFERROR(__xludf.DUMMYFUNCTION("""COMPUTED_VALUE"""),"#8") -> #8 | C89: =IFERROR(__xludf.DUMMYFUNCTION("""COMPUTED_VALUE"""),46067.4166666666) -> 46067.417 | D89: =IFERROR(__xludf.DUMMYFUNCTION("""COMPUTED_VALUE"""),2010) -> 2010 | E89: =IFERROR(__xludf.DUMMYFUNCTION("""COMPUTED_VALUE"""),"MXN") -> MXN | F89: =IFERROR(__xludf.DUMMYFUNCTION("""COMPUTED_VALUE"""),"Jose Ignacio Martinez Flemate") -> Jose Ignacio Martinez Flemate | G89: =IFERROR(__xludf.DUMMYFUNCTION("""COMPUTED_VALUE"""),"MERCADOPAGO *PASE Ciudad de Mex MEX") -> MERCADOPAGO *PASE Ciudad de Mex MEX | H89: =IFERROR(__xludf.DUMMYFUNCTION("""COMPUTED_VALUE"""),"Mercadopago") -> Mercadopago | I89: =IFERROR(__xludf.DUMMYFUNCTION("""COMPUTED_VALUE"""),"Transaction cost") -> Transaction cost | J89: =IFERROR(__xludf.DUMMYFUNCTION("""COMPUTED_VALUE"""),"CASETAS VISITA VISITA A ESCATO PO2165 - ENSAMBLE UF/CEB MECANICO") -> CASETAS VISITA VISITA A ESCATO PO2165 - ENSAMBLE UF/CEB MECANICO | K89: =IFERROR(__xludf.DUMMYFUNCTION("""COMPUTED_VALUE"""),".") -> . | S89: 960.93 | T89: =VLOOKUP(S89,D:F,3,FALSE) -> #N/A
A90: =IFERROR(__xludf.DUMMYFUNCTION("""COMPUTED_VALUE"""),"TRX1799") -> TRX1799 | B90: =IFERROR(__xludf.DUMMYFUNCTION("""COMPUTED_VALUE"""),"#8") -> #8 | C90: =IFERROR(__xludf.DUMMYFUNCTION("""COMPUTED_VALUE"""),46067.4166666666) -> 46067.417 | D90: =IFERROR(__xludf.DUMMYFUNCTION("""COMPUTED_VALUE"""),709.41) -> 709.41 | E90: =IFERROR(__xludf.DUMMYFUNCTION("""COMPUTED_VALUE"""),"MXN") -> MXN | F90: =IFERROR(__xludf.DUMMYFUNCTION("""COMPUTED_VALUE"""),"Jose Ignacio Martinez Flemate") -> Jose Ignacio Martinez Flemate | G90: =IFERROR(__xludf.DUMMYFUNCTION("""COMPUTED_VALUE"""),"GASOL LUNAGAS TECAMAC3 TECAMAC EM MEX") -> GASOL LUNAGAS TECAMAC3 TECAMAC EM MEX | H90: =IFERROR(__xludf.DUMMYFUNCTION("""COMPUTED_VALUE"""),"Gasol Lunagas Tecamac3 Tecamac Em Mex") -> Gasol Lunagas Tecamac3 Tecamac Em Mex | I90: =IFERROR(__xludf.DUMMYFUNCTION("""COMPUTED_VALUE"""),"Transaction cost") -> Transaction cost | J90: =IFERROR(__xludf.DUMMYFUNCTION("""COMPUTED_VALUE"""),"GASOLINA VISITA A CAMI PO2165 - ENSAMBLE UF/CEB MECANICO") -> GASOLINA VISITA A CAMI PO2165 - ENSAMBLE UF/CEB MECANICO | K90: =IFERROR(__xludf.DUMMYFUNCTION("""COMPUTED_VALUE"""),".") -> . | S90: 1108.63 | T90: =VLOOKUP(S90,D:F,3,FALSE) -> #N/A
A91: =IFERROR(__xludf.DUMMYFUNCTION("""COMPUTED_VALUE"""),"TRX1405") -> TRX1405 | B91: =IFERROR(__xludf.DUMMYFUNCTION("""COMPUTED_VALUE"""),"#8") -> #8 | C91: =IFERROR(__xludf.DUMMYFUNCTION("""COMPUTED_VALUE"""),46068.4166666666) -> 46068.417 | D91: =IFERROR(__xludf.DUMMYFUNCTION("""COMPUTED_VALUE"""),20) -> 20 | E91: =IFERROR(__xludf.DUMMYFUNCTION("""COMPUTED_VALUE"""),"MXN") -> MXN | F91: =IFERROR(__xludf.DUMMYFUNCTION("""COMPUTED_VALUE"""),"Jose Ignacio Martinez Flemate") -> Jose Ignacio Martinez Flemate | G91: =IFERROR(__xludf.DUMMYFUNCTION("""COMPUTED_VALUE"""),"UBER *TRIP HELP.UBER.C CMX MEX") -> UBER *TRIP HELP.UBER.C CMX MEX | H91: =IFERROR(__xludf.DUMMYFUNCTION("""COMPUTED_VALUE"""),"Uber") -> Uber | I91: =IFERROR(__xludf.DUMMYFUNCTION("""COMPUTED_VALUE"""),"Transaction cost") -> Transaction cost | J91: =IFERROR(__xludf.DUMMYFUNCTION("""COMPUTED_VALUE"""),"UBER PARA DEJAR HERRAMIENTA DE INSTALACION PO2023 - SAFE IN THE BOX ") -> UBER PARA DEJAR HERRAMIENTA DE INSTALACION PO2023 - SAFE IN THE BOX | K91: =IFERROR(__xludf.DUMMYFUNCTION("""COMPUTED_VALUE"""),".") -> . | S91: 999.35 | T91: =VLOOKUP(S91,D:F,3,FALSE) -> #N/A
A92: =IFERROR(__xludf.DUMMYFUNCTION("""COMPUTED_VALUE"""),"TRX2025") -> TRX2025 | B92: =IFERROR(__xludf.DUMMYFUNCTION("""COMPUTED_VALUE"""),"#8") -> #8 | C92: =IFERROR(__xludf.DUMMYFUNCTION("""COMPUTED_VALUE"""),46068.4166666666) -> 46068.417 | D92: =IFERROR(__xludf.DUMMYFUNCTION("""COMPUTED_VALUE"""),499.99) -> 499.99 | E92: =IFERROR(__xludf.DUMMYFUNCTION("""COMPUTED_VALUE"""),"MXN") -> MXN | F92: =IFERROR(__xludf.DUMMYFUNCTION("""COMPUTED_VALUE"""),"Jose Ignacio Martinez Flemate") -> Jose Ignacio Martinez Flemate | G92: =IFERROR(__xludf.DUMMYFUNCTION("""COMPUTED_VALUE"""),"UBER * PENDING CMX MEX") -> UBER * PENDING CMX MEX | H92: =IFERROR(__xludf.DUMMYFUNCTION("""COMPUTED_VALUE"""),"Uber") -> Uber | I92: =IFERROR(__xludf.DUMMYFUNCTION("""COMPUTED_VALUE"""),"Transaction cost") -> Transaction cost | J92: =IFERROR(__xludf.DUMMYFUNCTION("""COMPUTED_VALUE"""),"UBER VISITA A PROVEEDOR (NO CIRCULA) PO2165 - ENSAMBLE UF/CEB MECANICO") -> UBER VISITA A PROVEEDOR (NO CIRCULA) PO2165 - ENSAMBLE UF/CEB MECANICO | K92: =IFERROR(__xludf.DUMMYFUNCTION("""COMPUTED_VALUE"""),".") -> . | S92: 150 | T92: =VLOOKUP(S92,D:F,3,FALSE) -> Karen Alexandra Ballesteros Contreras
A93: =IFERROR(__xludf.DUMMYFUNCTION("""COMPUTED_VALUE"""),"TRX1045") -> TRX1045 | B93: =IFERROR(__xludf.DUMMYFUNCTION("""COMPUTED_VALUE"""),"#8") -> #8 | C93: =IFERROR(__xludf.DUMMYFUNCTION("""COMPUTED_VALUE"""),46068.4166666666) -> 46068.417 | D93: =IFERROR(__xludf.DUMMYFUNCTION("""COMPUTED_VALUE"""),309.98) -> 309.98 | E93: =IFERROR(__xludf.DUMMYFUNCTION("""COMPUTED_VALUE"""),"MXN") -> MXN | F93: =IFERROR(__xludf.DUMMYFUNCTION("""COMPUTED_VALUE"""),"Jose Ignacio Martinez Flemate") -> Jose Ignacio Martinez Flemate | G93: =IFERROR(__xludf.DUMMYFUNCTION("""COMPUTED_VALUE"""),"UBER * PENDING CMX MEX") -> UBER * PENDING CMX MEX | H93: =IFERROR(__xludf.DUMMYFUNCTION("""COMPUTED_VALUE"""),"Uber") -> Uber | I93: =IFERROR(__xludf.DUMMYFUNCTION("""COMPUTED_VALUE"""),"Transaction cost") -> Transaction cost | J93: =IFERROR(__xludf.DUMMYFUNCTION("""COMPUTED_VALUE"""),"UBER VISITA A PROVEEDOR (NO CIRCULA) PO2165 - ENSAMBLE UF/CEB MECANICO") -> UBER VISITA A PROVEEDOR (NO CIRCULA) PO2165 - ENSAMBLE UF/CEB MECANICO | K93: =IFERROR(__xludf.DUMMYFUNCTION("""COMPUTED_VALUE"""),".") -> . | S93: 0.01 | T93: =VLOOKUP(S93,D:F,3,FALSE) -> Gerardo Madrid
A94: =IFERROR(__xludf.DUMMYFUNCTION("""COMPUTED_VALUE"""),"TRX1800") -> TRX1800 | B94: =IFERROR(__xludf.DUMMYFUNCTION("""COMPUTED_VALUE"""),"#8") -> #8 | C94: =IFERROR(__xludf.DUMMYFUNCTION("""COMPUTED_VALUE"""),46071.4166666666) -> 46071.417 | D94: =IFERROR(__xludf.DUMMYFUNCTION("""COMPUTED_VALUE"""),102.5) -> 102.5 | E94: =IFERROR(__xludf.DUMMYFUNCTION("""COMPUTED_VALUE"""),"MXN") -> MXN | F94: =IFERROR(__xludf.DUMMYFUNCTION("""COMPUTED_VALUE"""),"Jose Ignacio Martinez Flemate") -> Jose Ignacio Martinez Flemate | G94: =IFERROR(__xludf.DUMMYFUNCTION("""COMPUTED_VALUE"""),"OXXOSAN ANTONIO 17 MEX CUAUTITLAN EM MEX") -> OXXOSAN ANTONIO 17 MEX CUAUTITLAN EM MEX | H94: =IFERROR(__xludf.DUMMYFUNCTION("""COMPUTED_VALUE"""),"Oxxosan Antonio 17 Mex Cuautitlan Em Mex") -> Oxxosan Antonio 17 Mex Cuautitlan Em Mex | I94: =IFERROR(__xludf.DUMMYFUNCTION("""COMPUTED_VALUE"""),"Transaction cost") -> Transaction cost | J94: =IFERROR(__xludf.DUMMYFUNCTION("""COMPUTED_VALUE"""),"COMIDA PO2165 - ENSAMBLE UF/CEB MECANICO") -> COMIDA PO2165 - ENSAMBLE UF/CEB MECANICO | K94: =IFERROR(__xludf.DUMMYFUNCTION("""COMPUTED_VALUE"""),".") -> . | S94: 262.9 | T94: =VLOOKUP(S94,D:F,3,FALSE) -> #N/A
A95: =IFERROR(__xludf.DUMMYFUNCTION("""COMPUTED_VALUE"""),"TRX1508") -> TRX1508 | B95: =IFERROR(__xludf.DUMMYFUNCTION("""COMPUTED_VALUE"""),"#8") -> #8 | C95: =IFERROR(__xludf.DUMMYFUNCTION("""COMPUTED_VALUE"""),46072.4173611111) -> 46072.417 | D95: =IFERROR(__xludf.DUMMYFUNCTION("""COMPUTED_VALUE"""),23.5) -> 23.5 | E95: =IFERROR(__xludf.DUMMYFUNCTION("""COMPUTED_VALUE"""),"MXN") -> MXN | F95: =IFERROR(__xludf.DUMMYFUNCTION("""COMPUTED_VALUE"""),"Jose Ignacio Martinez Flemate") -> Jose Ignacio Martinez Flemate | G95: =IFERROR(__xludf.DUMMYFUNCTION("""COMPUTED_VALUE"""),"OXXOSAN ANTONIO 17 MEX CUAUTITLAN EM MEX") -> OXXOSAN ANTONIO 17 MEX CUAUTITLAN EM MEX | H95: =IFERROR(__xludf.DUMMYFUNCTION("""COMPUTED_VALUE"""),"Oxxosan Antonio 17 Mex Cuautitlan Em Mex") -> Oxxosan Antonio 17 Mex Cuautitlan Em Mex | I95: =IFERROR(__xludf.DUMMYFUNCTION("""COMPUTED_VALUE"""),"Transaction cost") -> Transaction cost | J95: =IFERROR(__xludf.DUMMYFUNCTION("""COMPUTED_VALUE"""),"COMIDA PO2165 - ENSAMBLE UF/CEB MECANICO") -> COMIDA PO2165 - ENSAMBLE UF/CEB MECANICO | K95: =IFERROR(__xludf.DUMMYFUNCTION("""COMPUTED_VALUE"""),".") -> . | S95: 964.63 | T95: =VLOOKUP(S95,D:F,3,FALSE) -> #N/A
A96: =IFERROR(__xludf.DUMMYFUNCTION("""COMPUTED_VALUE"""),"TRX1931") -> TRX1931 | B96: =IFERROR(__xludf.DUMMYFUNCTION("""COMPUTED_VALUE"""),"#8") -> #8 | C96: =IFERROR(__xludf.DUMMYFUNCTION("""COMPUTED_VALUE"""),46073.4166666666) -> 46073.417 | D96: =IFERROR(__xludf.DUMMYFUNCTION("""COMPUTED_VALUE"""),129) -> 129 | E96: =IFERROR(__xludf.DUMMYFUNCTION("""COMPUTED_VALUE"""),"MXN") -> MXN | F96: =IFERROR(__xludf.DUMMYFUNCTION("""COMPUTED_VALUE"""),"Jose Ignacio Martinez Flemate") -> Jose Ignacio Martinez Flemate | G96: =IFERROR(__xludf.DUMMYFUNCTION("""COMPUTED_VALUE"""),"CLIP MX*TDA LAMINAS Y CUAUTITLAN MEX") -> CLIP MX*TDA LAMINAS Y CUAUTITLAN MEX | H96: =IFERROR(__xludf.DUMMYFUNCTION("""COMPUTED_VALUE"""),"Clip Mx Tda Laminas Y Cuautitlan Mex") -> Clip Mx Tda Laminas Y Cuautitlan Mex | I96: =IFERROR(__xludf.DUMMYFUNCTION("""COMPUTED_VALUE"""),"Transaction cost") -> Transaction cost | J96: =IFERROR(__xludf.DUMMYFUNCTION("""COMPUTED_VALUE"""),"INSUMOS PARA PRUEBA DE ADHEDRENCIA PO2165 - ENSAMBLE UF/CEB MECANICO") -> INSUMOS PARA PRUEBA DE ADHEDRENCIA PO2165 - ENSAMBLE UF/CEB MECANICO | K96: =IFERROR(__xludf.DUMMYFUNCTION("""COMPUTED_VALUE"""),".") -> . | S96: 240.7 | T96: =VLOOKUP(S96,D:F,3,FALSE) -> #N/A
A97: =IFERROR(__xludf.DUMMYFUNCTION("""COMPUTED_VALUE"""),"TRX1513") -> TRX1513 | B97: =IFERROR(__xludf.DUMMYFUNCTION("""COMPUTED_VALUE"""),"#8") -> #8 | C97: =IFERROR(__xludf.DUMMYFUNCTION("""COMPUTED_VALUE"""),46073.4166666666) -> 46073.417 | D97: =IFERROR(__xludf.DUMMYFUNCTION("""COMPUTED_VALUE"""),1376) -> 1376 | E97: =IFERROR(__xludf.DUMMYFUNCTION("""COMPUTED_VALUE"""),"MXN") -> MXN | F97: =IFERROR(__xludf.DUMMYFUNCTION("""COMPUTED_VALUE"""),"Jose Ignacio Martinez Flemate") -> Jose Ignacio Martinez Flemate | G97: =IFERROR(__xludf.DUMMYFUNCTION("""COMPUTED_VALUE"""),"HOME DEPOT CUAUTITLAN IZ MEX") -> HOME DEPOT CUAUTITLAN IZ MEX | H97: =IFERROR(__xludf.DUMMYFUNCTION("""COMPUTED_VALUE"""),"The Home Depot") -> The Home Depot | I97: =IFERROR(__xludf.DUMMYFUNCTION("""COMPUTED_VALUE"""),"Transaction cost") -> Transaction cost | J97: =IFERROR(__xludf.DUMMYFUNCTION("""COMPUTED_VALUE"""),"EPP E INSUMOS PARA PRUEBA DE ESPESORES DE PINTURA PO2165 - ENSAMBLE UF/CEB MECANICO") -> EPP E INSUMOS PARA PRUEBA DE ESPESORES DE PINTURA PO2165 - ENSAMBLE UF/CEB MECANICO | K97: =IFERROR(__xludf.DUMMYFUNCTION("""COMPUTED_VALUE"""),".") -> . | S97: 724 | T97: =VLOOKUP(S97,D:F,3,FALSE) -> #N/A
A98: =IFERROR(__xludf.DUMMYFUNCTION("""COMPUTED_VALUE"""),"TRX1826") -> TRX1826 | B98: =IFERROR(__xludf.DUMMYFUNCTION("""COMPUTED_VALUE"""),"#8") -> #8 | C98: =IFERROR(__xludf.DUMMYFUNCTION("""COMPUTED_VALUE"""),46073.4173611111) -> 46073.417 | D98: =IFERROR(__xludf.DUMMYFUNCTION("""COMPUTED_VALUE"""),48.5) -> 48.5 | E98: =IFERROR(__xludf.DUMMYFUNCTION("""COMPUTED_VALUE"""),"MXN") -> MXN | F98: =IFERROR(__xludf.DUMMYFUNCTION("""COMPUTED_VALUE"""),"Jose Ignacio Martinez Flemate") -> Jose Ignacio Martinez Flemate | G98: =IFERROR(__xludf.DUMMYFUNCTION("""COMPUTED_VALUE"""),"OXXOSAN ANTONIO 17 MEX CUAUTITLAN EM MEX") -> OXXOSAN ANTONIO 17 MEX CUAUTITLAN EM MEX | H98: =IFERROR(__xludf.DUMMYFUNCTION("""COMPUTED_VALUE"""),"Oxxosan Antonio 17 Mex Cuautitlan Em Mex") -> Oxxosan Antonio 17 Mex Cuautitlan Em Mex | I98: =IFERROR(__xludf.DUMMYFUNCTION("""COMPUTED_VALUE"""),"Transaction cost") -> Transaction cost | J98: =IFERROR(__xludf.DUMMYFUNCTION("""COMPUTED_VALUE"""),"COMIDA PO2165 - ENSAMBLE UF/CEB MECANICO") -> COMIDA PO2165 - ENSAMBLE UF/CEB MECANICO | K98: =IFERROR(__xludf.DUMMYFUNCTION("""COMPUTED_VALUE"""),".") -> . | S98: 228 | T98: =VLOOKUP(S98,D:F,3,FALSE) -> Karen Alexandra Ballesteros Contreras
A99: =IFERROR(__xludf.DUMMYFUNCTION("""COMPUTED_VALUE"""),"TRX2030") -> TRX2030 | B99: =IFERROR(__xludf.DUMMYFUNCTION("""COMPUTED_VALUE"""),"#8") -> #8 | C99: =IFERROR(__xludf.DUMMYFUNCTION("""COMPUTED_VALUE"""),46073.4173611111) -> 46073.417 | D99: =IFERROR(__xludf.DUMMYFUNCTION("""COMPUTED_VALUE"""),1946) -> 1946 | E99: =IFERROR(__xludf.DUMMYFUNCTION("""COMPUTED_VALUE"""),"MXN") -> MXN | F99: =IFERROR(__xludf.DUMMYFUNCTION("""COMPUTED_VALUE"""),"Jose Ignacio Martinez Flemate") -> Jose Ignacio Martinez Flemate | G99: =IFERROR(__xludf.DUMMYFUNCTION("""COMPUTED_VALUE"""),"REST 2 LA JEFA CUAUTITLAN EM MEX") -> REST 2 LA JEFA CUAUTITLAN EM MEX | H99: =IFERROR(__xludf.DUMMYFUNCTION("""COMPUTED_VALUE"""),"Rest 2 La Jefa Cuautitlan Em Mex") -> Rest 2 La Jefa Cuautitlan Em Mex | I99: =IFERROR(__xludf.DUMMYFUNCTION("""COMPUTED_VALUE"""),"Transaction cost") -> Transaction cost | J99: =IFERROR(__xludf.DUMMYFUNCTION("""COMPUTED_VALUE"""),"COMIDA - CENA VISITA A CAMI / VISITA DE CALIDAD VEOLIA PO2165 - ENSAMBLE UF/CEB MECANICO") -> COMIDA - CENA VISITA A CAMI / VISITA DE CALIDAD VEOLIA PO2165 - ENSAMBLE UF/CEB MECANICO | K99: =IFERROR(__xludf.DUMMYFUNCTION("""COMPUTED_VALUE"""),".") -> . | S99: 163.94 | T99: =VLOOKUP(S99,D:F,3,FALSE) -> #N/A
A100: =IFERROR(__xludf.DUMMYFUNCTION("""COMPUTED_VALUE"""),"TRX1117") -> TRX1117 | B100: =IFERROR(__xludf.DUMMYFUNCTION("""COMPUTED_VALUE"""),"#8") -> #8 | C100: =IFERROR(__xludf.DUMMYFUNCTION("""COMPUTED_VALUE"""),46074.4166666666) -> 46074.417 | D100: =IFERROR(__xludf.DUMMYFUNCTION("""COMPUTED_VALUE"""),781.02) -> 781.02 | E100: =IFERROR(__xludf.DUMMYFUNCTION("""COMPUTED_VALUE"""),"MXN") -> MXN | F100: =IFERROR(__xludf.DUMMYFUNCTION("""COMPUTED_VALUE"""),"Jose Ignacio Martinez Flemate") -> Jose Ignacio Martinez Flemate | G100: =IFERROR(__xludf.DUMMYFUNCTION("""COMPUTED_VALUE"""),"EST DE SERV EUL GUZ TECAMAC EM MEX") -> EST DE SERV EUL GUZ TECAMAC EM MEX | H100: =IFERROR(__xludf.DUMMYFUNCTION("""COMPUTED_VALUE"""),"Est De Serv Eul Guz Tecamac Em Mex") -> Est De Serv Eul Guz Tecamac Em Mex | I100: =IFERROR(__xludf.DUMMYFUNCTION("""COMPUTED_VALUE"""),"Transaction cost") -> Transaction cost | J100: =IFERROR(__xludf.DUMMYFUNCTION("""COMPUTED_VALUE"""),"GASOLINA VISITA A CAMI PO2165 - ENSAMBLE UF/CEB MECANICO") -> GASOLINA VISITA A CAMI PO2165 - ENSAMBLE UF/CEB MECANICO | K100: =IFERROR(__xludf.DUMMYFUNCTION("""COMPUTED_VALUE"""),".") -> . | S100: 172 | T100: =VLOOKUP(S100,D:F,3,FALSE) -> #N/A
...

Sheet Edo Cta Jeeves Sept
C1: JEEVES JAN 2024 | K1: # ID | L1: User | N1: # ID | O1: User | Y1: # ID | Z1: User | AB1: # ID | AC1: User | AD1: # ID | AE1: User
C2: Transaction cost | E2: =SUMIF($Y$12:$Y$1003,"Transaction cost",$G$12:$G$1003) -> 46697.96 | K2: #1 | L2: Annelies Gamble | N2: #13 | O2: Miguel De Lascurain | Y2: #26 | Z2: Karen Alexandra Ballesteros Contreras | AB2: #41 | AC2: Jose Arechavala | AD2: #53 | AE2: Monserrat Benitez | AF2: #63 | AG2: Diego Morodo | AH2: #72 | AI2: Julio Güemes
C3: Tech&Product | E3: =SUMIF($Y$12:$Y$1003,"Tech&Product",$G$12:$G$1003) -> 67472.96 | K3: #2 | L3: Cesar Gonzales | N3: #14 | O3: Patricio Servitje Azcarraga | Y3: #28 | Z3: Fernando Villalobos Lara | AB3: #42 | AC3: Rodrigo Perea | AD3: #54 | AE3: Mario Castorela | AF3: #64 | AG3: Erik Castillo | AH3: #73 | AI3: Manuel Caldera
C4: Sales | E4: =SUMIF($Y$12:$Y$1003,"Sales",$G$12:$G$1003) -> 196573.56 | K4: #3 | L4: Cesar Uriel Romo Trillo | N4: #16 | O4: Rogelio Gamez | Y4: #29 | Z4: Jonatan Cid Prati | AB4: #43 | AC4: Pablo Ortiz | AD4: #55 | AE4: Gerardo Madrid | AF4: #65 | AG4: Diana Miranda | AH4: #74 | AI4: Alan G
C5: Recruiting | E5: =SUMIF($Y$12:$Y$1003,"Recruiting",$G$12:$G$1003) -> 2232.52 | K5: #4 | L5: Daniel Autrique Echeveste | N5: #17 | O5: Sebastian Taracena Ebrard | Y5: #30 | Z5: Manuel Ibarra Cebreros | AB5: #44 | AC5: JP Hammerstein | AD5: #56 | AE5: Carlos Ivan Gonzalez Merino | AF5: #66 | AG5: Jorge Ramirez | AH5: #75 | AI5: Naomi Gonzalez
C6: Office expenses | E6: =SUMIF($Y$12:$Y$1003,"Office expenses",$G$12:$G$1003) -> 1339282.4 | K6: #5 | L6: Fernanda Sanchez Ruiz | N6: #19 | O6: Daniel Alejandro Castillo Rivera | Y6: #31 | Z6: Emiliano Cavazos | AB6: #45 | AC6: Erick Cival | AD6: #57 | AE6: Paloma Santos | AF6: #67 | AG6: Gustavo Rivas | AH6: #76 | AI6: Tonancy Isidoro
C7: G&A expenses | E7: =SUMIF($Y$12:$Y$1003,"G&A expenses",$G$12:$G$1003) -> 13900.53 | K7: #6 | L7: Fernando Sanchez Toledano | N7: #20 | O7: Gerardo Guadalupe Ruiz Huerta | Y7: #34 | Z7: Juan Pablo Ramos Aranda | AB7: #48 | AC7: Andres Preza | AD7: #58 | AE7: Jose Rosas Ortiz | AF7: #68 | AG7: Alfonso Bello
C8: Capex | E8: =SUMIF($Y$12:$Y$1003,"Capex",$G$12:$G$1003) -> 0 | K8: #7 | L8: Isaac Mendoza Ruiz | N8: #21 | O8: Jesus Gonzalez Grana | Y8: #35 | Z8: Termis | AB8: #49 | AC8: Jahaziel Galan | AD8: #60 | AE8: Carlos Aleman | AF8: #69 | AG8: Cole Anderson
C9: Marketing | E9: =SUMIF($Y$12:$Y$1003,"Marketing",$G$12:$G$1003) -> 0 | K9: #8 | L9: Jose Ignacio Martinez Flemate | N9: #24 | O9: Andres Camacho Herrera | Y9: #37 | Z9: Angel Pantoja | AB9: #51 | AC9: Saul Murillo | AD9: #61 | AE9: Jorge Diaz | AF9: #70 | AG9: Mariano Alcaraz
K10: #9 | L10: Jose Maria Garcia Hernandez | N10: #25 | O10: Jorge Eduardo Estrada Becerril | Y10: #40 | Z10: Gabriela Zacarias Aguirre | AB10: #52 | AC10: Tommaso Rivetti | AD10: #62 | AE10: Jorge Rojas | AF10: #71 | AG10: Alan R
A12: txr | B12: #id user | C12: Swipe Date | G12: Amount | H12: Amount | I12: MONEDA | J12: User | K12: Statement Descriptor | L12: Merchant Name | M12: 552568XXXXXX9581 | N12: virtual | O12: Memo | P12: Receipt Attached | Q12: Receipts | R12: CLABE | S12: Beneficiary Account | T12: Reference Number | U12: Bank Name | V12: Invoice Issuer | W12: Invoice Issuer ID | X12: Invoice ID | Y12: Expense Type | Z12: DESCRIPCION DEL CARGO | AC12: FOLIO DE FACTURA
A13: TRX1298 | B13: =IFERROR(VLOOKUP(J13,catalogo!$B$1:$C$75,2,0),"-") -> #26 | C13: 46055.417 | G13: 796.6 | H13: 796.6 | I13: MXN | J13: Karen Alexandra Ballesteros Contreras | K13: MERPAGO*MERCADOLIBRE Ciudad de Mex MEX | L13: Merpago Mercadolibre Ciudad De Mex Mex | M13: 552568XXXXXX3592 | N13: virtual | Y13: =IFERROR(VLOOKUP(A13,catalogo!$E:$H,2,0),"-") -> - | Z13: =IFERROR(VLOOKUP(A13,catalogo!$E:$G,3,0),"-") -> - | AC13: =IFERROR(VLOOKUP(A13,catalogo!$E:$H,4,0),"-") -> -
A14: TRX1297 | B14: =IFERROR(VLOOKUP(J14,catalogo!$B$1:$C$75,2,0),"-") -> #58 | C14: 46055.417 | G14: 3230.41 | H14: 3230.41 | I14: MXN | J14: Jose Rosas Ortiz | K14: EXPEDIA MEXICO CIUDAD DE MEX MEX | L14: Expedia | M14: 552568XXXXXX1484 | N14: virtual | Y14: =IFERROR(VLOOKUP(A14,catalogo!$E:$H,2,0),"-") -> - | Z14: =IFERROR(VLOOKUP(A14,catalogo!$E:$G,3,0),"-") -> - | AC14: =IFERROR(VLOOKUP(A14,catalogo!$E:$H,4,0),"-") -> -
A15: TRX1296 | B15: =IFERROR(VLOOKUP(J15,catalogo!$B$1:$C$75,2,0),"-") -> #64 | C15: 46055.417 | G15: 12000 | H15: 12000 | I15: MXN | J15: Jorge Rojas | K15: EUROPCAR WEB 2 BENITO JUAREZ MEX | L15: Europcar | M15: 7142 | N15: physical | Y15: =IFERROR(VLOOKUP(A15,catalogo!$E:$G,2,0),"-") -> - | Z15: =IFERROR(VLOOKUP(A15,catalogo!$E:$G,3,0),"-") -> - | AC15: =IFERROR(VLOOKUP(A15,catalogo!$E:$H,4,0),"-") -> -
A16: TRX1295 | B16: =IFERROR(VLOOKUP(J16,catalogo!$B$1:$C$75,2,0),"-") -> #64 | C16: 46055.417 | G16: 128.7 | H16: 128.7 | I16: MXN | J16: Jorge Rojas | K16: WALMART LOMAS STA FE TIJUANA BCN MEX | L16: Walmart | M16: 7142 | N16: physical | Y16: =IFERROR(VLOOKUP(A16,catalogo!$E:$G,2,0),"-") -> - | Z16: =IFERROR(VLOOKUP(A16,catalogo!$E:$G,3,0),"-") -> - | AC16: =IFERROR(VLOOKUP(A16,catalogo!$E:$H,4,0),"-") -> -
A17: TRX1294 | B17: =IFERROR(VLOOKUP(J17,catalogo!$B$1:$C$75,2,0),"-") -> #16 | C17: 46055.417 | G17: 363.15 | H17: 20 | I17: USD | J17: Rogelio Gamez | K17: OPENAI *CHATGPT SUBSCR SAN FRANCISCO USA | L17: Openai | M17: 552568XXXXXX9581 | N17: virtual | Y17: =IFERROR(VLOOKUP(A17,catalogo!$E:$H,2,0),"-") -> Tech&Product | Z17: =IFERROR(VLOOKUP(A17,catalogo!$E:$G,3,0),"-") -> 0 | AC17: =IFERROR(VLOOKUP(A17,catalogo!$E:$H,4,0),"-") -> 0
A18: TRX1293 | B18: =IFERROR(VLOOKUP(J18,catalogo!$B$1:$C$75,2,0),"-") -> #64 | C18: 46055.417 | G18: 1537 | H18: 1537 | I18: MXN | J18: Jorge Rojas | K18: SUPERCENTER TIJUANA HI TIJUANA BCN MEX | L18: Supercenter Tijuana Hi Tijuana Bcn Mex | M18: 7142 | N18: physical | Y18: =IFERROR(VLOOKUP(A18,catalogo!$E:$H,2,0),"-") -> - | Z18: =IFERROR(VLOOKUP(A18,catalogo!$E:$G,3,0),"-") -> - | AC18: =IFERROR(VLOOKUP(A18,catalogo!$E:$H,4,0),"-") -> -
A19: TRX1292 | B19: =IFERROR(VLOOKUP(J19,catalogo!$B$1:$C$75,2,0),"-") -> #26 | C19: 46056.417 | G19: 537.21 | H19: 537.21 | I19: MXN | J19: Karen Alexandra Ballesteros Contreras | K19: MERPAGO*MERCADOLIBRE Ciudad de Mex MEX | L19: Merpago Mercadolibre Ciudad De Mex Mex | M19: 552568XXXXXX3592 | N19: virtual | Y19: =IFERROR(VLOOKUP(A19,catalogo!$E:$G,2,0),"-") -> - | Z19: =IFERROR(VLOOKUP(A19,catalogo!$E:$G,3,0),"-") -> - | AC19: =IFERROR(VLOOKUP(A19,catalogo!$E:$H,4,0),"-") -> -
A20: TRX1291 | B20: =IFERROR(VLOOKUP(J20,catalogo!$B$1:$C$75,2,0),"-") -> #7 | C20: 46056.417 | G20: 341.6 | H20: 341.6 | I20: MXN | J20: Isaac Mendoza Ruiz | K20: UBER * EATS PENDING CMX MEX | L20: Uber Eats | M20: 552568XXXXXX7686 | N20: virtual | Y20: =IFERROR(VLOOKUP(A20,catalogo!$E:$H,2,0),"-") -> Office expenses | Z20: =IFERROR(VLOOKUP(A20,catalogo!$E:$G,3,0),"-") -> MTY ATP + Maken | AC20: =IFERROR(VLOOKUP(A20,catalogo!$E:$H,4,0),"-") -> .
A21: TRX1290 | B21: =IFERROR(VLOOKUP(J21,catalogo!$B$1:$C$75,2,0),"-") -> #64 | C21: 46056.417 | G21: 175 | H21: 175 | I21: MXN | J21: Jorge Rojas | K21: CLIP MX*SUPER BARRA LI TIJUANA MEX | L21: Super Mex | M21: 7142 | N21: physical | Y21: =IFERROR(VLOOKUP(A21,catalogo!$E:$G,2,0),"-") -> Sales | Z21: =IFERROR(VLOOKUP(A21,catalogo!$E:$G,3,0),"-") -> Comida Cliente. Asistentes: - Mariela Martínez (Gaya) - Kenia Durán (Gaya) - Miguel de Lascurain (Prima) - Alfonso Bello (Prima) | AC21: =IFERROR(VLOOKUP(A21,catalogo!$E:$H,4,0),"-") -> 8787B2CF-A15D-4633-8ACA-5D36673EEA82103181561770853649271
A22: TRX1289 | B22: =IFERROR(VLOOKUP(J22,catalogo!$B$1:$C$75,2,0),"-") -> - | C22: 46056.417 | G22: 1317.13 | H22: 1317.13 | I22: MXN | J22: Daniel Caraveo | K22: WM EXPRESS BONAMPAK CANCUN QROO MEX | L22: Wm Express Bonampak Cancun Qroo Mex | M22: XXXXXXXXXXXX7525 | N22: physical | Y22: =IFERROR(VLOOKUP(A22,catalogo!$E:$H,2,0),"-") -> - | Z22: =IFERROR(VLOOKUP(A22,catalogo!$E:$G,3,0),"-") -> - | AC22: =IFERROR(VLOOKUP(A22,catalogo!$E:$H,4,0),"-") -> -
A23: TRX1288 | B23: =IFERROR(VLOOKUP(J23,catalogo!$B$1:$C$75,2,0),"-") -> #4 | C23: 46056.417 | G23: 915.4 | H23: 915.4 | I23: MXN | J23: Daniel Autrique Echeveste | K23: LPQ AICM T1 SALA 8 1 CIUDAD DE MEX MEX | L23: L | M23: 975 | N23: physical | Y23: =IFERROR(VLOOKUP(A23,catalogo!$E:$H,2,0),"-") -> Recruiting | Z23: =IFERROR(VLOOKUP(A23,catalogo!$E:$G,3,0),"-") -> LinkedIn | AC23: =IFERROR(VLOOKUP(A23,catalogo!$E:$H,4,0),"-") -> .
A24: TRX1287 | B24: =IFERROR(VLOOKUP(J24,catalogo!$B$1:$C$75,2,0),"-") -> #64 | C24: 46056.417 | G24: 538.63 | H24: 538.63 | I24: MXN | J24: Jorge Rojas | K24: DLO*Uber eats CDMX MEX | L24: Uber Eats | M24: 7142 | N24: physical | Y24: =IFERROR(VLOOKUP(A24,catalogo!$E:$G,2,0),"-") -> - | Z24: =IFERROR(VLOOKUP(A24,catalogo!$E:$G,3,0),"-") -> - | AC24: =IFERROR(VLOOKUP(A24,catalogo!$E:$H,4,0),"-") -> -
A25: TRX1286 | B25: =IFERROR(VLOOKUP(J25,catalogo!$B$1:$C$75,2,0),"-") -> #2 | C25: 46056.417 | G25: 3642.61 | H25: 200.61 | I25: USD | J25: Cesar Gonzales | K25: HASHICORP HCP SAN FRANCISCO USA | L25: Hashicorp | M25: 552568XXXXXX7852 | N25: virtual | Y25: =IFERROR(VLOOKUP(A25,catalogo!$E:$H,2,0),"-") -> Tech&Product | Z25: =IFERROR(VLOOKUP(A25,catalogo!$E:$G,3,0),"-") -> 0 | AC25: =IFERROR(VLOOKUP(A25,catalogo!$E:$H,4,0),"-") -> .
A26: TRX1285 | B26: =IFERROR(VLOOKUP(J26,catalogo!$B$1:$C$75,2,0),"-") -> #66 | C26: 46056.417 | G26: 262 | H26: 262 | I26: MXN | J26: Erik Castillo | K26: HAMBURGUESAS DIANA TIZAYUCA HGO MEX | L26: Hamburguesas Diana Tizayuca Hgo Mex | M26: 2406 | N26: physical | Y26: =IFERROR(VLOOKUP(A26,catalogo!$E:$H,2,0),"-") -> Transaction cost | Z26: =IFERROR(VLOOKUP(A26,catalogo!$E:$G,3,0),"-") -> PO1953 ARTEVALLEDEBRAVO | AC26: =IFERROR(VLOOKUP(A26,catalogo!$E:$H,4,0),"-") -> -
A27: TRX1284 | B27: =IFERROR(VLOOKUP(J27,catalogo!$B$1:$C$75,2,0),"-") -> #64 | C27: 46056.417 | G27: 3626.74 | H27: 3626.74 | I27: MXN | J27: Jorge Rojas | K27: AIRBNB * HM4BMJSNK4 LONDON GBR | L27: Airbnb | M27: 7142 | N27: physical | Y27: =IFERROR(VLOOKUP(A27,catalogo!$E:$G,2,0),"-") -> - | Z27: =IFERROR(VLOOKUP(A27,catalogo!$E:$G,3,0),"-") -> - | AC27: =IFERROR(VLOOKUP(A27,catalogo!$E:$H,4,0),"-") -> -
A28: TRX1283 | B28: =IFERROR(VLOOKUP(J28,catalogo!$B$1:$C$75,2,0),"-") -> #35 | C28: 46056.417 | G28: 137.81 | H28: 7.59 | I28: USD | J28: Termis | K28: FACEBK *Y8ZJ8FVSH2 DUBLIN 2 IRL | L28: Meta | M28: 1771 | N28: physical | Y28: =IFERROR(VLOOKUP(A28,catalogo!$E:$H,2,0),"-") -> - | Z28: =IFERROR(VLOOKUP(A28,catalogo!$E:$G,3,0),"-") -> - | AC28: =IFERROR(VLOOKUP(A28,catalogo!$E:$H,4,0),"-") -> -
A29: TRX1282 | B29: =IFERROR(VLOOKUP(J29,catalogo!$B$1:$C$75,2,0),"-") -> #35 | C29: 46056.417 | G29: 790 | H29: 790 | I29: MXN | J29: Termis | K29: CBA*AUTODESK COLOGNE DEU | L29: Autodesk | M29: 1771 | N29: physical | Y29: =IFERROR(VLOOKUP(A29,catalogo!$E:$H,2,0),"-") -> - | Z29: =IFERROR(VLOOKUP(A29,catalogo!$E:$G,3,0),"-") -> - | AC29: =IFERROR(VLOOKUP(A29,catalogo!$E:$H,4,0),"-") -> -
A30: TRX1281 | B30: =IFERROR(VLOOKUP(J30,catalogo!$B$1:$C$75,2,0),"-") -> #58 | C30: 46056.417 | G30: 537.41 | H30: 537.41 | I30: MXN | J30: Jose Rosas Ortiz | K30: WELCOME TO LV LAS VEGAS USA | L30: Welcome To Lv Las Vegas USA | M30: 5576 | N30: physical | Y30: =IFERROR(VLOOKUP(A30,catalogo!$E:$G,2,0),"-") -> - | Z30: =IFERROR(VLOOKUP(A30,catalogo!$E:$G,3,0),"-") -> - | AC30: =IFERROR(VLOOKUP(A30,catalogo!$E:$H,4,0),"-") -> -
A31: TRX1280 | B31: =IFERROR(VLOOKUP(J31,catalogo!$B$1:$C$75,2,0),"-") -> #58 | C31: 46056.417 | G31: 453.95 | H31: 25 | I31: USD | J31: Jose Rosas Ortiz | K31: NAYAX PARKING Reno USA | L31: Nayax Parking Reno USA | M31: 5576 | N31: physical | Y31: =IFERROR(VLOOKUP(A31,catalogo!$E:$H,2,0),"-") -> - | Z31: =IFERROR(VLOOKUP(A31,catalogo!$E:$G,3,0),"-") -> - | AC31: =IFERROR(VLOOKUP(A31,catalogo!$E:$H,4,0),"-") -> -
A32: TRX1279 | B32: =IFERROR(VLOOKUP(J32,catalogo!$B$1:$C$75,2,0),"-") -> #4 | C32: 46056.417 | G32: 704.7 | H32: 38.81 | I32: USD | J32: Daniel Autrique Echeveste | K32: CURB MOBILITY ASTORIA USA | L32: Curb Mobility | M32: 975 | N32: physical | Y32: =IFERROR(VLOOKUP(A32,catalogo!$E:$G,2,0),"-") -> Sales | Z32: =IFERROR(VLOOKUP(A32,catalogo!$E:$G,3,0),"-") -> Vuelo a chicago Radioflyer | AC32: =IFERROR(VLOOKUP(A32,catalogo!$E:$H,4,0),"-") -> .
A33: TRX1278 | B33: =IFERROR(VLOOKUP(J33,catalogo!$B$1:$C$75,2,0),"-") -> #58 | C33: 46056.417 | G33: 1852.27 | H33: 102.01 | I33: USD | J33: Jose Rosas Ortiz | K33: VOLARIS VOLARIS.COM GBR | L33: Volaris | M33: 552568XXXXXX1484 | N33: virtual | Y33: =IFERROR(VLOOKUP(A33,catalogo!$E:$G,2,0),"-") -> - | Z33: =IFERROR(VLOOKUP(A33,catalogo!$E:$G,3,0),"-") -> - | AC33: =IFERROR(VLOOKUP(A33,catalogo!$E:$H,4,0),"-") -> -
A34: TRX1277 | B34: =IFERROR(VLOOKUP(J34,catalogo!$B$1:$C$75,2,0),"-") -> - | C34: 46057.035 | G34: 1282559.6 | H34: 1282559.6 | I34: MXN | J34: Jeeves System | K34: 1282559.56 MXN Paid | Y34: =IFERROR(VLOOKUP(A34,catalogo!$E:$H,2,0),"-") -> Office expenses | Z34: =IFERROR(VLOOKUP(A34,catalogo!$E:$G,3,0),"-") -> 0 | AC34: =IFERROR(VLOOKUP(A34,catalogo!$E:$H,4,0),"-") -> 0
A35: TRX1276 | B35: =IFERROR(VLOOKUP(J35,catalogo!$B$1:$C$75,2,0),"-") -> #64 | C35: 46057.417 | G35: 529.97 | H35: 529.97 | I35: MXN | J35: Jorge Rojas | K35: UBER * EATS PENDING CMX MEX | L35: Uber Eats | M35: 7142 | N35: physical
A36: TRX1275 | B36: =IFERROR(VLOOKUP(J36,catalogo!$B$1:$C$75,2,0),"-") -> #66 | C36: 46057.417 | G36: 1214.65 | H36: 1214.65 | I36: MXN | J36: Erik Castillo | K36: ENERGETICOS ZAPATA 4 TIZAYUCA HGO MEX | L36: Energeticos Zapata 4 Tizayuca Hgo Mex | M36: 2406 | N36: physical | Y36: =IFERROR(VLOOKUP(A36,catalogo!$E:$G,2,0),"-") -> - | Z36: =IFERROR(VLOOKUP(A36,catalogo!$E:$G,3,0),"-") -> - | AC36: =IFERROR(VLOOKUP(A36,catalogo!$E:$H,4,0),"-") -> -
A37: TRX1274 | B37: =IFERROR(VLOOKUP(J37,catalogo!$B$1:$C$75,2,0),"-") -> #56 | C37: 46057.417 | G37: 429.98 | H37: 429.98 | I37: MXN | J37: Carlos Ivan Gonzalez Merino | K37: UBER * PENDING CMX MEX | L37: Uber | M37: 8949 | N37: physical | Y37: =IFERROR(VLOOKUP(A37,catalogo!$E:$G,2,0),"-") -> - | Z37: =IFERROR(VLOOKUP(A37,catalogo!$E:$G,3,0),"-") -> - | AC37: =IFERROR(VLOOKUP(A37,catalogo!$E:$H,4,0),"-") -> -
A38: TRX1273 | B38: =IFERROR(VLOOKUP(J38,catalogo!$B$1:$C$75,2,0),"-") -> #58 | C38: 46057.417 | G38: 90.79 | H38: 5 | I38: USD | J38: Jose Rosas Ortiz | K38: 4930 LVNPO LAS VEGAS USA | L38: 4930 Lvnpo Las Vegas USA | M38: 5576 | N38: physical | Y38: =IFERROR(VLOOKUP(A38,catalogo!$E:$H,2,0),"-") -> G&A expenses | Z38: =IFERROR(VLOOKUP(A38,catalogo!$E:$G,3,0),"-") -> PO1774. Importación material TORQ para IMESA | AC38: =IFERROR(VLOOKUP(A38,catalogo!$E:$H,4,0),"-") -> https://drive.google.com/drive/folders/1tBRPEiGyYMUgsvzRDRDhDGIf_ZAKNFA1?usp=sharing
A39: TRX1272 | B39: =IFERROR(VLOOKUP(J39,catalogo!$B$1:$C$75,2,0),"-") -> #4 | C39: 46057.417 | G39: 1216.2 | H39: 66.98 | I39: USD | J39: Daniel Autrique Echeveste | K39: TCOLV - Naughty Patt LAS VEGAS USA | L39: Tcolv Naughty Patt Las Vegas USA | M39: 975 | N39: physical | Y39: =IFERROR(VLOOKUP(A39,catalogo!$E:$G,2,0),"-") -> Sales | Z39: =IFERROR(VLOOKUP(A39,catalogo!$E:$G,3,0),"-") -> 0 | AC39: =IFERROR(VLOOKUP(A39,catalogo!$E:$H,4,0),"-") -> .
A40: TRX1271 | B40: =IFERROR(VLOOKUP(J40,catalogo!$B$1:$C$75,2,0),"-") -> #4 | C40: 46057.417 | G40: 476.1 | H40: 26.22 | I40: USD | J40: Daniel Autrique Echeveste | K40: ZTRIP TAXI KANSAS CITY USA | L40: Ztrip Taxi Kansas City USA | M40: 975 | N40: physical | Y40: =IFERROR(VLOOKUP(A40,catalogo!$E:$G,2,0),"-") -> Sales | Z40: =IFERROR(VLOOKUP(A40,catalogo!$E:$G,3,0),"-") -> 0 | AC40: =IFERROR(VLOOKUP(A40,catalogo!$E:$H,4,0),"-") -> .
A41: TRX1270 | B41: =IFERROR(VLOOKUP(J41,catalogo!$B$1:$C$75,2,0),"-") -> #30 | C41: 46057.417 | G41: 907.88 | H41: 50 | I41: USD | J41: Manuel Ibarra Cebreros | K41: SONESTA SIMPLY SUITES LAS VEGAS USA | L41: Simply Vegas Real Estate | M41: 9904 | N41: physical | Y41: =IFERROR(VLOOKUP(A41,catalogo!$E:$H,2,0),"-") -> - | Z41: =IFERROR(VLOOKUP(A41,catalogo!$E:$G,3,0),"-") -> - | AC41: =IFERROR(VLOOKUP(A41,catalogo!$E:$H,4,0),"-") -> -
A42: TRX1269 | B42: =IFERROR(VLOOKUP(J42,catalogo!$B$1:$C$75,2,0),"-") -> #58 | C42: 46057.417 | G42: 181.94 | H42: 10.02 | I42: USD | J42: Jose Rosas Ortiz | K42: IN-N-OUT LINQ LAS VEGAS USA | L42: In N Out Linq Las Vegas USA | M42: 5576 | N42: physical | Y42: =IFERROR(VLOOKUP(A42,catalogo!$E:$H,2,0),"-") -> - | Z42: =IFERROR(VLOOKUP(A42,catalogo!$E:$G,3,0),"-") -> - | AC42: =IFERROR(VLOOKUP(A42,catalogo!$E:$H,4,0),"-") -> -
A43: TRX1268 | B43: =IFERROR(VLOOKUP(J43,catalogo!$B$1:$C$75,2,0),"-") -> #35 | C43: 46057.417 | G43: 635.34 | H43: 34.99 | I43: USD | J43: Termis | K43: BLOOMBERG* B38899628 NEW YORK USA | L43: Bloomberg | M43: 1771 | N43: physical | Y43: =IFERROR(VLOOKUP(A43,catalogo!$E:$H,2,0),"-") -> - | Z43: =IFERROR(VLOOKUP(A43,catalogo!$E:$G,3,0),"-") -> - | AC43: =IFERROR(VLOOKUP(A43,catalogo!$E:$H,4,0),"-") -> -
A44: TRX1267 | B44: =IFERROR(VLOOKUP(J44,catalogo!$B$1:$C$75,2,0),"-") -> #52 | C44: 46057.417 | G44: 1051.87 | H44: 57.93 | I44: USD | J44: Tommaso Rivetti Vinea | K44: TST* ADAIR DOWNTOWN HOUSTON USA | L44: Adair Downtown Houston USA | M44: 6137 | N44: physical | Y44: =IFERROR(VLOOKUP(A44,catalogo!$E:$H,2,0),"-") -> - | Z44: =IFERROR(VLOOKUP(A44,catalogo!$E:$G,3,0),"-") -> - | AC44: =IFERROR(VLOOKUP(A44,catalogo!$E:$H,4,0),"-") -> -
A45: TRX1266 | B45: =IFERROR(VLOOKUP(J45,catalogo!$B$1:$C$75,2,0),"-") -> #52 | C45: 46057.417 | G45: 520.04 | H45: 28.64 | I45: USD | J45: Tommaso Rivetti Vinea | K45: UBER * EATS PENDING SAN FRANCISCO USA | L45: Uber Eats | M45: 6137 | N45: physical | Y45: =IFERROR(VLOOKUP(A45,catalogo!$E:$G,2,0),"-") -> - | Z45: =IFERROR(VLOOKUP(A45,catalogo!$E:$G,3,0),"-") -> - | AC45: =IFERROR(VLOOKUP(A45,catalogo!$E:$H,4,0),"-") -> -
A46: TRX1265 | B46: =IFERROR(VLOOKUP(J46,catalogo!$B$1:$C$75,2,0),"-") -> #58 | C46: 46057.417 | G46: 273.27 | H46: 15.05 | I46: USD | J46: Jose Rosas Ortiz | K46: DOLLAR-GENERAL MKT #12 LAS VEGAS USA | L46: Dollar General | M46: 5576 | N46: physical | Y46: =IFERROR(VLOOKUP(A46,catalogo!$E:$H,2,0),"-") -> Sales | Z46: =IFERROR(VLOOKUP(A46,catalogo!$E:$G,3,0),"-") -> Marketing | AC46: =IFERROR(VLOOKUP(A46,catalogo!$E:$H,4,0),"-") -> 0
A47: TRX1264 | B47: =IFERROR(VLOOKUP(J47,catalogo!$B$1:$C$75,2,0),"-") -> #58 | C47: 46057.417 | G47: 604.1 | H47: 33.27 | I47: USD | J47: Jose Rosas Ortiz | K47: LAS VEGAS CONVENTION C LAS VEGAS USA | L47: Las Vegas Convention C Las Vegas USA | M47: 5576 | N47: physical | Y47: =IFERROR(VLOOKUP(A47,catalogo!$E:$H,2,0),"-") -> - | Z47: =IFERROR(VLOOKUP(A47,catalogo!$E:$G,3,0),"-") -> - | AC47: =IFERROR(VLOOKUP(A47,catalogo!$E:$H,4,0),"-") -> -
A48: TRX1263 | B48: =IFERROR(VLOOKUP(J48,catalogo!$B$1:$C$75,2,0),"-") -> #58 | C48: 46057.417 | G48: 389.66 | H48: 21.46 | I48: USD | J48: Jose Rosas Ortiz | K48: LAS VEGAS CONVENTION C LAS VEGAS USA | L48: Las Vegas Convention C Las Vegas USA | M48: 5576 | N48: physical | Y48: =IFERROR(VLOOKUP(A48,catalogo!$E:$G,2,0),"-") -> - | Z48: =IFERROR(VLOOKUP(A48,catalogo!$E:$G,3,0),"-") -> - | AC48: =IFERROR(VLOOKUP(A48,catalogo!$E:$H,4,0),"-") -> -
A49: TRX1262 | B49: =IFERROR(VLOOKUP(J49,catalogo!$B$1:$C$75,2,0),"-") -> #26 | C49: 46057.417 | G49: 126 | H49: 126 | I49: MXN | J49: Karen Alexandra Ballesteros Contreras | K49: Didi Mexico CAUHTEMOC MEX | L49: Didi Mexico Cauhtemoc Mex | M49: 552568XXXXXX3592 | N49: virtual
A50: TRX1261 | B50: =IFERROR(VLOOKUP(J50,catalogo!$B$1:$C$75,2,0),"-") -> - | C50: 46057.417 | G50: 549.98 | H50: 549.98 | I50: MXN | J50: Jose Luis Franco Vaquero | K50: UBER * PENDING CMX MEX | L50: Uber | M50: 552568XXXXXX0567 | N50: virtual | Y50: =IFERROR(VLOOKUP(A50,catalogo!$E:$G,2,0),"-") -> - | Z50: =IFERROR(VLOOKUP(A50,catalogo!$E:$G,3,0),"-") -> - | AC50: =IFERROR(VLOOKUP(A50,catalogo!$E:$H,4,0),"-") -> -
A51: TRX1260 | B51: =IFERROR(VLOOKUP(J51,catalogo!$B$1:$C$75,2,0),"-") -> - | C51: 46058.417 | G51: 500 | H51: 500 | I51: MXN | J51: Cindy Aguirre | K51: GAS COGA LOM CHA MIT 2 CIUDAD DE MEX MEX | L51: Gas Coga Lom Cha Mit 2 Ciudad De Mex Mex | M51: 2409 | N51: physical | Y51: =IFERROR(VLOOKUP(A51,catalogo!$E:$G,2,0),"-") -> - | Z51: =IFERROR(VLOOKUP(A51,catalogo!$E:$G,3,0),"-") -> - | AC51: =IFERROR(VLOOKUP(A51,catalogo!$E:$H,4,0),"-") -> -
A52: TRX1259 | B52: =IFERROR(VLOOKUP(J52,catalogo!$B$1:$C$75,2,0),"-") -> #19 | C52: 46058.417 | G52: 99.96 | H52: 99.96 | I52: MXN | J52: Daniel Alejandro Castillo Rivera | K52: UBER * PENDING CMX MEX | L52: Uber | M52: 552568XXXXXX6185 | N52: virtual | Y52: =IFERROR(VLOOKUP(A52,catalogo!$E:$H,2,0),"-") -> Transaction cost | Z52: =IFERROR(VLOOKUP(A52,catalogo!$E:$G,3,0),"-") -> PO2023 SIB 99 min | AC52: =IFERROR(VLOOKUP(A52,catalogo!$E:$H,4,0),"-") -> -
A53: TRX1258 | B53: =IFERROR(VLOOKUP(J53,catalogo!$B$1:$C$75,2,0),"-") -> #26 | C53: 46058.417 | G53: 61.21 | H53: 61.21 | I53: MXN | J53: Karen Alexandra Ballesteros Contreras | K53: Didi Mexico CAUHTEMOC MEX | L53: Didi Mexico Cauhtemoc Mex | M53: 552568XXXXXX3592 | N53: virtual | Y53: =IFERROR(VLOOKUP(A53,catalogo!$E:$G,2,0),"-") -> Transaction cost | Z53: =IFERROR(VLOOKUP(A53,catalogo!$E:$G,3,0),"-") -> PO1953 ARTEVALLEDEBRAVO | AC53: =IFERROR(VLOOKUP(A53,catalogo!$E:$H,4,0),"-") -> -
A54: TRX1257 | B54: =IFERROR(VLOOKUP(J54,catalogo!$B$1:$C$75,2,0),"-") -> - | C54: 46058.417 | G54: 89.94 | H54: 89.94 | I54: MXN | J54: Naomi Gonzalez | K54: UBER * PENDING CMX MEX | L54: Uber | M54: 552568XXXXXX3818 | N54: virtual | Y54: =IFERROR(VLOOKUP(A54,catalogo!$E:$G,2,0),"-") -> Transaction cost | Z54: =IFERROR(VLOOKUP(A54,catalogo!$E:$G,3,0),"-") -> PO1953 ARTEVALLEDEBRAVO | AC54: =IFERROR(VLOOKUP(A54,catalogo!$E:$H,4,0),"-") -> -
A55: TRX1256 | B55: =IFERROR(VLOOKUP(J55,catalogo!$B$1:$C$75,2,0),"-") -> #56 | C55: 46058.417 | G55: 280 | H55: 280 | I55: MXN | J55: Carlos Ivan Gonzalez Merino | K55: ADO SUC AEROPUERTO VERACRUZ VER MEX | L55: Ado Suc Aeropuerto Veracruz Ver Mex | M55: 8949 | N55: physical | Y55: =IFERROR(VLOOKUP(A55,catalogo!$E:$H,2,0),"-") -> - | Z55: =IFERROR(VLOOKUP(A55,catalogo!$E:$G,3,0),"-") -> - | AC55: =IFERROR(VLOOKUP(A55,catalogo!$E:$H,4,0),"-") -> -
A56: TRX1255 | B56: =IFERROR(VLOOKUP(J56,catalogo!$B$1:$C$75,2,0),"-") -> #19 | C56: 46058.417 | G56: 90.25 | H56: 90.25 | I56: MXN | J56: Daniel Alejandro Castillo Rivera | K56: UBER *TRIP HELP.UBER.C CMX MEX | L56: Uber | M56: 552568XXXXXX6185 | N56: virtual | Y56: =IFERROR(VLOOKUP(A56,catalogo!$E:$H,2,0),"-") -> Transaction cost | Z56: =IFERROR(VLOOKUP(A56,catalogo!$E:$G,3,0),"-") -> PO2023 SIB 99 min | AC56: =IFERROR(VLOOKUP(A56,catalogo!$E:$H,4,0),"-") -> -
A57: TRX1254 | B57: =IFERROR(VLOOKUP(J57,catalogo!$B$1:$C$75,2,0),"-") -> #74 | C57: 46058.417 | G57: 59.94 | H57: 59.94 | I57: MXN | J57: Julio Cesar Guemes Reynoso | K57: UBER * PENDING CMX MEX | L57: Uber | M57: 5481 | N57: physical | Y57: =IFERROR(VLOOKUP(A57,catalogo!$E:$H,2,0),"-") -> - | Z57: =IFERROR(VLOOKUP(A57,catalogo!$E:$G,3,0),"-") -> - | AC57: =IFERROR(VLOOKUP(A57,catalogo!$E:$H,4,0),"-") -> -
A58: TRX1253 | B58: =IFERROR(VLOOKUP(J58,catalogo!$B$1:$C$75,2,0),"-") -> #74 | C58: 46058.417 | G58: 70.81 | H58: 70.81 | I58: MXN | J58: Julio Cesar Guemes Reynoso | K58: UBER *TRIP HELP.UBER.C CMX MEX | L58: Uber | M58: 5481 | N58: physical | Y58: =IFERROR(VLOOKUP(A58,catalogo!$E:$H,2,0),"-") -> - | Z58: =IFERROR(VLOOKUP(A58,catalogo!$E:$G,3,0),"-") -> - | AC58: =IFERROR(VLOOKUP(A58,catalogo!$E:$H,4,0),"-") -> -
A59: TRX1252 | B59: =IFERROR(VLOOKUP(J59,catalogo!$B$1:$C$75,2,0),"-") -> #28 | C59: 46058.417 | G59: 79.96 | H59: 79.96 | I59: MXN | J59: Fernando Villalobos Lara | K59: UBER * PENDING CMX MEX | L59: Uber | M59: 552568XXXXXX7421 | N59: virtual | Y59: =IFERROR(VLOOKUP(A59,catalogo!$E:$H,2,0),"-") -> - | Z59: =IFERROR(VLOOKUP(A59,catalogo!$E:$G,3,0),"-") -> - | AC59: =IFERROR(VLOOKUP(A59,catalogo!$E:$H,4,0),"-") -> -
A60: TRX1251 | B60: =IFERROR(VLOOKUP(J60,catalogo!$B$1:$C$75,2,0),"-") -> #8 | C60: 46058.417 | G60: 489.95 | H60: 489.95 | I60: MXN | J60: Jose Ignacio Martinez Flemate | K60: UBER *TRIP HELP.UBER.C CMX MEX | L60: Uber | M60: 16 | N60: physical | Y60: =IFERROR(VLOOKUP(A60,catalogo!$E:$H,2,0),"-") -> Office expenses | Z60: =IFERROR(VLOOKUP(A60,catalogo!$E:$G,3,0),"-") -> Botiquin | AC60: =IFERROR(VLOOKUP(A60,catalogo!$E:$H,4,0),"-") -> .
A61: TRX1250 | B61: =IFERROR(VLOOKUP(J61,catalogo!$B$1:$C$75,2,0),"-") -> #74 | C61: 46058.417 | G61: 69.95 | H61: 69.95 | I61: MXN | J61: Julio Cesar Guemes Reynoso | K61: UBER * PENDING CMX MEX | L61: Uber | M61: 5481 | N61: physical | Y61: =IFERROR(VLOOKUP(A61,catalogo!$E:$G,2,0),"-") -> - | Z61: =IFERROR(VLOOKUP(A61,catalogo!$E:$G,3,0),"-") -> - | AC61: =IFERROR(VLOOKUP(A61,catalogo!$E:$H,4,0),"-") -> -
A62: TRX1249 | B62: =IFERROR(VLOOKUP(J62,catalogo!$B$1:$C$75,2,0),"-") -> #56 | C62: 46058.417 | G62: 276 | H62: 276 | I62: MXN | J62: Carlos Ivan Gonzalez Merino | K62: Starbucks CMX MEX | L62: Starbucks | M62: 8949 | N62: physical | Y62: =IFERROR(VLOOKUP(A62,catalogo!$E:$G,2,0),"-") -> - | Z62: =IFERROR(VLOOKUP(A62,catalogo!$E:$G,3,0),"-") -> - | AC62: =IFERROR(VLOOKUP(A62,catalogo!$E:$H,4,0),"-") -> -
A63: TRX1248 | B63: =IFERROR(VLOOKUP(J63,catalogo!$B$1:$C$75,2,0),"-") -> #14 | C63: 46058.417 | G63: 10 | H63: 10 | I63: MXN | J63: Patricio Servitje Azcarraga | K63: UBER *TRIP HELP.UBER.C CMX MEX | L63: Uber | M63: 7350 | N63: physical | Y63: =IFERROR(VLOOKUP(A63,catalogo!$E:$H,2,0),"-") -> 0 | Z63: =IFERROR(VLOOKUP(A63,catalogo!$E:$G,3,0),"-") -> 0 | AC63: =IFERROR(VLOOKUP(A63,catalogo!$E:$H,4,0),"-") -> .
A64: TRX1247 | B64: =IFERROR(VLOOKUP(J64,catalogo!$B$1:$C$75,2,0),"-") -> #55 | C64: 46058.417 | G64: 147.93 | H64: 147.93 | I64: MXN | J64: Gerardo Madrid | K64: UBER *TRIP HELP.UBER.C CMX MEX | L64: Uber | M64: 3013 | N64: physical | Y64: =IFERROR(VLOOKUP(A64,catalogo!$E:$G,2,0),"-") -> - | Z64: =IFERROR(VLOOKUP(A64,catalogo!$E:$G,3,0),"-") -> - | AC64: =IFERROR(VLOOKUP(A64,catalogo!$E:$H,4,0),"-") -> -
A65: TRX1246 | B65: =IFERROR(VLOOKUP(J65,catalogo!$B$1:$C$75,2,0),"-") -> #2 | C65: 46058.417 | G65: 15105.29 | H65: 15105.29 | I65: MXN | J65: Cesar Gonzales | K65: PAYU *GOOGLE CLOUD MIGUEL HIDALG MEX | L65: Google Cloud | M65: 552568XXXXXX7852 | N65: virtual
A66: TRX1245 | B66: =IFERROR(VLOOKUP(J66,catalogo!$B$1:$C$75,2,0),"-") -> #74 | C66: 46058.417 | G66: 459.94 | H66: 459.94 | I66: MXN | J66: Julio Cesar Guemes Reynoso | K66: UBER * PENDING CMX MEX | L66: Uber | M66: 5481 | N66: physical | Y66: =IFERROR(VLOOKUP(A66,catalogo!$E:$G,2,0),"-") -> Tech&Product | Z66: =IFERROR(VLOOKUP(A66,catalogo!$E:$G,3,0),"-") -> 0 | AC66: =IFERROR(VLOOKUP(A66,catalogo!$E:$H,4,0),"-") -> .
A67: TRX1244 | B67: =IFERROR(VLOOKUP(J67,catalogo!$B$1:$C$75,2,0),"-") -> #9 | C67: 46058.417 | G67: 700 | H67: 700 | I67: MXN | J67: Jose Maria Garcia Hernandez | K67: GASOLINERIA ES 06254 HUIXQUILUCAN MEX | L67: Gasolineria Es Huixquilucan Mex | M67: 1026 | N67: physical | Y67: =IFERROR(VLOOKUP(A67,catalogo!$E:$H,2,0),"-") -> Sales | Z67: =IFERROR(VLOOKUP(A67,catalogo!$E:$G,3,0),"-") -> Vuelo Mty Grupo GI | AC67: =IFERROR(VLOOKUP(A67,catalogo!$E:$H,4,0),"-") -> .
A68: TRX1243 | B68: =IFERROR(VLOOKUP(J68,catalogo!$B$1:$C$75,2,0),"-") -> #74 | C68: 46058.417 | G68: 462 | H68: 462 | I68: MXN | J68: Julio Cesar Guemes Reynoso | K68: CASA BENELL SUE TB APODACA NL MEX | L68: Casa Benell Sue Tb Apodaca Nl Mex | M68: 5481 | N68: physical | Y68: =IFERROR(VLOOKUP(A68,catalogo!$E:$H,2,0),"-") -> - | Z68: =IFERROR(VLOOKUP(A68,catalogo!$E:$G,3,0),"-") -> - | AC68: =IFERROR(VLOOKUP(A68,catalogo!$E:$H,4,0),"-") -> -
A69: TRX1242 | B69: =IFERROR(VLOOKUP(J69,catalogo!$B$1:$C$75,2,0),"-") -> #2 | C69: 46058.417 | G69: 957.38 | H69: 957.38 | I69: MXN | J69: Cesar Gonzales | K69: PAYU *GOOGLE CLOUD MIGUEL HIDALG MEX | L69: Google Cloud | M69: 552568XXXXXX7852 | N69: virtual | Y69: =IFERROR(VLOOKUP(A69,catalogo!$E:$H,2,0),"-") -> Tech&Product | Z69: =IFERROR(VLOOKUP(A69,catalogo!$E:$G,3,0),"-") -> 0 | AC69: =IFERROR(VLOOKUP(A69,catalogo!$E:$H,4,0),"-") -> .
A70: TRX1241 | B70: =IFERROR(VLOOKUP(J70,catalogo!$B$1:$C$75,2,0),"-") -> #35 | C70: 46058.417 | G70: 1825.31 | H70: 1825.31 | I70: MXN | J70: Termis | K70: PAYU *GOOGLE CLOUD MIGUEL HIDALG MEX | L70: Google Cloud | M70: 1771 | N70: physical | Y70: =IFERROR(VLOOKUP(A70,catalogo!$E:$H,2,0),"-") -> - | Z70: =IFERROR(VLOOKUP(A70,catalogo!$E:$G,3,0),"-") -> - | AC70: =IFERROR(VLOOKUP(A70,catalogo!$E:$H,4,0),"-") -> -
A71: TRX1240 | B71: =IFERROR(VLOOKUP(J71,catalogo!$B$1:$C$75,2,0),"-") -> - | C71: 46058.417 | G71: 473 | H71: 473 | I71: MXN | J71: Jose Luis Franco Vaquero | K71: LOMA LINDA III T1 3 CIUDAD DE MEX MEX | L71: Loma Linda Iii T1 3 Ciudad De Mex Mex | M71: 6130 | N71: physical | Y71: =IFERROR(VLOOKUP(A71,catalogo!$E:$H,2,0),"-") -> - | Z71: =IFERROR(VLOOKUP(A71,catalogo!$E:$G,3,0),"-") -> - | AC71: =IFERROR(VLOOKUP(A71,catalogo!$E:$H,4,0),"-") -> -
A72: TRX1239 | B72: =IFERROR(VLOOKUP(J72,catalogo!$B$1:$C$75,2,0),"-") -> #3 | C72: 46058.417 | G72: 1130 | H72: 1130 | I72: MXN | J72: Cesar Uriel Romo Trillo | K72: HAMMER STRONG CIUDAD DE MEX MEX | L72: Hammer Strong Ciudad De Mex Mex | M72: 8657 | N72: physical | Y72: =IFERROR(VLOOKUP(A72,catalogo!$E:$H,2,0),"-") -> Sales | Z72: =IFERROR(VLOOKUP(A72,catalogo!$E:$G,3,0),"-") -> Compra de Pulidora y discos para obra Grajales Robles PO1129 | AC72: =IFERROR(VLOOKUP(A72,catalogo!$E:$H,4,0),"-") -> TICKET
A73: TRX1238 | B73: =IFERROR(VLOOKUP(J73,catalogo!$B$1:$C$75,2,0),"-") -> #26 | C73: 46058.417 | G73: 520 | H73: 520 | I73: MXN | J73: Karen Alexandra Ballesteros Contreras | K73: MERCADOPAGO *EBANOCAF Benito jurez MEX | L73: Mercadopago | M73: 8061 | N73: physical | Y73: =IFERROR(VLOOKUP(A73,catalogo!$E:$H,2,0),"-") -> - | Z73: =IFERROR(VLOOKUP(A73,catalogo!$E:$G,3,0),"-") -> - | AC73: =IFERROR(VLOOKUP(A73,catalogo!$E:$H,4,0),"-") -> -
A74: TRX1237 | B74: =IFERROR(VLOOKUP(J74,catalogo!$B$1:$C$75,2,0),"-") -> #9 | C74: 46058.417 | G74: 210 | H74: 210 | I74: MXN | J74: Jose Maria Garcia Hernandez | K74: MERCADOPAGO *PASE MIGUEL HIDALG MEX | L74: Mercadopago | M74: 1026 | N74: physical | Y74: =IFERROR(VLOOKUP(A74,catalogo!$E:$H,2,0),"-") -> Sales | Z74: =IFERROR(VLOOKUP(A74,catalogo!$E:$G,3,0),"-") -> Comida 2KDC | AC74: =IFERROR(VLOOKUP(A74,catalogo!$E:$H,4,0),"-") -> .
A75: TRX1236 | B75: =IFERROR(VLOOKUP(J75,catalogo!$B$1:$C$75,2,0),"-") -> - | C75: 46058.417 | G75: 755.7 | H75: 755.7 | I75: MXN | J75: Jose Luis Ramirez Gonzalez | K75: GAS DUERO TOLUCA EM MEX | L75: Gas Duero Toluca Em Mex | M75: 3340 | N75: physical | Y75: =IFERROR(VLOOKUP(A75,catalogo!$E:$G,2,0),"-") -> - | Z75: =IFERROR(VLOOKUP(A75,catalogo!$E:$G,3,0),"-") -> - | AC75: =IFERROR(VLOOKUP(A75,catalogo!$E:$H,4,0),"-") -> -
A76: TRX1235 | B76: =IFERROR(VLOOKUP(J76,catalogo!$B$1:$C$75,2,0),"-") -> - | C76: 46058.417 | G76: 171 | H76: 171 | I76: MXN | J76: TONANCY ISIDORO PENA | K76: MERCADOPAGO *EBANOCAF Benito jurez MEX | L76: Mercadopago | M76: 7984 | N76: physical | Y76: =IFERROR(VLOOKUP(A76,catalogo!$E:$G,2,0),"-") -> - | Z76: =IFERROR(VLOOKUP(A76,catalogo!$E:$G,3,0),"-") -> - | AC76: =IFERROR(VLOOKUP(A76,catalogo!$E:$H,4,0),"-") -> -
A77: TRX1234 | B77: =IFERROR(VLOOKUP(J77,catalogo!$B$1:$C$75,2,0),"-") -> - | C77: 46058.417 | G77: 600 | H77: 600 | I77: MXN | J77: TONANCY ISIDORO PENA | K77: HF LERMA EM MEX | L77: Hf Lerma Em Mex | M77: 7984 | N77: physical | Y77: =IFERROR(VLOOKUP(A77,catalogo!$E:$H,2,0),"-") -> Transaction cost | Z77: =IFERROR(VLOOKUP(A77,catalogo!$E:$G,3,0),"-") -> Recarga de tag | AC77: =IFERROR(VLOOKUP(A77,catalogo!$E:$H,4,0),"-") -> 0
A78: TRX1233 | B78: =IFERROR(VLOOKUP(J78,catalogo!$B$1:$C$75,2,0),"-") -> #16 | C78: 46058.417 | G78: 6615.11 | H78: 6615.11 | I78: MXN | J78: Rogelio Gamez | K78: PAYU *GOOGLE ADS MIGUEL HIDALG MEX | L78: Google | M78: 552568XXXXXX0724 | N78: virtual | Y78: =IFERROR(VLOOKUP(A78,catalogo!$E:$H,2,0),"-") -> Sales | Z78: =IFERROR(VLOOKUP(A78,catalogo!$E:$G,3,0),"-") -> Marketing | AC78: =IFERROR(VLOOKUP(A78,catalogo!$E:$H,4,0),"-") -> 0
A79: TRX1232 | B79: =IFERROR(VLOOKUP(J79,catalogo!$B$1:$C$75,2,0),"-") -> - | C79: 46058.417 | G79: 1510 | H79: 1510 | I79: MXN | J79: Jose Luis Ramirez Gonzalez | K79: MERCADOPAGO *PASE MIGUEL HIDALG MEX | L79: Mercadopago | M79: 3340 | N79: physical | Y79: =IFERROR(VLOOKUP(A79,catalogo!$E:$H,2,0),"-") -> - | Z79: =IFERROR(VLOOKUP(A79,catalogo!$E:$G,3,0),"-") -> - | AC79: =IFERROR(VLOOKUP(A79,catalogo!$E:$H,4,0),"-") -> -
A80: TRX1231 | B80: =IFERROR(VLOOKUP(J80,catalogo!$B$1:$C$75,2,0),"-") -> #26 | C80: 46058.417 | G80: 385 | H80: 385 | I80: MXN | J80: Karen Alexandra Ballesteros Contreras | K80: D LOCAL*DIDI RIDES CIUDAD DE MEX MEX | L80: Didi Chuxing | M80: 552568XXXXXX3592 | N80: virtual | Y80: =IFERROR(VLOOKUP(A80,catalogo!$E:$H,2,0),"-") -> - | Z80: =IFERROR(VLOOKUP(A80,catalogo!$E:$G,3,0),"-") -> - | AC80: =IFERROR(VLOOKUP(A80,catalogo!$E:$H,4,0),"-") -> -
A81: TRX1230 | B81: =IFERROR(VLOOKUP(J81,catalogo!$B$1:$C$75,2,0),"-") -> - | C81: 46058.417 | G81: 1377.87 | H81: 1377.87 | I81: MXN | J81: Jose Luis Franco Vaquero | K81: MERCADOPAGO *GASOLINA Tlalnepantla MEX | L81: Mercadopago | M81: 552568XXXXXX0567 | N81: virtual | Y81: =IFERROR(VLOOKUP(A81,catalogo!$E:$H,2,0),"-") -> - | Z81: =IFERROR(VLOOKUP(A81,catalogo!$E:$G,3,0),"-") -> - | AC81: =IFERROR(VLOOKUP(A81,catalogo!$E:$H,4,0),"-") -> -
A82: TRX1229 | B82: =IFERROR(VLOOKUP(J82,catalogo!$B$1:$C$75,2,0),"-") -> #74 | C82: 46058.417 | G82: 4468.56 | H82: 4468.56 | I82: MXN | J82: Julio Cesar Guemes Reynoso | K82: HOTELES COM CIUDAD DE MEX MEX | L82: Hoteles Com Ciudad De Mex Mex | M82: 5481 | N82: physical | Y82: =IFERROR(VLOOKUP(A82,catalogo!$E:$G,2,0),"-") -> - | Z82: =IFERROR(VLOOKUP(A82,catalogo!$E:$G,3,0),"-") -> - | AC82: =IFERROR(VLOOKUP(A82,catalogo!$E:$H,4,0),"-") -> -
A83: TRX1228 | B83: =IFERROR(VLOOKUP(J83,catalogo!$B$1:$C$75,2,0),"-") -> - | C83: 46058.417 | G83: 80 | H83: 80 | I83: MXN | J83: Manuel Caldera Urcuyo | K83: G68 THE MARKET APODACA NL MEX | L83: G68 The Market Apodaca Nl Mex | M83: 6747 | N83: physical | Y83: =IFERROR(VLOOKUP(A83,catalogo!$E:$G,2,0),"-") -> 0 | Z83: =IFERROR(VLOOKUP(A83,catalogo!$E:$G,3,0),"-") -> 0 | AC83: =IFERROR(VLOOKUP(A83,catalogo!$E:$H,4,0),"-") -> .
A84: TRX1227 | B84: =IFERROR(VLOOKUP(J84,catalogo!$B$1:$C$75,2,0),"-") -> #74 | C84: 46058.417 | G84: 5423.7 | H84: 5423.7 | I84: MXN | J84: Julio Cesar Guemes Reynoso | K84: VIVA AEROBUS CIB APODACA MEX | L84: Viva Aerobus Cib Apodaca Mex | M84: 5481 | N84: physical | Y84: =IFERROR(VLOOKUP(A84,catalogo!$E:$H,2,0),"-") -> Transaction cost | Z84: =IFERROR(VLOOKUP(A84,catalogo!$E:$G,3,0),"-") -> calibracion rugosimetro CC calidad | AC84: =IFERROR(VLOOKUP(A84,catalogo!$E:$H,4,0),"-") -> -
A85: TRX1226 | B85: =IFERROR(VLOOKUP(J85,catalogo!$B$1:$C$75,2,0),"-") -> - | C85: 46058.417 | G85: 355 | H85: 355 | I85: MXN | J85: Daniel Caraveo | K85: RITUAL CAFE CANCUN QROO MEX | L85: Ritual Cafe Cancun Qroo Mex | M85: XXXXXXXXXXXX7525 | N85: physical | Y85: =IFERROR(VLOOKUP(A85,catalogo!$E:$G,2,0),"-") -> - | Z85: =IFERROR(VLOOKUP(A85,catalogo!$E:$G,3,0),"-") -> - | AC85: =IFERROR(VLOOKUP(A85,catalogo!$E:$H,4,0),"-") -> -
A86: TRX1225 | B86: =IFERROR(VLOOKUP(J86,catalogo!$B$1:$C$75,2,0),"-") -> - | C86: 46058.417 | G86: 178 | H86: 178 | I86: MXN | J86: Daniel Caraveo | K86: LAVANDERIA ALBORADA CANCUN QROO MEX | L86: Lavanderia Alborada Cancun Qroo Mex | M86: XXXXXXXXXXXX7525 | N86: physical | Y86: =IFERROR(VLOOKUP(A86,catalogo!$E:$H,2,0),"-") -> - | Z86: =IFERROR(VLOOKUP(A86,catalogo!$E:$G,3,0),"-") -> - | AC86: =IFERROR(VLOOKUP(A86,catalogo!$E:$H,4,0),"-") -> -
A87: TRX1224 | B87: =IFERROR(VLOOKUP(J87,catalogo!$B$1:$C$75,2,0),"-") -> - | C87: 46058.417 | G87: 110 | H87: 110 | I87: MXN | J87: TONANCY ISIDORO PENA | K87: CONEKTA*MIBAIT DF MEX | L87: Conekta Mibait Df Mex | M87: 7984 | N87: physical | Y87: =IFERROR(VLOOKUP(A87,catalogo!$E:$G,2,0),"-") -> - | Z87: =IFERROR(VLOOKUP(A87,catalogo!$E:$G,3,0),"-") -> - | AC87: =IFERROR(VLOOKUP(A87,catalogo!$E:$H,4,0),"-") -> -
A88: TRX1223 | B88: =IFERROR(VLOOKUP(J88,catalogo!$B$1:$C$75,2,0),"-") -> #26 | C88: 46058.417 | G88: 126 | H88: 126 | I88: MXN | J88: Karen Alexandra Ballesteros Contreras | K88: DLO*DIDI RIDES MEXICO MEX | L88: Didi Chuxing | M88: 552568XXXXXX3592 | N88: virtual | Y88: =IFERROR(VLOOKUP(A88,catalogo!$E:$H,2,0),"-") -> - | Z88: =IFERROR(VLOOKUP(A88,catalogo!$E:$G,3,0),"-") -> - | AC88: =IFERROR(VLOOKUP(A88,catalogo!$E:$H,4,0),"-") -> -
A89: TRX1222 | B89: =IFERROR(VLOOKUP(J89,catalogo!$B$1:$C$75,2,0),"-") -> #6 | C89: 46058.417 | G89: 1149 | H89: 1149 | I89: MXN | J89: Fernando Sanchez Toledano | K89: AVIS WEB MXN MERIDA YUC MEX | L89: Avis | M89: 552568XXXXXX9303 | N89: virtual | Y89: =IFERROR(VLOOKUP(A89,catalogo!$E:$H,2,0),"-") -> 0 | Z89: =IFERROR(VLOOKUP(A89,catalogo!$E:$G,3,0),"-") -> 0 | AC89: =IFERROR(VLOOKUP(A89,catalogo!$E:$H,4,0),"-") -> .
A90: TRX1221 | B90: =IFERROR(VLOOKUP(J90,catalogo!$B$1:$C$75,2,0),"-") -> #26 | C90: 46058.417 | G90: 410.08 | H90: 410.08 | I90: MXN | J90: Karen Alexandra Ballesteros Contreras | K90: VIVAAEROBUS MOBILE APODACA NL MEX | L90: Vivaaerobus | M90: 552568XXXXXX3592 | N90: virtual | Y90: =IFERROR(VLOOKUP(A90,catalogo!$E:$H,2,0),"-") -> - | Z90: =IFERROR(VLOOKUP(A90,catalogo!$E:$G,3,0),"-") -> - | AC90: =IFERROR(VLOOKUP(A90,catalogo!$E:$H,4,0),"-") -> -
A91: TRX1220 | B91: =IFERROR(VLOOKUP(J91,catalogo!$B$1:$C$75,2,0),"-") -> - | C91: 46058.417 | G91: 446 | H91: 446 | I91: MXN | J91: Naomi Gonzalez | K91: CLIP MX*REST SHAKA 808 MIGUEL HIDALG MEX | L91: Clip Mx Rest Shaka 808 Miguel Hidalg Mex | M91: 6448 | N91: physical | Y91: =IFERROR(VLOOKUP(A91,catalogo!$E:$H,2,0),"-") -> - | Z91: =IFERROR(VLOOKUP(A91,catalogo!$E:$G,3,0),"-") -> - | AC91: =IFERROR(VLOOKUP(A91,catalogo!$E:$H,4,0),"-") -> -
A92: TRX1219 | B92: =IFERROR(VLOOKUP(J92,catalogo!$B$1:$C$75,2,0),"-") -> #5 | C92: 46058.417 | G92: 70 | H92: 70 | I92: MXN | J92: Fernanda Sanchez Ruiz | K92: DLO*UBER RIDE CIUDAD DE MEX MEX | L92: Uber | M92: 3283 | N92: physical | Y92: =IFERROR(VLOOKUP(A92,catalogo!$E:$H,2,0),"-") -> Office expenses | Z92: =IFERROR(VLOOKUP(A92,catalogo!$E:$G,3,0),"-") -> Snacks para la oficina | AC92: =IFERROR(VLOOKUP(A92,catalogo!$E:$H,4,0),"-") -> .
A93: TRX1218 | B93: =IFERROR(VLOOKUP(J93,catalogo!$B$1:$C$75,2,0),"-") -> #64 | C93: 46058.417 | G93: 380 | H93: 380 | I93: MXN | J93: Jorge Rojas | K93: CLIP MX*SUPER BARRA LI TIJUANA MEX | L93: Super Mex | M93: 7142 | N93: physical | Y93: =IFERROR(VLOOKUP(A93,catalogo!$E:$H,2,0),"-") -> - | Z93: =IFERROR(VLOOKUP(A93,catalogo!$E:$G,3,0),"-") -> - | AC93: =IFERROR(VLOOKUP(A93,catalogo!$E:$H,4,0),"-") -> -
A94: TRX1217 | B94: =IFERROR(VLOOKUP(J94,catalogo!$B$1:$C$75,2,0),"-") -> - | C94: 46058.417 | G94: 61.2 | H94: 61.2 | I94: MXN | J94: Jose Luis Franco Vaquero | K94: REA AUTOPISTA GPE CADEREYTA JIM MEX | L94: Rea Autopista Gpe Cadereyta Jim Mex | M94: 6130 | N94: physical | Y94: =IFERROR(VLOOKUP(A94,catalogo!$E:$G,2,0),"-") -> - | Z94: =IFERROR(VLOOKUP(A94,catalogo!$E:$G,3,0),"-") -> - | AC94: =IFERROR(VLOOKUP(A94,catalogo!$E:$H,4,0),"-") -> -
A95: TRX1216 | B95: =IFERROR(VLOOKUP(J95,catalogo!$B$1:$C$75,2,0),"-") -> - | C95: 46058.417 | G95: 462 | H95: 462 | I95: MXN | J95: Jose Luis Franco Vaquero | K95: REST CAFE BARCELO SN PEDRO GARZ MEX | L95: Rest Cafe Barcelo Sn Pedro Garz Mex | M95: 6130 | N95: physical | Y95: =IFERROR(VLOOKUP(A95,catalogo!$E:$H,2,0),"-") -> - | Z95: =IFERROR(VLOOKUP(A95,catalogo!$E:$G,3,0),"-") -> - | AC95: =IFERROR(VLOOKUP(A95,catalogo!$E:$H,4,0),"-") -> -
A96: TRX1215 | B96: =IFERROR(VLOOKUP(J96,catalogo!$B$1:$C$75,2,0),"-") -> #64 | C96: 46058.417 | G96: 233.15 | H96: 233.15 | I96: MXN | J96: Jorge Rojas | K96: WALMART LOMAS STA FE TIJUANA BCN MEX | L96: Walmart | M96: 7142 | N96: physical | Y96: =IFERROR(VLOOKUP(A96,catalogo!$E:$G,2,0),"-") -> - | Z96: =IFERROR(VLOOKUP(A96,catalogo!$E:$G,3,0),"-") -> - | AC96: =IFERROR(VLOOKUP(A96,catalogo!$E:$H,4,0),"-") -> -
